{
  "fish": "マルイカ",
  "ship": "はら丸",
  "last_reviewed": "2026-07-03",
  "status": "point_model_marginal",
  "metrics": {
    "wmape_h0": 42.7,
    "bl2_wmape": 54.0,
    "oos_r": 0.663,
    "n_records": 92,
    "use_fallback": false,
    "kaiyu_promoted": false
  },
  "point_models": [
    {
      "name": "城ヶ島沖",
      "n": 53,
      "wmape_h0": 38.8,
      "bl2_wmape": 65.6,
      "oos_r": 0.756,
      "improvement_pt": 3.93
    }
  ],
  "best_point": {
    "name": "城ヶ島沖",
    "wmape_h0": 38.8,
    "improvement_pt": 3.93
  },
  "improvement_pt": 3.93,
  "history": [
    {
      "date": "2026-04-22",
      "action": "point_backtest_updated",
      "note": "best=城ヶ島沖 wmape=43.6% imp=4.86pt"
    },
    {
      "date": "2026-04-24",
      "action": "point_backtest_updated",
      "note": "best=城ヶ島沖 wmape=43.6% imp=2.01pt"
    },
    {
      "date": "2026-04-25",
      "action": "point_backtest_updated",
      "note": "best=城ヶ島沖 wmape=43.7% imp=1.87pt"
    },
    {
      "date": "2026-04-26",
      "action": "point_backtest_updated",
      "note": "best=城ヶ島沖 wmape=41.0% imp=0.44pt"
    },
    {
      "date": "2026-04-27",
      "action": "point_backtest_updated",
      "note": "best=城ヶ島沖 wmape=41.0% imp=0.44pt"
    },
    {
      "date": "2026-04-28",
      "action": "point_backtest_updated",
      "note": "best=城ヶ島沖 wmape=41.0% imp=1.46pt"
    },
    {
      "date": "2026-04-29",
      "action": "point_backtest_updated",
      "note": "best=城ヶ島沖 wmape=40.9% imp=1.48pt"
    },
    {
      "date": "2026-05-03",
      "action": "point_backtest_updated",
      "note": "best=城ヶ島沖 wmape=40.9% imp=1.48pt"
    },
    {
      "date": "2026-05-08",
      "action": "point_backtest_updated",
      "note": "best=城ヶ島沖 wmape=40.9% imp=1.81pt"
    },
    {
      "date": "2026-05-09",
      "action": "point_backtest_updated",
      "note": "best=城ヶ島沖 wmape=40.9% imp=2.12pt"
    },
    {
      "date": "2026-05-12",
      "action": "point_backtest_updated",
      "note": "best=城ヶ島沖 wmape=40.9% imp=2.12pt"
    },
    {
      "date": "2026-05-17",
      "action": "point_backtest_updated",
      "note": "best=城ヶ島沖 wmape=40.9% imp=0.5pt"
    },
    {
      "date": "2026-06-23",
      "action": "point_backtest_updated",
      "note": "best=城ヶ島沖 wmape=38.7% imp=3.84pt"
    },
    {
      "date": "2026-07-03",
      "action": "point_backtest_updated",
      "note": "best=城ヶ島沖 wmape=38.8% imp=3.93pt"
    }
  ]
}