[
  {
    "ship": "喜久丸",
    "area": "腰越港",
    "date": "2026/05/16",
    "trip_no": 1,
    "fish_raw": "アマダイ",
    "count_raw": "0～1匹",
    "size_raw": "24～30cm",
    "weight_raw": "",
    "tokki_raw": "メイン",
    "point_raw": "神奈川県 鎌倉市 腰越漁港",
    "kanso_raw": "ウィリーアマダイ五目 ターゲットのアマダイシロアマダイイトヨリ始め釣りガールの皆さんもゲストの良型アジサバのお土産はキープしてもらえて良かったです！ チャーター船 皆さん手返も良く良型アジサバアマダイイトヨリEtcと楽しんでもらえて帰港です！",
    "suion_raw": "19.7℃",
    "suishoku_raw": "",
    "color_raw": "",
    "source": "chowari/喜久丸",
    "tide_label": "大潮",
    "weather_text": "晴れ",
    "weather_detail": {
      "sunrise": "04:37",
      "sunset": "18:40",
      "moonrise": "03:36",
      "moonset": "18:12",
      "weather": "晴れ",
      "temp_high": "26℃",
      "temp_low": "17℃",
      "pressure": "1023.8hPa",
      "wind_dir": "東",
      "wind_speed": "1.2m/s",
      "wave_dir": "南南東",
      "wave_height": "0.2m/s",
      "water_temp": "19.7℃",
      "tide": "大潮",
      "moon_age": "28.6",
      "bi": "8.9"
    }
  },
  {
    "ship": "喜久丸",
    "area": "腰越港",
    "date": "2026/05/16",
    "trip_no": 1,
    "fish_raw": "イトヨリ",
    "count_raw": "0～2匹",
    "size_raw": "22～35cm",
    "weight_raw": "",
    "tokki_raw": "外道",
    "point_raw": "神奈川県 鎌倉市 腰越漁港",
    "kanso_raw": "ウィリーアマダイ五目 ターゲットのアマダイシロアマダイイトヨリ始め釣りガールの皆さんもゲストの良型アジサバのお土産はキープしてもらえて良かったです！ チャーター船 皆さん手返も良く良型アジサバアマダイイトヨリEtcと楽しんでもらえて帰港です！",
    "suion_raw": "19.7℃",
    "suishoku_raw": "",
    "color_raw": "",
    "source": "chowari/喜久丸",
    "tide_label": "大潮",
    "weather_text": "晴れ",
    "weather_detail": {
      "sunrise": "04:37",
      "sunset": "18:40",
      "moonrise": "03:36",
      "moonset": "18:12",
      "weather": "晴れ",
      "temp_high": "26℃",
      "temp_low": "17℃",
      "pressure": "1023.8hPa",
      "wind_dir": "東",
      "wind_speed": "1.2m/s",
      "wave_dir": "南南東",
      "wave_height": "0.2m/s",
      "water_temp": "19.7℃",
      "tide": "大潮",
      "moon_age": "28.6",
      "bi": "8.9"
    }
  },
  {
    "ship": "喜久丸",
    "area": "腰越港",
    "date": "2026/05/16",
    "trip_no": 1,
    "fish_raw": "アジ",
    "count_raw": "0～6匹",
    "size_raw": "25～38cm",
    "weight_raw": "",
    "tokki_raw": "外道",
    "point_raw": "神奈川県 鎌倉市 腰越漁港",
    "kanso_raw": "ウィリーアマダイ五目 ターゲットのアマダイシロアマダイイトヨリ始め釣りガールの皆さんもゲストの良型アジサバのお土産はキープしてもらえて良かったです！ チャーター船 皆さん手返も良く良型アジサバアマダイイトヨリEtcと楽しんでもらえて帰港です！",
    "suion_raw": "19.7℃",
    "suishoku_raw": "",
    "color_raw": "",
    "source": "chowari/喜久丸",
    "tide_label": "大潮",
    "weather_text": "晴れ",
    "weather_detail": {
      "sunrise": "04:37",
      "sunset": "18:40",
      "moonrise": "03:36",
      "moonset": "18:12",
      "weather": "晴れ",
      "temp_high": "26℃",
      "temp_low": "17℃",
      "pressure": "1023.8hPa",
      "wind_dir": "東",
      "wind_speed": "1.2m/s",
      "wave_dir": "南南東",
      "wave_height": "0.2m/s",
      "water_temp": "19.7℃",
      "tide": "大潮",
      "moon_age": "28.6",
      "bi": "8.9"
    }
  },
  {
    "ship": "喜久丸",
    "area": "腰越港",
    "date": "2026/05/16",
    "trip_no": 1,
    "fish_raw": "サバ",
    "count_raw": "0～5匹",
    "size_raw": "27～40cm",
    "weight_raw": "",
    "tokki_raw": "外道",
    "point_raw": "神奈川県 鎌倉市 腰越漁港",
    "kanso_raw": "ウィリーアマダイ五目 ターゲットのアマダイシロアマダイイトヨリ始め釣りガールの皆さんもゲストの良型アジサバのお土産はキープしてもらえて良かったです！ チャーター船 皆さん手返も良く良型アジサバアマダイイトヨリEtcと楽しんでもらえて帰港です！",
    "suion_raw": "19.7℃",
    "suishoku_raw": "",
    "color_raw": "",
    "source": "chowari/喜久丸",
    "tide_label": "大潮",
    "weather_text": "晴れ",
    "weather_detail": {
      "sunrise": "04:37",
      "sunset": "18:40",
      "moonrise": "03:36",
      "moonset": "18:12",
      "weather": "晴れ",
      "temp_high": "26℃",
      "temp_low": "17℃",
      "pressure": "1023.8hPa",
      "wind_dir": "東",
      "wind_speed": "1.2m/s",
      "wave_dir": "南南東",
      "wave_height": "0.2m/s",
      "water_temp": "19.7℃",
      "tide": "大潮",
      "moon_age": "28.6",
      "bi": "8.9"
    }
  },
  {
    "ship": "喜久丸",
    "area": "腰越港",
    "date": "2026/05/15",
    "trip_no": 1,
    "fish_raw": "アマダイ",
    "count_raw": "0～1匹",
    "size_raw": "28～30cm",
    "weight_raw": "",
    "tokki_raw": "メイン",
    "point_raw": "神奈川県 鎌倉市 腰越漁港",
    "kanso_raw": "ウィリーアマダイ五目 シロアマダイアマダイハナダイ他に良型アジサバと皆さんお土産",
    "suion_raw": "19.5℃",
    "suishoku_raw": "",
    "color_raw": "",
    "source": "chowari/喜久丸",
    "tide_label": "大潮",
    "weather_text": "晴れ",
    "weather_detail": {
      "sunrise": "04:38",
      "sunset": "18:39",
      "moonrise": "03:01",
      "moonset": "16:56",
      "weather": "晴れ",
      "temp_high": "25℃",
      "temp_low": "15℃",
      "pressure": "1023.1hPa",
      "wind_dir": "北東",
      "wind_speed": "2.9m/s",
      "wave_dir": "南南東",
      "wave_height": "0.3m/s",
      "water_temp": "19.5℃",
      "tide": "大潮",
      "moon_age": "27.6",
      "bi": "9.5"
    }
  },
  {
    "ship": "喜久丸",
    "area": "腰越港",
    "date": "2026/05/15",
    "trip_no": 1,
    "fish_raw": "アジ",
    "count_raw": "1～8匹",
    "size_raw": "23～40cm",
    "weight_raw": "",
    "tokki_raw": "外道",
    "point_raw": "神奈川県 鎌倉市 腰越漁港",
    "kanso_raw": "ウィリーアマダイ五目 シロアマダイアマダイハナダイ他に良型アジサバと皆さんお土産",
    "suion_raw": "19.5℃",
    "suishoku_raw": "",
    "color_raw": "",
    "source": "chowari/喜久丸",
    "tide_label": "大潮",
    "weather_text": "晴れ",
    "weather_detail": {
      "sunrise": "04:38",
      "sunset": "18:39",
      "moonrise": "03:01",
      "moonset": "16:56",
      "weather": "晴れ",
      "temp_high": "25℃",
      "temp_low": "15℃",
      "pressure": "1023.1hPa",
      "wind_dir": "北東",
      "wind_speed": "2.9m/s",
      "wave_dir": "南南東",
      "wave_height": "0.3m/s",
      "water_temp": "19.5℃",
      "tide": "大潮",
      "moon_age": "27.6",
      "bi": "9.5"
    }
  },
  {
    "ship": "喜久丸",
    "area": "腰越港",
    "date": "2026/05/15",
    "trip_no": 1,
    "fish_raw": "サバ",
    "count_raw": "5～10匹",
    "size_raw": "20～38cm",
    "weight_raw": "",
    "tokki_raw": "外道",
    "point_raw": "神奈川県 鎌倉市 腰越漁港",
    "kanso_raw": "ウィリーアマダイ五目 シロアマダイアマダイハナダイ他に良型アジサバと皆さんお土産",
    "suion_raw": "19.5℃",
    "suishoku_raw": "",
    "color_raw": "",
    "source": "chowari/喜久丸",
    "tide_label": "大潮",
    "weather_text": "晴れ",
    "weather_detail": {
      "sunrise": "04:38",
      "sunset": "18:39",
      "moonrise": "03:01",
      "moonset": "16:56",
      "weather": "晴れ",
      "temp_high": "25℃",
      "temp_low": "15℃",
      "pressure": "1023.1hPa",
      "wind_dir": "北東",
      "wind_speed": "2.9m/s",
      "wave_dir": "南南東",
      "wave_height": "0.3m/s",
      "water_temp": "19.5℃",
      "tide": "大潮",
      "moon_age": "27.6",
      "bi": "9.5"
    }
  },
  {
    "ship": "喜久丸",
    "area": "腰越港",
    "date": "2026/05/13",
    "trip_no": 1,
    "fish_raw": "アマダイ",
    "count_raw": "0～1匹",
    "size_raw": "28～35cm",
    "weight_raw": "",
    "tokki_raw": "メイン",
    "point_raw": "神奈川県 鎌倉市 腰越漁港",
    "kanso_raw": "ウィリーアマダイ五目 天気にも恵まれターゲットのアマダイイトヨリも顔を出してくれました他に良型アジサバと皆さんお土産はバッチリで良かったです！ PS明日は臨時休業で休船しますm(__)m",
    "suion_raw": "19.3℃",
    "suishoku_raw": "",
    "color_raw": "",
    "source": "chowari/喜久丸",
    "tide_label": "中潮",
    "weather_text": "晴れ後時々曇り",
    "weather_detail": {
      "sunrise": "04:39",
      "sunset": "18:38",
      "moonrise": "02:03",
      "moonset": "14:35",
      "weather": "晴れ後時々曇り",
      "temp_high": "27℃",
      "temp_low": "15℃",
      "pressure": "1010.3hPa",
      "wind_dir": "東",
      "wind_speed": "1.1m/s",
      "wave_dir": "南南東",
      "wave_height": "0.4m/s",
      "water_temp": "19.3℃",
      "tide": "中潮",
      "moon_age": "25.6",
      "bi": "8.9"
    }
  },
  {
    "ship": "喜久丸",
    "area": "腰越港",
    "date": "2026/05/13",
    "trip_no": 1,
    "fish_raw": "イトヨリ",
    "count_raw": "0～1匹",
    "size_raw": "23～32cm",
    "weight_raw": "",
    "tokki_raw": "外道",
    "point_raw": "神奈川県 鎌倉市 腰越漁港",
    "kanso_raw": "ウィリーアマダイ五目 天気にも恵まれターゲットのアマダイイトヨリも顔を出してくれました他に良型アジサバと皆さんお土産はバッチリで良かったです！ PS明日は臨時休業で休船しますm(__)m",
    "suion_raw": "19.3℃",
    "suishoku_raw": "",
    "color_raw": "",
    "source": "chowari/喜久丸",
    "tide_label": "中潮",
    "weather_text": "晴れ後時々曇り",
    "weather_detail": {
      "sunrise": "04:39",
      "sunset": "18:38",
      "moonrise": "02:03",
      "moonset": "14:35",
      "weather": "晴れ後時々曇り",
      "temp_high": "27℃",
      "temp_low": "15℃",
      "pressure": "1010.3hPa",
      "wind_dir": "東",
      "wind_speed": "1.1m/s",
      "wave_dir": "南南東",
      "wave_height": "0.4m/s",
      "water_temp": "19.3℃",
      "tide": "中潮",
      "moon_age": "25.6",
      "bi": "8.9"
    }
  },
  {
    "ship": "喜久丸",
    "area": "腰越港",
    "date": "2026/05/13",
    "trip_no": 1,
    "fish_raw": "アジ",
    "count_raw": "7～12匹",
    "size_raw": "23～38cm",
    "weight_raw": "",
    "tokki_raw": "外道",
    "point_raw": "神奈川県 鎌倉市 腰越漁港",
    "kanso_raw": "ウィリーアマダイ五目 天気にも恵まれターゲットのアマダイイトヨリも顔を出してくれました他に良型アジサバと皆さんお土産はバッチリで良かったです！ PS明日は臨時休業で休船しますm(__)m",
    "suion_raw": "19.3℃",
    "suishoku_raw": "",
    "color_raw": "",
    "source": "chowari/喜久丸",
    "tide_label": "中潮",
    "weather_text": "晴れ後時々曇り",
    "weather_detail": {
      "sunrise": "04:39",
      "sunset": "18:38",
      "moonrise": "02:03",
      "moonset": "14:35",
      "weather": "晴れ後時々曇り",
      "temp_high": "27℃",
      "temp_low": "15℃",
      "pressure": "1010.3hPa",
      "wind_dir": "東",
      "wind_speed": "1.1m/s",
      "wave_dir": "南南東",
      "wave_height": "0.4m/s",
      "water_temp": "19.3℃",
      "tide": "中潮",
      "moon_age": "25.6",
      "bi": "8.9"
    }
  },
  {
    "ship": "喜久丸",
    "area": "腰越港",
    "date": "2026/05/13",
    "trip_no": 1,
    "fish_raw": "サバ",
    "count_raw": "4～15匹",
    "size_raw": "23～40cm",
    "weight_raw": "",
    "tokki_raw": "外道",
    "point_raw": "神奈川県 鎌倉市 腰越漁港",
    "kanso_raw": "ウィリーアマダイ五目 天気にも恵まれターゲットのアマダイイトヨリも顔を出してくれました他に良型アジサバと皆さんお土産はバッチリで良かったです！ PS明日は臨時休業で休船しますm(__)m",
    "suion_raw": "19.3℃",
    "suishoku_raw": "",
    "color_raw": "",
    "source": "chowari/喜久丸",
    "tide_label": "中潮",
    "weather_text": "晴れ後時々曇り",
    "weather_detail": {
      "sunrise": "04:39",
      "sunset": "18:38",
      "moonrise": "02:03",
      "moonset": "14:35",
      "weather": "晴れ後時々曇り",
      "temp_high": "27℃",
      "temp_low": "15℃",
      "pressure": "1010.3hPa",
      "wind_dir": "東",
      "wind_speed": "1.1m/s",
      "wave_dir": "南南東",
      "wave_height": "0.4m/s",
      "water_temp": "19.3℃",
      "tide": "中潮",
      "moon_age": "25.6",
      "bi": "8.9"
    }
  },
  {
    "ship": "喜久丸",
    "area": "腰越港",
    "date": "2026/05/12",
    "trip_no": 1,
    "fish_raw": "ハナダイ",
    "count_raw": "合計1匹",
    "size_raw": "0.80kg",
    "weight_raw": "",
    "tokki_raw": "メイン",
    "point_raw": "神奈川県 鎌倉市 腰越漁港",
    "kanso_raw": "ウィリーアマダイ五目 船酔いでダウンされた方も居ましたがお土産はキープ出来ました！",
    "suion_raw": "19.1℃",
    "suishoku_raw": "",
    "color_raw": "",
    "source": "chowari/喜久丸",
    "tide_label": "若潮",
    "weather_text": "晴れ",
    "weather_detail": {
      "sunrise": "04:40",
      "sunset": "18:37",
      "moonrise": "01:37",
      "moonset": "13:30",
      "weather": "晴れ",
      "temp_high": "25℃",
      "temp_low": "16℃",
      "pressure": "1015.9hPa",
      "wind_dir": "南南東",
      "wind_speed": "1.8m/s",
      "wave_dir": "南南東",
      "wave_height": "0.6m/s",
      "water_temp": "19.1℃",
      "tide": "若潮",
      "moon_age": "24.6",
      "bi": "9.0"
    }
  },
  {
    "ship": "喜久丸",
    "area": "腰越港",
    "date": "2026/05/12",
    "trip_no": 1,
    "fish_raw": "アジ",
    "count_raw": "0～15匹",
    "size_raw": "25～38cm",
    "weight_raw": "",
    "tokki_raw": "外道",
    "point_raw": "神奈川県 鎌倉市 腰越漁港",
    "kanso_raw": "ウィリーアマダイ五目 船酔いでダウンされた方も居ましたがお土産はキープ出来ました！",
    "suion_raw": "19.1℃",
    "suishoku_raw": "",
    "color_raw": "",
    "source": "chowari/喜久丸",
    "tide_label": "若潮",
    "weather_text": "晴れ",
    "weather_detail": {
      "sunrise": "04:40",
      "sunset": "18:37",
      "moonrise": "01:37",
      "moonset": "13:30",
      "weather": "晴れ",
      "temp_high": "25℃",
      "temp_low": "16℃",
      "pressure": "1015.9hPa",
      "wind_dir": "南南東",
      "wind_speed": "1.8m/s",
      "wave_dir": "南南東",
      "wave_height": "0.6m/s",
      "water_temp": "19.1℃",
      "tide": "若潮",
      "moon_age": "24.6",
      "bi": "9.0"
    }
  },
  {
    "ship": "喜久丸",
    "area": "腰越港",
    "date": "2026/05/12",
    "trip_no": 1,
    "fish_raw": "サバ",
    "count_raw": "1～12匹",
    "size_raw": "28～30cm",
    "weight_raw": "",
    "tokki_raw": "外道",
    "point_raw": "神奈川県 鎌倉市 腰越漁港",
    "kanso_raw": "ウィリーアマダイ五目 船酔いでダウンされた方も居ましたがお土産はキープ出来ました！",
    "suion_raw": "19.1℃",
    "suishoku_raw": "",
    "color_raw": "",
    "source": "chowari/喜久丸",
    "tide_label": "若潮",
    "weather_text": "晴れ",
    "weather_detail": {
      "sunrise": "04:40",
      "sunset": "18:37",
      "moonrise": "01:37",
      "moonset": "13:30",
      "weather": "晴れ",
      "temp_high": "25℃",
      "temp_low": "16℃",
      "pressure": "1015.9hPa",
      "wind_dir": "南南東",
      "wind_speed": "1.8m/s",
      "wave_dir": "南南東",
      "wave_height": "0.6m/s",
      "water_temp": "19.1℃",
      "tide": "若潮",
      "moon_age": "24.6",
      "bi": "9.0"
    }
  },
  {
    "ship": "喜久丸",
    "area": "腰越港",
    "date": "2026/05/09",
    "trip_no": 1,
    "fish_raw": "アマダイ",
    "count_raw": "0～1匹",
    "size_raw": "28～52cm",
    "weight_raw": "",
    "tokki_raw": "メイン",
    "point_raw": "神奈川県 鎌倉市 腰越漁港",
    "kanso_raw": "ウィリーアマダイ五目 親子ペアの皆さんも良型アジサバをメインにアマダイイトヨリホウボウとお土産もバッチリキープで帰港です！ チャーター船 朝のうちは船酔い気味でダウンされてた方も後半から元気をとりもどし皆さん良型アジサバアマダイと釣果に恵まれ楽しんでもらえて良かったです！ PS明日はみなと祭で休船しますm(__)m",
    "suion_raw": "18.8℃",
    "suishoku_raw": "",
    "color_raw": "",
    "source": "chowari/喜久丸",
    "tide_label": "小潮",
    "weather_text": "晴れ",
    "weather_detail": {
      "sunrise": "04:43",
      "sunset": "18:34",
      "moonrise": "00:10",
      "moonset": "10:22",
      "weather": "晴れ",
      "temp_high": "24℃",
      "temp_low": "16℃",
      "pressure": "1010.9hPa",
      "wind_dir": "南南東",
      "wind_speed": "0.3m/s",
      "wave_dir": "南",
      "wave_height": "0.7m/s",
      "water_temp": "18.8℃",
      "tide": "小潮",
      "moon_age": "21.6",
      "bi": "6.7"
    }
  },
  {
    "ship": "喜久丸",
    "area": "腰越港",
    "date": "2026/05/09",
    "trip_no": 1,
    "fish_raw": "アジ",
    "count_raw": "2～9匹",
    "size_raw": "25～36cm",
    "weight_raw": "",
    "tokki_raw": "外道",
    "point_raw": "神奈川県 鎌倉市 腰越漁港",
    "kanso_raw": "ウィリーアマダイ五目 親子ペアの皆さんも良型アジサバをメインにアマダイイトヨリホウボウとお土産もバッチリキープで帰港です！ チャーター船 朝のうちは船酔い気味でダウンされてた方も後半から元気をとりもどし皆さん良型アジサバアマダイと釣果に恵まれ楽しんでもらえて良かったです！ PS明日はみなと祭で休船しますm(__)m",
    "suion_raw": "18.8℃",
    "suishoku_raw": "",
    "color_raw": "",
    "source": "chowari/喜久丸",
    "tide_label": "小潮",
    "weather_text": "晴れ",
    "weather_detail": {
      "sunrise": "04:43",
      "sunset": "18:34",
      "moonrise": "00:10",
      "moonset": "10:22",
      "weather": "晴れ",
      "temp_high": "24℃",
      "temp_low": "16℃",
      "pressure": "1010.9hPa",
      "wind_dir": "南南東",
      "wind_speed": "0.3m/s",
      "wave_dir": "南",
      "wave_height": "0.7m/s",
      "water_temp": "18.8℃",
      "tide": "小潮",
      "moon_age": "21.6",
      "bi": "6.7"
    }
  },
  {
    "ship": "喜久丸",
    "area": "腰越港",
    "date": "2026/05/09",
    "trip_no": 1,
    "fish_raw": "サバ",
    "count_raw": "3～12匹",
    "size_raw": "23～40cm",
    "weight_raw": "",
    "tokki_raw": "外道",
    "point_raw": "神奈川県 鎌倉市 腰越漁港",
    "kanso_raw": "ウィリーアマダイ五目 親子ペアの皆さんも良型アジサバをメインにアマダイイトヨリホウボウとお土産もバッチリキープで帰港です！ チャーター船 朝のうちは船酔い気味でダウンされてた方も後半から元気をとりもどし皆さん良型アジサバアマダイと釣果に恵まれ楽しんでもらえて良かったです！ PS明日はみなと祭で休船しますm(__)m",
    "suion_raw": "18.8℃",
    "suishoku_raw": "",
    "color_raw": "",
    "source": "chowari/喜久丸",
    "tide_label": "小潮",
    "weather_text": "晴れ",
    "weather_detail": {
      "sunrise": "04:43",
      "sunset": "18:34",
      "moonrise": "00:10",
      "moonset": "10:22",
      "weather": "晴れ",
      "temp_high": "24℃",
      "temp_low": "16℃",
      "pressure": "1010.9hPa",
      "wind_dir": "南南東",
      "wind_speed": "0.3m/s",
      "wave_dir": "南",
      "wave_height": "0.7m/s",
      "water_temp": "18.8℃",
      "tide": "小潮",
      "moon_age": "21.6",
      "bi": "6.7"
    }
  },
  {
    "ship": "喜久丸",
    "area": "腰越港",
    "date": "2026/05/06",
    "trip_no": 1,
    "fish_raw": "アマダイ",
    "count_raw": "0～1匹",
    "size_raw": "23～32cm",
    "weight_raw": "",
    "tokki_raw": "メイン",
    "point_raw": "神奈川県 鎌倉市 腰越漁港",
    "kanso_raw": "ハナダイクロダイアマダイイトヨリ始めアジサバと親子ペアの方からビギナーのグループの皆さんもお土産はバッチリキープ！楽しんでもらえて良かったです。 PS船酔いでダウンされた方は釣果に恵まれませんでした。 明日は定休日で休船しますm(__)m",
    "suion_raw": "18.7℃",
    "suishoku_raw": "",
    "color_raw": "",
    "source": "chowari/喜久丸",
    "tide_label": "中潮",
    "weather_text": "曇り",
    "weather_detail": {
      "sunrise": "04:46",
      "sunset": "18:32",
      "moonrise": "22:52",
      "moonset": "07:25",
      "weather": "曇り",
      "temp_high": "22℃",
      "temp_low": "15℃",
      "pressure": "1023.2hPa",
      "wind_dir": "南",
      "wind_speed": "3.7m/s",
      "wave_dir": "南南東",
      "wave_height": "0.8m/s",
      "water_temp": "18.7℃",
      "tide": "中潮",
      "moon_age": "18.6",
      "bi": "8.0"
    }
  },
  {
    "ship": "喜久丸",
    "area": "腰越港",
    "date": "2026/05/06",
    "trip_no": 1,
    "fish_raw": "アジ",
    "count_raw": "0～10匹",
    "size_raw": "25～38cm",
    "weight_raw": "",
    "tokki_raw": "外道",
    "point_raw": "神奈川県 鎌倉市 腰越漁港",
    "kanso_raw": "ハナダイクロダイアマダイイトヨリ始めアジサバと親子ペアの方からビギナーのグループの皆さんもお土産はバッチリキープ！楽しんでもらえて良かったです。 PS船酔いでダウンされた方は釣果に恵まれませんでした。 明日は定休日で休船しますm(__)m",
    "suion_raw": "18.7℃",
    "suishoku_raw": "",
    "color_raw": "",
    "source": "chowari/喜久丸",
    "tide_label": "中潮",
    "weather_text": "曇り",
    "weather_detail": {
      "sunrise": "04:46",
      "sunset": "18:32",
      "moonrise": "22:52",
      "moonset": "07:25",
      "weather": "曇り",
      "temp_high": "22℃",
      "temp_low": "15℃",
      "pressure": "1023.2hPa",
      "wind_dir": "南",
      "wind_speed": "3.7m/s",
      "wave_dir": "南南東",
      "wave_height": "0.8m/s",
      "water_temp": "18.7℃",
      "tide": "中潮",
      "moon_age": "18.6",
      "bi": "8.0"
    }
  },
  {
    "ship": "喜久丸",
    "area": "腰越港",
    "date": "2026/05/06",
    "trip_no": 1,
    "fish_raw": "サバ",
    "count_raw": "0～15匹",
    "size_raw": "25～40cm",
    "weight_raw": "",
    "tokki_raw": "外道",
    "point_raw": "神奈川県 鎌倉市 腰越漁港",
    "kanso_raw": "ハナダイクロダイアマダイイトヨリ始めアジサバと親子ペアの方からビギナーのグループの皆さんもお土産はバッチリキープ！楽しんでもらえて良かったです。 PS船酔いでダウンされた方は釣果に恵まれませんでした。 明日は定休日で休船しますm(__)m",
    "suion_raw": "18.7℃",
    "suishoku_raw": "",
    "color_raw": "",
    "source": "chowari/喜久丸",
    "tide_label": "中潮",
    "weather_text": "曇り",
    "weather_detail": {
      "sunrise": "04:46",
      "sunset": "18:32",
      "moonrise": "22:52",
      "moonset": "07:25",
      "weather": "曇り",
      "temp_high": "22℃",
      "temp_low": "15℃",
      "pressure": "1023.2hPa",
      "wind_dir": "南",
      "wind_speed": "3.7m/s",
      "wave_dir": "南南東",
      "wave_height": "0.8m/s",
      "water_temp": "18.7℃",
      "tide": "中潮",
      "moon_age": "18.6",
      "bi": "8.0"
    }
  },
  {
    "ship": "喜久丸",
    "area": "腰越港",
    "date": "2026/05/05",
    "trip_no": 1,
    "fish_raw": "アマダイ",
    "count_raw": "0～1匹",
    "size_raw": "25～33cm",
    "weight_raw": "",
    "tokki_raw": "メイン",
    "point_raw": "神奈川県 鎌倉市 腰越漁港",
    "kanso_raw": "親子ペア、釣りガールの皆さんもアジサバソーダのお土産はバッチリキープで良かったです！他にアマダイホウボウハナダイと顔は見れました。 チャーター船 アジサバソーダアマダイと天気にも恵まれ楽しんでもらえました！",
    "suion_raw": "18.7℃",
    "suishoku_raw": "",
    "color_raw": "",
    "source": "chowari/喜久丸",
    "tide_label": "中潮",
    "weather_text": "晴れ",
    "weather_detail": {
      "sunrise": "04:47",
      "sunset": "18:31",
      "moonrise": "22:04",
      "moonset": "06:34",
      "weather": "晴れ",
      "temp_high": "24℃",
      "temp_low": "14℃",
      "pressure": "1020.4hPa",
      "wind_dir": "北東",
      "wind_speed": "4.1m/s",
      "wave_dir": "南",
      "wave_height": "0.7m/s",
      "water_temp": "18.7℃",
      "tide": "中潮",
      "moon_age": "17.6",
      "bi": "7.8"
    }
  },
  {
    "ship": "喜久丸",
    "area": "腰越港",
    "date": "2026/05/05",
    "trip_no": 1,
    "fish_raw": "アジ",
    "count_raw": "0～6匹",
    "size_raw": "23～33cm",
    "weight_raw": "",
    "tokki_raw": "外道",
    "point_raw": "神奈川県 鎌倉市 腰越漁港",
    "kanso_raw": "親子ペア、釣りガールの皆さんもアジサバソーダのお土産はバッチリキープで良かったです！他にアマダイホウボウハナダイと顔は見れました。 チャーター船 アジサバソーダアマダイと天気にも恵まれ楽しんでもらえました！",
    "suion_raw": "18.7℃",
    "suishoku_raw": "",
    "color_raw": "",
    "source": "chowari/喜久丸",
    "tide_label": "中潮",
    "weather_text": "晴れ",
    "weather_detail": {
      "sunrise": "04:47",
      "sunset": "18:31",
      "moonrise": "22:04",
      "moonset": "06:34",
      "weather": "晴れ",
      "temp_high": "24℃",
      "temp_low": "14℃",
      "pressure": "1020.4hPa",
      "wind_dir": "北東",
      "wind_speed": "4.1m/s",
      "wave_dir": "南",
      "wave_height": "0.7m/s",
      "water_temp": "18.7℃",
      "tide": "中潮",
      "moon_age": "17.6",
      "bi": "7.8"
    }
  },
  {
    "ship": "喜久丸",
    "area": "腰越港",
    "date": "2026/05/05",
    "trip_no": 1,
    "fish_raw": "サバ",
    "count_raw": "0～10匹",
    "size_raw": "23～35cm",
    "weight_raw": "",
    "tokki_raw": "外道",
    "point_raw": "神奈川県 鎌倉市 腰越漁港",
    "kanso_raw": "親子ペア、釣りガールの皆さんもアジサバソーダのお土産はバッチリキープで良かったです！他にアマダイホウボウハナダイと顔は見れました。 チャーター船 アジサバソーダアマダイと天気にも恵まれ楽しんでもらえました！",
    "suion_raw": "18.7℃",
    "suishoku_raw": "",
    "color_raw": "",
    "source": "chowari/喜久丸",
    "tide_label": "中潮",
    "weather_text": "晴れ",
    "weather_detail": {
      "sunrise": "04:47",
      "sunset": "18:31",
      "moonrise": "22:04",
      "moonset": "06:34",
      "weather": "晴れ",
      "temp_high": "24℃",
      "temp_low": "14℃",
      "pressure": "1020.4hPa",
      "wind_dir": "北東",
      "wind_speed": "4.1m/s",
      "wave_dir": "南",
      "wave_height": "0.7m/s",
      "water_temp": "18.7℃",
      "tide": "中潮",
      "moon_age": "17.6",
      "bi": "7.8"
    }
  },
  {
    "ship": "喜久丸",
    "area": "腰越港",
    "date": "2026/05/03",
    "trip_no": 1,
    "fish_raw": "ハナダイ",
    "count_raw": "0～1匹",
    "size_raw": "0.30～0.70kg",
    "weight_raw": "",
    "tokki_raw": "メイン",
    "point_raw": "神奈川県 鎌倉市 腰越漁港",
    "kanso_raw": "ハナダイアマダイシロアマダイ他に良型アジサバソーダと親子ペア、ファミリーの皆さんもお土産バッチリで帰港出来ました！ 釣果に恵まれ無かった方は船酔いでダウンされた方でした。",
    "suion_raw": "18.4℃",
    "suishoku_raw": "",
    "color_raw": "",
    "source": "chowari/喜久丸",
    "tide_label": "大潮",
    "weather_text": "曇りのち一時雨",
    "weather_detail": {
      "sunrise": "04:49",
      "sunset": "18:29",
      "moonrise": "20:13",
      "moonset": "05:10",
      "weather": "曇りのち一時雨",
      "temp_high": "24℃",
      "temp_low": "17℃",
      "pressure": "1013.4hPa",
      "wind_dir": "北北東",
      "wind_speed": "1.5m/s",
      "wave_dir": "南",
      "wave_height": "0.4m/s",
      "water_temp": "18.4℃",
      "tide": "大潮",
      "moon_age": "15.6",
      "bi": "8.4"
    }
  },
  {
    "ship": "喜久丸",
    "area": "腰越港",
    "date": "2026/05/03",
    "trip_no": 1,
    "fish_raw": "アマダイ",
    "count_raw": "0～1匹",
    "size_raw": "23～28cm",
    "weight_raw": "",
    "tokki_raw": "外道",
    "point_raw": "神奈川県 鎌倉市 腰越漁港",
    "kanso_raw": "ハナダイアマダイシロアマダイ他に良型アジサバソーダと親子ペア、ファミリーの皆さんもお土産バッチリで帰港出来ました！ 釣果に恵まれ無かった方は船酔いでダウンされた方でした。",
    "suion_raw": "18.4℃",
    "suishoku_raw": "",
    "color_raw": "",
    "source": "chowari/喜久丸",
    "tide_label": "大潮",
    "weather_text": "曇りのち一時雨",
    "weather_detail": {
      "sunrise": "04:49",
      "sunset": "18:29",
      "moonrise": "20:13",
      "moonset": "05:10",
      "weather": "曇りのち一時雨",
      "temp_high": "24℃",
      "temp_low": "17℃",
      "pressure": "1013.4hPa",
      "wind_dir": "北北東",
      "wind_speed": "1.5m/s",
      "wave_dir": "南",
      "wave_height": "0.4m/s",
      "water_temp": "18.4℃",
      "tide": "大潮",
      "moon_age": "15.6",
      "bi": "8.4"
    }
  },
  {
    "ship": "喜久丸",
    "area": "腰越港",
    "date": "2026/05/03",
    "trip_no": 1,
    "fish_raw": "アジ",
    "count_raw": "0～10匹",
    "size_raw": "23～35cm",
    "weight_raw": "",
    "tokki_raw": "外道",
    "point_raw": "神奈川県 鎌倉市 腰越漁港",
    "kanso_raw": "ハナダイアマダイシロアマダイ他に良型アジサバソーダと親子ペア、ファミリーの皆さんもお土産バッチリで帰港出来ました！ 釣果に恵まれ無かった方は船酔いでダウンされた方でした。",
    "suion_raw": "18.4℃",
    "suishoku_raw": "",
    "color_raw": "",
    "source": "chowari/喜久丸",
    "tide_label": "大潮",
    "weather_text": "曇りのち一時雨",
    "weather_detail": {
      "sunrise": "04:49",
      "sunset": "18:29",
      "moonrise": "20:13",
      "moonset": "05:10",
      "weather": "曇りのち一時雨",
      "temp_high": "24℃",
      "temp_low": "17℃",
      "pressure": "1013.4hPa",
      "wind_dir": "北北東",
      "wind_speed": "1.5m/s",
      "wave_dir": "南",
      "wave_height": "0.4m/s",
      "water_temp": "18.4℃",
      "tide": "大潮",
      "moon_age": "15.6",
      "bi": "8.4"
    }
  },
  {
    "ship": "喜久丸",
    "area": "腰越港",
    "date": "2026/05/03",
    "trip_no": 1,
    "fish_raw": "サバ",
    "count_raw": "0～8匹",
    "size_raw": "25～40cm",
    "weight_raw": "",
    "tokki_raw": "外道",
    "point_raw": "神奈川県 鎌倉市 腰越漁港",
    "kanso_raw": "ハナダイアマダイシロアマダイ他に良型アジサバソーダと親子ペア、ファミリーの皆さんもお土産バッチリで帰港出来ました！ 釣果に恵まれ無かった方は船酔いでダウンされた方でした。",
    "suion_raw": "18.4℃",
    "suishoku_raw": "",
    "color_raw": "",
    "source": "chowari/喜久丸",
    "tide_label": "大潮",
    "weather_text": "曇りのち一時雨",
    "weather_detail": {
      "sunrise": "04:49",
      "sunset": "18:29",
      "moonrise": "20:13",
      "moonset": "05:10",
      "weather": "曇りのち一時雨",
      "temp_high": "24℃",
      "temp_low": "17℃",
      "pressure": "1013.4hPa",
      "wind_dir": "北北東",
      "wind_speed": "1.5m/s",
      "wave_dir": "南",
      "wave_height": "0.4m/s",
      "water_temp": "18.4℃",
      "tide": "大潮",
      "moon_age": "15.6",
      "bi": "8.4"
    }
  },
  {
    "ship": "喜久丸",
    "area": "腰越港",
    "date": "2026/04/30",
    "trip_no": 1,
    "fish_raw": "アマダイ",
    "count_raw": "0～2匹",
    "size_raw": "28～32cm",
    "weight_raw": "",
    "tokki_raw": "メイン",
    "point_raw": "神奈川県 鎌倉市 腰越漁港",
    "kanso_raw": "皆さん棚トリもバッチリでアマダイイトヨリホウボウカサゴ他に良型アジサバと楽しんでもらえました！ PS明日は天気予報も悪いので休船しますm(__)m",
    "suion_raw": "17.3℃",
    "suishoku_raw": "",
    "color_raw": "",
    "source": "chowari/喜久丸",
    "tide_label": "大潮",
    "weather_text": "曇りのち一時雨",
    "weather_detail": {
      "sunrise": "04:52",
      "sunset": "18:27",
      "moonrise": "17:11",
      "moonset": "03:41",
      "weather": "曇りのち一時雨",
      "temp_high": "18℃",
      "temp_low": "14℃",
      "pressure": "1022.4hPa",
      "wind_dir": "北東",
      "wind_speed": "2.8m/s",
      "wave_dir": "南南東",
      "wave_height": "0.2m/s",
      "water_temp": "17.3℃",
      "tide": "大潮",
      "moon_age": "12.6",
      "bi": "9.3"
    }
  },
  {
    "ship": "喜久丸",
    "area": "腰越港",
    "date": "2026/04/30",
    "trip_no": 1,
    "fish_raw": "ホウボウ",
    "count_raw": "0～3匹",
    "size_raw": "25～30cm",
    "weight_raw": "",
    "tokki_raw": "外道",
    "point_raw": "神奈川県 鎌倉市 腰越漁港",
    "kanso_raw": "皆さん棚トリもバッチリでアマダイイトヨリホウボウカサゴ他に良型アジサバと楽しんでもらえました！ PS明日は天気予報も悪いので休船しますm(__)m",
    "suion_raw": "17.3℃",
    "suishoku_raw": "",
    "color_raw": "",
    "source": "chowari/喜久丸",
    "tide_label": "大潮",
    "weather_text": "曇りのち一時雨",
    "weather_detail": {
      "sunrise": "04:52",
      "sunset": "18:27",
      "moonrise": "17:11",
      "moonset": "03:41",
      "weather": "曇りのち一時雨",
      "temp_high": "18℃",
      "temp_low": "14℃",
      "pressure": "1022.4hPa",
      "wind_dir": "北東",
      "wind_speed": "2.8m/s",
      "wave_dir": "南南東",
      "wave_height": "0.2m/s",
      "water_temp": "17.3℃",
      "tide": "大潮",
      "moon_age": "12.6",
      "bi": "9.3"
    }
  },
  {
    "ship": "喜久丸",
    "area": "腰越港",
    "date": "2026/04/30",
    "trip_no": 1,
    "fish_raw": "イトヨリ",
    "count_raw": "0～1匹",
    "size_raw": "25～28cm",
    "weight_raw": "",
    "tokki_raw": "外道",
    "point_raw": "神奈川県 鎌倉市 腰越漁港",
    "kanso_raw": "皆さん棚トリもバッチリでアマダイイトヨリホウボウカサゴ他に良型アジサバと楽しんでもらえました！ PS明日は天気予報も悪いので休船しますm(__)m",
    "suion_raw": "17.3℃",
    "suishoku_raw": "",
    "color_raw": "",
    "source": "chowari/喜久丸",
    "tide_label": "大潮",
    "weather_text": "曇りのち一時雨",
    "weather_detail": {
      "sunrise": "04:52",
      "sunset": "18:27",
      "moonrise": "17:11",
      "moonset": "03:41",
      "weather": "曇りのち一時雨",
      "temp_high": "18℃",
      "temp_low": "14℃",
      "pressure": "1022.4hPa",
      "wind_dir": "北東",
      "wind_speed": "2.8m/s",
      "wave_dir": "南南東",
      "wave_height": "0.2m/s",
      "water_temp": "17.3℃",
      "tide": "大潮",
      "moon_age": "12.6",
      "bi": "9.3"
    }
  },
  {
    "ship": "喜久丸",
    "area": "腰越港",
    "date": "2026/04/30",
    "trip_no": 1,
    "fish_raw": "アジ",
    "count_raw": "3～12匹",
    "size_raw": "28～40cm",
    "weight_raw": "",
    "tokki_raw": "外道",
    "point_raw": "神奈川県 鎌倉市 腰越漁港",
    "kanso_raw": "皆さん棚トリもバッチリでアマダイイトヨリホウボウカサゴ他に良型アジサバと楽しんでもらえました！ PS明日は天気予報も悪いので休船しますm(__)m",
    "suion_raw": "17.3℃",
    "suishoku_raw": "",
    "color_raw": "",
    "source": "chowari/喜久丸",
    "tide_label": "大潮",
    "weather_text": "曇りのち一時雨",
    "weather_detail": {
      "sunrise": "04:52",
      "sunset": "18:27",
      "moonrise": "17:11",
      "moonset": "03:41",
      "weather": "曇りのち一時雨",
      "temp_high": "18℃",
      "temp_low": "14℃",
      "pressure": "1022.4hPa",
      "wind_dir": "北東",
      "wind_speed": "2.8m/s",
      "wave_dir": "南南東",
      "wave_height": "0.2m/s",
      "water_temp": "17.3℃",
      "tide": "大潮",
      "moon_age": "12.6",
      "bi": "9.3"
    }
  },
  {
    "ship": "喜久丸",
    "area": "腰越港",
    "date": "2026/04/30",
    "trip_no": 1,
    "fish_raw": "サバ",
    "count_raw": "5～8匹",
    "size_raw": "25～40cm",
    "weight_raw": "",
    "tokki_raw": "外道",
    "point_raw": "神奈川県 鎌倉市 腰越漁港",
    "kanso_raw": "皆さん棚トリもバッチリでアマダイイトヨリホウボウカサゴ他に良型アジサバと楽しんでもらえました！ PS明日は天気予報も悪いので休船しますm(__)m",
    "suion_raw": "17.3℃",
    "suishoku_raw": "",
    "color_raw": "",
    "source": "chowari/喜久丸",
    "tide_label": "大潮",
    "weather_text": "曇りのち一時雨",
    "weather_detail": {
      "sunrise": "04:52",
      "sunset": "18:27",
      "moonrise": "17:11",
      "moonset": "03:41",
      "weather": "曇りのち一時雨",
      "temp_high": "18℃",
      "temp_low": "14℃",
      "pressure": "1022.4hPa",
      "wind_dir": "北東",
      "wind_speed": "2.8m/s",
      "wave_dir": "南南東",
      "wave_height": "0.2m/s",
      "water_temp": "17.3℃",
      "tide": "大潮",
      "moon_age": "12.6",
      "bi": "9.3"
    }
  },
  {
    "ship": "喜久丸",
    "area": "腰越港",
    "date": "2026/04/29",
    "trip_no": 1,
    "fish_raw": "ハナダイ",
    "count_raw": "0～1匹",
    "size_raw": "0.40～0.80kg",
    "weight_raw": "",
    "tokki_raw": "メイン",
    "point_raw": "神奈川県 鎌倉市 腰越漁港",
    "kanso_raw": "海上はややウネリがあり船酔いでダウンされた方も出てしまい少し残念でしたがターゲットのハナダイシロアマダイアマダイアオハタイトヨリ他に良型アジサバムシガレイとお土産はバッチリキープ出来ました！",
    "suion_raw": "17.1℃",
    "suishoku_raw": "",
    "color_raw": "",
    "source": "chowari/喜久丸",
    "tide_label": "中潮",
    "weather_text": "曇り",
    "weather_detail": {
      "sunrise": "04:53",
      "sunset": "18:26",
      "moonrise": "16:12",
      "moonset": "03:17",
      "weather": "曇り",
      "temp_high": "22℃",
      "temp_low": "15℃",
      "pressure": "1011.2hPa",
      "wind_dir": "南",
      "wind_speed": "0.5m/s",
      "wave_dir": "南",
      "wave_height": "0.8m/s",
      "water_temp": "17.1℃",
      "tide": "中潮",
      "moon_age": "11.6",
      "bi": "8.9"
    }
  },
  {
    "ship": "喜久丸",
    "area": "腰越港",
    "date": "2026/04/29",
    "trip_no": 1,
    "fish_raw": "アマダイ",
    "count_raw": "0～1匹",
    "size_raw": "25～45cm",
    "weight_raw": "",
    "tokki_raw": "外道",
    "point_raw": "神奈川県 鎌倉市 腰越漁港",
    "kanso_raw": "海上はややウネリがあり船酔いでダウンされた方も出てしまい少し残念でしたがターゲットのハナダイシロアマダイアマダイアオハタイトヨリ他に良型アジサバムシガレイとお土産はバッチリキープ出来ました！",
    "suion_raw": "17.1℃",
    "suishoku_raw": "",
    "color_raw": "",
    "source": "chowari/喜久丸",
    "tide_label": "中潮",
    "weather_text": "曇り",
    "weather_detail": {
      "sunrise": "04:53",
      "sunset": "18:26",
      "moonrise": "16:12",
      "moonset": "03:17",
      "weather": "曇り",
      "temp_high": "22℃",
      "temp_low": "15℃",
      "pressure": "1011.2hPa",
      "wind_dir": "南",
      "wind_speed": "0.5m/s",
      "wave_dir": "南",
      "wave_height": "0.8m/s",
      "water_temp": "17.1℃",
      "tide": "中潮",
      "moon_age": "11.6",
      "bi": "8.9"
    }
  },
  {
    "ship": "喜久丸",
    "area": "腰越港",
    "date": "2026/04/29",
    "trip_no": 1,
    "fish_raw": "アジ",
    "count_raw": "0～8匹",
    "size_raw": "25～40cm",
    "weight_raw": "",
    "tokki_raw": "外道",
    "point_raw": "神奈川県 鎌倉市 腰越漁港",
    "kanso_raw": "海上はややウネリがあり船酔いでダウンされた方も出てしまい少し残念でしたがターゲットのハナダイシロアマダイアマダイアオハタイトヨリ他に良型アジサバムシガレイとお土産はバッチリキープ出来ました！",
    "suion_raw": "17.1℃",
    "suishoku_raw": "",
    "color_raw": "",
    "source": "chowari/喜久丸",
    "tide_label": "中潮",
    "weather_text": "曇り",
    "weather_detail": {
      "sunrise": "04:53",
      "sunset": "18:26",
      "moonrise": "16:12",
      "moonset": "03:17",
      "weather": "曇り",
      "temp_high": "22℃",
      "temp_low": "15℃",
      "pressure": "1011.2hPa",
      "wind_dir": "南",
      "wind_speed": "0.5m/s",
      "wave_dir": "南",
      "wave_height": "0.8m/s",
      "water_temp": "17.1℃",
      "tide": "中潮",
      "moon_age": "11.6",
      "bi": "8.9"
    }
  },
  {
    "ship": "喜久丸",
    "area": "腰越港",
    "date": "2026/04/29",
    "trip_no": 1,
    "fish_raw": "サバ",
    "count_raw": "0～10匹",
    "size_raw": "30～40cm",
    "weight_raw": "",
    "tokki_raw": "外道",
    "point_raw": "神奈川県 鎌倉市 腰越漁港",
    "kanso_raw": "海上はややウネリがあり船酔いでダウンされた方も出てしまい少し残念でしたがターゲットのハナダイシロアマダイアマダイアオハタイトヨリ他に良型アジサバムシガレイとお土産はバッチリキープ出来ました！",
    "suion_raw": "17.1℃",
    "suishoku_raw": "",
    "color_raw": "",
    "source": "chowari/喜久丸",
    "tide_label": "中潮",
    "weather_text": "曇り",
    "weather_detail": {
      "sunrise": "04:53",
      "sunset": "18:26",
      "moonrise": "16:12",
      "moonset": "03:17",
      "weather": "曇り",
      "temp_high": "22℃",
      "temp_low": "15℃",
      "pressure": "1011.2hPa",
      "wind_dir": "南",
      "wind_speed": "0.5m/s",
      "wave_dir": "南",
      "wave_height": "0.8m/s",
      "water_temp": "17.1℃",
      "tide": "中潮",
      "moon_age": "11.6",
      "bi": "8.9"
    }
  },
  {
    "ship": "喜久丸",
    "area": "腰越港",
    "date": "2026/04/28",
    "trip_no": 1,
    "fish_raw": "アマダイ",
    "count_raw": "0～1匹",
    "size_raw": "28～30cm",
    "weight_raw": "",
    "tokki_raw": "メイン",
    "point_raw": "神奈川県 鎌倉市 腰越漁港",
    "kanso_raw": "海上はややウネリがあり棚トリが難しかったですそれでも皆さんの頑張りでアマダイイトヨリホウボウ始めゲストのサバと顔を見れたのですが11時ごろから南西風が強くなり12時ごろ帰港しました！",
    "suion_raw": "16.8℃",
    "suishoku_raw": "",
    "color_raw": "",
    "source": "chowari/喜久丸",
    "tide_label": "中潮",
    "weather_text": "晴れ後時々曇り",
    "weather_detail": {
      "sunrise": "04:54",
      "sunset": "18:25",
      "moonrise": "15:12",
      "moonset": "02:52",
      "weather": "晴れ後時々曇り",
      "temp_high": "25℃",
      "temp_low": "14℃",
      "pressure": "1013.3hPa",
      "wind_dir": "南南西",
      "wind_speed": "5.6m/s",
      "wave_dir": "南",
      "wave_height": "0.7m/s",
      "water_temp": "16.8℃",
      "tide": "中潮",
      "moon_age": "10.6",
      "bi": "9.4"
    }
  },
  {
    "ship": "喜久丸",
    "area": "腰越港",
    "date": "2026/04/28",
    "trip_no": 1,
    "fish_raw": "イトヨリ",
    "count_raw": "0～1匹",
    "size_raw": "30～40cm",
    "weight_raw": "",
    "tokki_raw": "外道",
    "point_raw": "神奈川県 鎌倉市 腰越漁港",
    "kanso_raw": "海上はややウネリがあり棚トリが難しかったですそれでも皆さんの頑張りでアマダイイトヨリホウボウ始めゲストのサバと顔を見れたのですが11時ごろから南西風が強くなり12時ごろ帰港しました！",
    "suion_raw": "16.8℃",
    "suishoku_raw": "",
    "color_raw": "",
    "source": "chowari/喜久丸",
    "tide_label": "中潮",
    "weather_text": "晴れ後時々曇り",
    "weather_detail": {
      "sunrise": "04:54",
      "sunset": "18:25",
      "moonrise": "15:12",
      "moonset": "02:52",
      "weather": "晴れ後時々曇り",
      "temp_high": "25℃",
      "temp_low": "14℃",
      "pressure": "1013.3hPa",
      "wind_dir": "南南西",
      "wind_speed": "5.6m/s",
      "wave_dir": "南",
      "wave_height": "0.7m/s",
      "water_temp": "16.8℃",
      "tide": "中潮",
      "moon_age": "10.6",
      "bi": "9.4"
    }
  },
  {
    "ship": "喜久丸",
    "area": "腰越港",
    "date": "2026/04/28",
    "trip_no": 1,
    "fish_raw": "サバ",
    "count_raw": "0～4匹",
    "size_raw": "30～42cm",
    "weight_raw": "",
    "tokki_raw": "外道",
    "point_raw": "神奈川県 鎌倉市 腰越漁港",
    "kanso_raw": "海上はややウネリがあり棚トリが難しかったですそれでも皆さんの頑張りでアマダイイトヨリホウボウ始めゲストのサバと顔を見れたのですが11時ごろから南西風が強くなり12時ごろ帰港しました！",
    "suion_raw": "16.8℃",
    "suishoku_raw": "",
    "color_raw": "",
    "source": "chowari/喜久丸",
    "tide_label": "中潮",
    "weather_text": "晴れ後時々曇り",
    "weather_detail": {
      "sunrise": "04:54",
      "sunset": "18:25",
      "moonrise": "15:12",
      "moonset": "02:52",
      "weather": "晴れ後時々曇り",
      "temp_high": "25℃",
      "temp_low": "14℃",
      "pressure": "1013.3hPa",
      "wind_dir": "南南西",
      "wind_speed": "5.6m/s",
      "wave_dir": "南",
      "wave_height": "0.7m/s",
      "water_temp": "16.8℃",
      "tide": "中潮",
      "moon_age": "10.6",
      "bi": "9.4"
    }
  },
  {
    "ship": "喜久丸",
    "area": "腰越港",
    "date": "2026/04/26",
    "trip_no": 1,
    "fish_raw": "タイ",
    "count_raw": "0～1匹",
    "size_raw": "0.50～2.00kg",
    "weight_raw": "",
    "tokki_raw": "メイン",
    "point_raw": "神奈川県 鎌倉市 腰越漁港",
    "kanso_raw": "ターゲットのマダイハナダイアマダイシロアマダイも顔を出してくれました他にゲストのアジサバと釣りガールの皆さんもお土産バッチリで楽しんでもらえて嬉しかったです！ PS明日は休船しますm(__)m",
    "suion_raw": "16.0℃",
    "suishoku_raw": "",
    "color_raw": "",
    "source": "chowari/喜久丸",
    "tide_label": "長潮",
    "weather_text": "晴れ後時々曇り",
    "weather_detail": {
      "sunrise": "04:56",
      "sunset": "18:24",
      "moonrise": "13:09",
      "moonset": "02:00",
      "weather": "晴れ後時々曇り",
      "temp_high": "21℃",
      "temp_low": "12℃",
      "pressure": "1022.1hPa",
      "wind_dir": "北北東",
      "wind_speed": "1.8m/s",
      "wave_dir": "南南東",
      "wave_height": "0.5m/s",
      "water_temp": "16.0℃",
      "tide": "長潮",
      "moon_age": "8.6",
      "bi": "8.0"
    }
  },
  {
    "ship": "喜久丸",
    "area": "腰越港",
    "date": "2026/04/26",
    "trip_no": 1,
    "fish_raw": "アマダイ",
    "count_raw": "0～1匹",
    "size_raw": "27～30cm",
    "weight_raw": "",
    "tokki_raw": "外道",
    "point_raw": "神奈川県 鎌倉市 腰越漁港",
    "kanso_raw": "ターゲットのマダイハナダイアマダイシロアマダイも顔を出してくれました他にゲストのアジサバと釣りガールの皆さんもお土産バッチリで楽しんでもらえて嬉しかったです！ PS明日は休船しますm(__)m",
    "suion_raw": "16.0℃",
    "suishoku_raw": "",
    "color_raw": "",
    "source": "chowari/喜久丸",
    "tide_label": "長潮",
    "weather_text": "晴れ後時々曇り",
    "weather_detail": {
      "sunrise": "04:56",
      "sunset": "18:24",
      "moonrise": "13:09",
      "moonset": "02:00",
      "weather": "晴れ後時々曇り",
      "temp_high": "21℃",
      "temp_low": "12℃",
      "pressure": "1022.1hPa",
      "wind_dir": "北北東",
      "wind_speed": "1.8m/s",
      "wave_dir": "南南東",
      "wave_height": "0.5m/s",
      "water_temp": "16.0℃",
      "tide": "長潮",
      "moon_age": "8.6",
      "bi": "8.0"
    }
  },
  {
    "ship": "喜久丸",
    "area": "腰越港",
    "date": "2026/04/26",
    "trip_no": 1,
    "fish_raw": "アジ",
    "count_raw": "0～4匹",
    "size_raw": "25～35cm",
    "weight_raw": "",
    "tokki_raw": "外道",
    "point_raw": "神奈川県 鎌倉市 腰越漁港",
    "kanso_raw": "ターゲットのマダイハナダイアマダイシロアマダイも顔を出してくれました他にゲストのアジサバと釣りガールの皆さんもお土産バッチリで楽しんでもらえて嬉しかったです！ PS明日は休船しますm(__)m",
    "suion_raw": "16.0℃",
    "suishoku_raw": "",
    "color_raw": "",
    "source": "chowari/喜久丸",
    "tide_label": "長潮",
    "weather_text": "晴れ後時々曇り",
    "weather_detail": {
      "sunrise": "04:56",
      "sunset": "18:24",
      "moonrise": "13:09",
      "moonset": "02:00",
      "weather": "晴れ後時々曇り",
      "temp_high": "21℃",
      "temp_low": "12℃",
      "pressure": "1022.1hPa",
      "wind_dir": "北北東",
      "wind_speed": "1.8m/s",
      "wave_dir": "南南東",
      "wave_height": "0.5m/s",
      "water_temp": "16.0℃",
      "tide": "長潮",
      "moon_age": "8.6",
      "bi": "8.0"
    }
  },
  {
    "ship": "喜久丸",
    "area": "腰越港",
    "date": "2026/04/26",
    "trip_no": 1,
    "fish_raw": "サバ",
    "count_raw": "3～10匹",
    "size_raw": "27～40cm",
    "weight_raw": "",
    "tokki_raw": "外道",
    "point_raw": "神奈川県 鎌倉市 腰越漁港",
    "kanso_raw": "ターゲットのマダイハナダイアマダイシロアマダイも顔を出してくれました他にゲストのアジサバと釣りガールの皆さんもお土産バッチリで楽しんでもらえて嬉しかったです！ PS明日は休船しますm(__)m",
    "suion_raw": "16.0℃",
    "suishoku_raw": "",
    "color_raw": "",
    "source": "chowari/喜久丸",
    "tide_label": "長潮",
    "weather_text": "晴れ後時々曇り",
    "weather_detail": {
      "sunrise": "04:56",
      "sunset": "18:24",
      "moonrise": "13:09",
      "moonset": "02:00",
      "weather": "晴れ後時々曇り",
      "temp_high": "21℃",
      "temp_low": "12℃",
      "pressure": "1022.1hPa",
      "wind_dir": "北北東",
      "wind_speed": "1.8m/s",
      "wave_dir": "南南東",
      "wave_height": "0.5m/s",
      "water_temp": "16.0℃",
      "tide": "長潮",
      "moon_age": "8.6",
      "bi": "8.0"
    }
  },
  {
    "ship": "喜久丸",
    "area": "腰越港",
    "date": "2026/04/23",
    "trip_no": 1,
    "fish_raw": "シロアマダイ",
    "count_raw": "0～1匹",
    "size_raw": "27～42cm",
    "weight_raw": "",
    "tokki_raw": "メイン",
    "point_raw": "神奈川県 鎌倉市 腰越漁港",
    "kanso_raw": "小雨が降りコンデションが今ひとつのなか皆さん頑張ってくれてハナダイシロアマダイイトヨリと顔を見ることが出来ましたが 魚影のわりにアタリが少なく少し残念でした！",
    "suion_raw": "15.7℃",
    "suishoku_raw": "",
    "color_raw": "",
    "source": "chowari/喜久丸",
    "tide_label": "小潮",
    "weather_text": "雨",
    "weather_detail": {
      "sunrise": "05:00",
      "sunset": "18:21",
      "moonrise": "09:42",
      "moonset": "00:01",
      "weather": "雨",
      "temp_high": "19℃",
      "temp_low": "13℃",
      "pressure": "1012.1hPa",
      "wind_dir": "北北東",
      "wind_speed": "2.3m/s",
      "wave_dir": "南南東",
      "wave_height": "0.6m/s",
      "water_temp": "15.7℃",
      "tide": "小潮",
      "moon_age": "5.6",
      "bi": "7.6"
    }
  },
  {
    "ship": "喜久丸",
    "area": "腰越港",
    "date": "2026/04/23",
    "trip_no": 1,
    "fish_raw": "イトヨリ",
    "count_raw": "1～3匹",
    "size_raw": "23～40cm",
    "weight_raw": "",
    "tokki_raw": "外道",
    "point_raw": "神奈川県 鎌倉市 腰越漁港",
    "kanso_raw": "小雨が降りコンデションが今ひとつのなか皆さん頑張ってくれてハナダイシロアマダイイトヨリと顔を見ることが出来ましたが 魚影のわりにアタリが少なく少し残念でした！",
    "suion_raw": "15.7℃",
    "suishoku_raw": "",
    "color_raw": "",
    "source": "chowari/喜久丸",
    "tide_label": "小潮",
    "weather_text": "雨",
    "weather_detail": {
      "sunrise": "05:00",
      "sunset": "18:21",
      "moonrise": "09:42",
      "moonset": "00:01",
      "weather": "雨",
      "temp_high": "19℃",
      "temp_low": "13℃",
      "pressure": "1012.1hPa",
      "wind_dir": "北北東",
      "wind_speed": "2.3m/s",
      "wave_dir": "南南東",
      "wave_height": "0.6m/s",
      "water_temp": "15.7℃",
      "tide": "小潮",
      "moon_age": "5.6",
      "bi": "7.6"
    }
  },
  {
    "ship": "喜久丸",
    "area": "腰越港",
    "date": "2026/04/22",
    "trip_no": 1,
    "fish_raw": "アマダイ",
    "count_raw": "0～3匹",
    "size_raw": "25～30cm",
    "weight_raw": "",
    "tokki_raw": "メイン",
    "point_raw": "神奈川県 鎌倉市 腰越漁港",
    "kanso_raw": "ウィリーアマダイ五目 アマダイ25~30㎝0~3枚イトヨリ23~32㎝0~1枚アジ28~35㎝3~6匹マダイサバEtc ターゲットのマダイアマダイイトヨリ始め良型アジとお土産はキープ出来ましたが10時30分ごろから南西風が強くなり11時ごろ沖上がり帰港しました！",
    "suion_raw": "15.5℃",
    "suishoku_raw": "",
    "color_raw": "",
    "source": "chowari/喜久丸",
    "tide_label": "中潮",
    "weather_text": "晴れ後時々曇り",
    "weather_detail": {
      "sunrise": "05:01",
      "sunset": "18:20",
      "moonrise": "08:32",
      "moonset": "",
      "weather": "晴れ後時々曇り",
      "temp_high": "23℃",
      "temp_low": "13℃",
      "pressure": "1017.4hPa",
      "wind_dir": "南南西",
      "wind_speed": "3.4m/s",
      "wave_dir": "南南東",
      "wave_height": "0.6m/s",
      "water_temp": "15.5℃",
      "tide": "中潮",
      "moon_age": "4.6",
      "bi": "8.8"
    }
  },
  {
    "ship": "喜久丸",
    "area": "腰越港",
    "date": "2026/04/22",
    "trip_no": 1,
    "fish_raw": "イトヨリ",
    "count_raw": "0～1匹",
    "size_raw": "23～30cm",
    "weight_raw": "",
    "tokki_raw": "外道",
    "point_raw": "神奈川県 鎌倉市 腰越漁港",
    "kanso_raw": "ウィリーアマダイ五目 アマダイ25~30㎝0~3枚イトヨリ23~32㎝0~1枚アジ28~35㎝3~6匹マダイサバEtc ターゲットのマダイアマダイイトヨリ始め良型アジとお土産はキープ出来ましたが10時30分ごろから南西風が強くなり11時ごろ沖上がり帰港しました！",
    "suion_raw": "15.5℃",
    "suishoku_raw": "",
    "color_raw": "",
    "source": "chowari/喜久丸",
    "tide_label": "中潮",
    "weather_text": "晴れ後時々曇り",
    "weather_detail": {
      "sunrise": "05:01",
      "sunset": "18:20",
      "moonrise": "08:32",
      "moonset": "",
      "weather": "晴れ後時々曇り",
      "temp_high": "23℃",
      "temp_low": "13℃",
      "pressure": "1017.4hPa",
      "wind_dir": "南南西",
      "wind_speed": "3.4m/s",
      "wave_dir": "南南東",
      "wave_height": "0.6m/s",
      "water_temp": "15.5℃",
      "tide": "中潮",
      "moon_age": "4.6",
      "bi": "8.8"
    }
  },
  {
    "ship": "喜久丸",
    "area": "腰越港",
    "date": "2026/04/22",
    "trip_no": 1,
    "fish_raw": "アジ",
    "count_raw": "3～6匹",
    "size_raw": "28～35cm",
    "weight_raw": "",
    "tokki_raw": "外道",
    "point_raw": "神奈川県 鎌倉市 腰越漁港",
    "kanso_raw": "ウィリーアマダイ五目 アマダイ25~30㎝0~3枚イトヨリ23~32㎝0~1枚アジ28~35㎝3~6匹マダイサバEtc ターゲットのマダイアマダイイトヨリ始め良型アジとお土産はキープ出来ましたが10時30分ごろから南西風が強くなり11時ごろ沖上がり帰港しました！",
    "suion_raw": "15.5℃",
    "suishoku_raw": "",
    "color_raw": "",
    "source": "chowari/喜久丸",
    "tide_label": "中潮",
    "weather_text": "晴れ後時々曇り",
    "weather_detail": {
      "sunrise": "05:01",
      "sunset": "18:20",
      "moonrise": "08:32",
      "moonset": "",
      "weather": "晴れ後時々曇り",
      "temp_high": "23℃",
      "temp_low": "13℃",
      "pressure": "1017.4hPa",
      "wind_dir": "南南西",
      "wind_speed": "3.4m/s",
      "wave_dir": "南南東",
      "wave_height": "0.6m/s",
      "water_temp": "15.5℃",
      "tide": "中潮",
      "moon_age": "4.6",
      "bi": "8.8"
    }
  },
  {
    "ship": "喜久丸",
    "area": "腰越港",
    "date": "2026/04/20",
    "trip_no": 1,
    "fish_raw": "イトヨリ",
    "count_raw": "0～3匹",
    "size_raw": "20～35cm",
    "weight_raw": "",
    "tokki_raw": "メイン",
    "point_raw": "神奈川県 鎌倉市 腰越漁港",
    "kanso_raw": "残念でしたがアマダイは顔を見れずそれでもイトヨリホウボウ始め良型アジサバと皆さんお土産はバッチリ楽しんでもらえて良かったです！ PS明日は天気予報が悪いので休船は微妙です！",
    "suion_raw": "15.2℃",
    "suishoku_raw": "",
    "color_raw": "",
    "source": "chowari/喜久丸",
    "tide_label": "中潮",
    "weather_text": "晴れ時々曇り",
    "weather_detail": {
      "sunrise": "05:03",
      "sunset": "18:19",
      "moonrise": "06:31",
      "moonset": "21:55",
      "weather": "晴れ時々曇り",
      "temp_high": "24℃",
      "temp_low": "14℃",
      "pressure": "1017.2hPa",
      "wind_dir": "北東",
      "wind_speed": "2.0m/s",
      "wave_dir": "南南東",
      "wave_height": "0.9m/s",
      "water_temp": "15.2℃",
      "tide": "中潮",
      "moon_age": "2.6",
      "bi": "8.4"
    }
  },
  {
    "ship": "喜久丸",
    "area": "腰越港",
    "date": "2026/04/20",
    "trip_no": 1,
    "fish_raw": "アジ",
    "count_raw": "3～11匹",
    "size_raw": "25～40cm",
    "weight_raw": "",
    "tokki_raw": "外道",
    "point_raw": "神奈川県 鎌倉市 腰越漁港",
    "kanso_raw": "残念でしたがアマダイは顔を見れずそれでもイトヨリホウボウ始め良型アジサバと皆さんお土産はバッチリ楽しんでもらえて良かったです！ PS明日は天気予報が悪いので休船は微妙です！",
    "suion_raw": "15.2℃",
    "suishoku_raw": "",
    "color_raw": "",
    "source": "chowari/喜久丸",
    "tide_label": "中潮",
    "weather_text": "晴れ時々曇り",
    "weather_detail": {
      "sunrise": "05:03",
      "sunset": "18:19",
      "moonrise": "06:31",
      "moonset": "21:55",
      "weather": "晴れ時々曇り",
      "temp_high": "24℃",
      "temp_low": "14℃",
      "pressure": "1017.2hPa",
      "wind_dir": "北東",
      "wind_speed": "2.0m/s",
      "wave_dir": "南南東",
      "wave_height": "0.9m/s",
      "water_temp": "15.2℃",
      "tide": "中潮",
      "moon_age": "2.6",
      "bi": "8.4"
    }
  },
  {
    "ship": "喜久丸",
    "area": "腰越港",
    "date": "2026/04/20",
    "trip_no": 1,
    "fish_raw": "サバ",
    "count_raw": "3～8匹",
    "size_raw": "20～40cm",
    "weight_raw": "",
    "tokki_raw": "外道",
    "point_raw": "神奈川県 鎌倉市 腰越漁港",
    "kanso_raw": "残念でしたがアマダイは顔を見れずそれでもイトヨリホウボウ始め良型アジサバと皆さんお土産はバッチリ楽しんでもらえて良かったです！ PS明日は天気予報が悪いので休船は微妙です！",
    "suion_raw": "15.2℃",
    "suishoku_raw": "",
    "color_raw": "",
    "source": "chowari/喜久丸",
    "tide_label": "中潮",
    "weather_text": "晴れ時々曇り",
    "weather_detail": {
      "sunrise": "05:03",
      "sunset": "18:19",
      "moonrise": "06:31",
      "moonset": "21:55",
      "weather": "晴れ時々曇り",
      "temp_high": "24℃",
      "temp_low": "14℃",
      "pressure": "1017.2hPa",
      "wind_dir": "北東",
      "wind_speed": "2.0m/s",
      "wave_dir": "南南東",
      "wave_height": "0.9m/s",
      "water_temp": "15.2℃",
      "tide": "中潮",
      "moon_age": "2.6",
      "bi": "8.4"
    }
  },
  {
    "ship": "喜久丸",
    "area": "腰越港",
    "date": "2026/04/19",
    "trip_no": 1,
    "fish_raw": "アマダイ",
    "count_raw": "0～1匹",
    "size_raw": "28～33cm",
    "weight_raw": "",
    "tokki_raw": "メイン",
    "point_raw": "神奈川県 鎌倉市 腰越漁港",
    "kanso_raw": "アマダイシロアマダイクロダイメジナ イトヨリ(船中20枚以上)始め良型アジサバとお土産もバッチリ天気にも恵まれ嬉しい帰港です！",
    "suion_raw": "14.8℃",
    "suishoku_raw": "",
    "color_raw": "",
    "source": "chowari/喜久丸",
    "tide_label": "中潮",
    "weather_text": "曇り時々晴れ",
    "weather_detail": {
      "sunrise": "05:05",
      "sunset": "18:18",
      "moonrise": "05:45",
      "moonset": "20:40",
      "weather": "曇り時々晴れ",
      "temp_high": "24℃",
      "temp_low": "13℃",
      "pressure": "1016.4hPa",
      "wind_dir": "北東",
      "wind_speed": "2.1m/s",
      "wave_dir": "南南東",
      "wave_height": "1.2m/s",
      "water_temp": "14.8℃",
      "tide": "中潮",
      "moon_age": "1.6",
      "bi": "7.7"
    }
  },
  {
    "ship": "喜久丸",
    "area": "腰越港",
    "date": "2026/04/19",
    "trip_no": 1,
    "fish_raw": "シロアマダイ",
    "count_raw": "0～1匹",
    "size_raw": "33～38cm",
    "weight_raw": "",
    "tokki_raw": "外道",
    "point_raw": "神奈川県 鎌倉市 腰越漁港",
    "kanso_raw": "アマダイシロアマダイクロダイメジナ イトヨリ(船中20枚以上)始め良型アジサバとお土産もバッチリ天気にも恵まれ嬉しい帰港です！",
    "suion_raw": "14.8℃",
    "suishoku_raw": "",
    "color_raw": "",
    "source": "chowari/喜久丸",
    "tide_label": "中潮",
    "weather_text": "曇り時々晴れ",
    "weather_detail": {
      "sunrise": "05:05",
      "sunset": "18:18",
      "moonrise": "05:45",
      "moonset": "20:40",
      "weather": "曇り時々晴れ",
      "temp_high": "24℃",
      "temp_low": "13℃",
      "pressure": "1016.4hPa",
      "wind_dir": "北東",
      "wind_speed": "2.1m/s",
      "wave_dir": "南南東",
      "wave_height": "1.2m/s",
      "water_temp": "14.8℃",
      "tide": "中潮",
      "moon_age": "1.6",
      "bi": "7.7"
    }
  },
  {
    "ship": "喜久丸",
    "area": "腰越港",
    "date": "2026/04/19",
    "trip_no": 1,
    "fish_raw": "メジナ",
    "count_raw": "0～2匹",
    "size_raw": "0.50～0.70kg",
    "weight_raw": "",
    "tokki_raw": "外道",
    "point_raw": "神奈川県 鎌倉市 腰越漁港",
    "kanso_raw": "アマダイシロアマダイクロダイメジナ イトヨリ(船中20枚以上)始め良型アジサバとお土産もバッチリ天気にも恵まれ嬉しい帰港です！",
    "suion_raw": "14.8℃",
    "suishoku_raw": "",
    "color_raw": "",
    "source": "chowari/喜久丸",
    "tide_label": "中潮",
    "weather_text": "曇り時々晴れ",
    "weather_detail": {
      "sunrise": "05:05",
      "sunset": "18:18",
      "moonrise": "05:45",
      "moonset": "20:40",
      "weather": "曇り時々晴れ",
      "temp_high": "24℃",
      "temp_low": "13℃",
      "pressure": "1016.4hPa",
      "wind_dir": "北東",
      "wind_speed": "2.1m/s",
      "wave_dir": "南南東",
      "wave_height": "1.2m/s",
      "water_temp": "14.8℃",
      "tide": "中潮",
      "moon_age": "1.6",
      "bi": "7.7"
    }
  },
  {
    "ship": "喜久丸",
    "area": "腰越港",
    "date": "2026/04/19",
    "trip_no": 1,
    "fish_raw": "イトヨリ",
    "count_raw": "0～3匹",
    "size_raw": "23～38cm",
    "weight_raw": "",
    "tokki_raw": "外道",
    "point_raw": "神奈川県 鎌倉市 腰越漁港",
    "kanso_raw": "アマダイシロアマダイクロダイメジナ イトヨリ(船中20枚以上)始め良型アジサバとお土産もバッチリ天気にも恵まれ嬉しい帰港です！",
    "suion_raw": "14.8℃",
    "suishoku_raw": "",
    "color_raw": "",
    "source": "chowari/喜久丸",
    "tide_label": "中潮",
    "weather_text": "曇り時々晴れ",
    "weather_detail": {
      "sunrise": "05:05",
      "sunset": "18:18",
      "moonrise": "05:45",
      "moonset": "20:40",
      "weather": "曇り時々晴れ",
      "temp_high": "24℃",
      "temp_low": "13℃",
      "pressure": "1016.4hPa",
      "wind_dir": "北東",
      "wind_speed": "2.1m/s",
      "wave_dir": "南南東",
      "wave_height": "1.2m/s",
      "water_temp": "14.8℃",
      "tide": "中潮",
      "moon_age": "1.6",
      "bi": "7.7"
    }
  },
  {
    "ship": "喜久丸",
    "area": "腰越港",
    "date": "2026/04/19",
    "trip_no": 1,
    "fish_raw": "アジ",
    "count_raw": "0～7匹",
    "size_raw": "27～40cm",
    "weight_raw": "",
    "tokki_raw": "外道",
    "point_raw": "神奈川県 鎌倉市 腰越漁港",
    "kanso_raw": "アマダイシロアマダイクロダイメジナ イトヨリ(船中20枚以上)始め良型アジサバとお土産もバッチリ天気にも恵まれ嬉しい帰港です！",
    "suion_raw": "14.8℃",
    "suishoku_raw": "",
    "color_raw": "",
    "source": "chowari/喜久丸",
    "tide_label": "中潮",
    "weather_text": "曇り時々晴れ",
    "weather_detail": {
      "sunrise": "05:05",
      "sunset": "18:18",
      "moonrise": "05:45",
      "moonset": "20:40",
      "weather": "曇り時々晴れ",
      "temp_high": "24℃",
      "temp_low": "13℃",
      "pressure": "1016.4hPa",
      "wind_dir": "北東",
      "wind_speed": "2.1m/s",
      "wave_dir": "南南東",
      "wave_height": "1.2m/s",
      "water_temp": "14.8℃",
      "tide": "中潮",
      "moon_age": "1.6",
      "bi": "7.7"
    }
  },
  {
    "ship": "喜久丸",
    "area": "腰越港",
    "date": "2026/04/19",
    "trip_no": 1,
    "fish_raw": "サバ",
    "count_raw": "3～8匹",
    "size_raw": "25～42cm",
    "weight_raw": "",
    "tokki_raw": "外道",
    "point_raw": "神奈川県 鎌倉市 腰越漁港",
    "kanso_raw": "アマダイシロアマダイクロダイメジナ イトヨリ(船中20枚以上)始め良型アジサバとお土産もバッチリ天気にも恵まれ嬉しい帰港です！",
    "suion_raw": "14.8℃",
    "suishoku_raw": "",
    "color_raw": "",
    "source": "chowari/喜久丸",
    "tide_label": "中潮",
    "weather_text": "曇り時々晴れ",
    "weather_detail": {
      "sunrise": "05:05",
      "sunset": "18:18",
      "moonrise": "05:45",
      "moonset": "20:40",
      "weather": "曇り時々晴れ",
      "temp_high": "24℃",
      "temp_low": "13℃",
      "pressure": "1016.4hPa",
      "wind_dir": "北東",
      "wind_speed": "2.1m/s",
      "wave_dir": "南南東",
      "wave_height": "1.2m/s",
      "water_temp": "14.8℃",
      "tide": "中潮",
      "moon_age": "1.6",
      "bi": "7.7"
    }
  },
  {
    "ship": "喜久丸",
    "area": "腰越港",
    "date": "2026/04/17",
    "trip_no": 1,
    "fish_raw": "シロアマダイ",
    "count_raw": "合計1匹",
    "size_raw": "40cm",
    "weight_raw": "",
    "tokki_raw": "メイン",
    "point_raw": "神奈川県 鎌倉市 腰越漁港",
    "kanso_raw": "ターゲットの良型シロアマダイアマダイマダイクロダイイトヨリとまずまずでした！",
    "suion_raw": "14.1℃",
    "suishoku_raw": "",
    "color_raw": "",
    "source": "chowari/喜久丸",
    "tide_label": "大潮",
    "weather_text": "晴れ後時々曇り",
    "weather_detail": {
      "sunrise": "05:07",
      "sunset": "18:16",
      "moonrise": "04:34",
      "moonset": "18:08",
      "weather": "晴れ後時々曇り",
      "temp_high": "21℃",
      "temp_low": "11℃",
      "pressure": "1024.0hPa",
      "wind_dir": "北東",
      "wind_speed": "4.0m/s",
      "wave_dir": "南南東",
      "wave_height": "0.9m/s",
      "water_temp": "14.1℃",
      "tide": "大潮",
      "moon_age": "29.1",
      "bi": "10.1"
    }
  },
  {
    "ship": "喜久丸",
    "area": "腰越港",
    "date": "2026/04/17",
    "trip_no": 1,
    "fish_raw": "アマダイ",
    "count_raw": "1～3匹",
    "size_raw": "28～30cm",
    "weight_raw": "",
    "tokki_raw": "外道",
    "point_raw": "神奈川県 鎌倉市 腰越漁港",
    "kanso_raw": "ターゲットの良型シロアマダイアマダイマダイクロダイイトヨリとまずまずでした！",
    "suion_raw": "14.1℃",
    "suishoku_raw": "",
    "color_raw": "",
    "source": "chowari/喜久丸",
    "tide_label": "大潮",
    "weather_text": "晴れ後時々曇り",
    "weather_detail": {
      "sunrise": "05:07",
      "sunset": "18:16",
      "moonrise": "04:34",
      "moonset": "18:08",
      "weather": "晴れ後時々曇り",
      "temp_high": "21℃",
      "temp_low": "11℃",
      "pressure": "1024.0hPa",
      "wind_dir": "北東",
      "wind_speed": "4.0m/s",
      "wave_dir": "南南東",
      "wave_height": "0.9m/s",
      "water_temp": "14.1℃",
      "tide": "大潮",
      "moon_age": "29.1",
      "bi": "10.1"
    }
  },
  {
    "ship": "喜久丸",
    "area": "腰越港",
    "date": "2026/04/17",
    "trip_no": 1,
    "fish_raw": "クロダイ",
    "count_raw": "0～2匹",
    "size_raw": "0.60～0.80kg",
    "weight_raw": "",
    "tokki_raw": "外道",
    "point_raw": "神奈川県 鎌倉市 腰越漁港",
    "kanso_raw": "ターゲットの良型シロアマダイアマダイマダイクロダイイトヨリとまずまずでした！",
    "suion_raw": "14.1℃",
    "suishoku_raw": "",
    "color_raw": "",
    "source": "chowari/喜久丸",
    "tide_label": "大潮",
    "weather_text": "晴れ後時々曇り",
    "weather_detail": {
      "sunrise": "05:07",
      "sunset": "18:16",
      "moonrise": "04:34",
      "moonset": "18:08",
      "weather": "晴れ後時々曇り",
      "temp_high": "21℃",
      "temp_low": "11℃",
      "pressure": "1024.0hPa",
      "wind_dir": "北東",
      "wind_speed": "4.0m/s",
      "wave_dir": "南南東",
      "wave_height": "0.9m/s",
      "water_temp": "14.1℃",
      "tide": "大潮",
      "moon_age": "29.1",
      "bi": "10.1"
    }
  },
  {
    "ship": "喜久丸",
    "area": "腰越港",
    "date": "2026/04/17",
    "trip_no": 1,
    "fish_raw": "タイ",
    "count_raw": "合計1匹",
    "size_raw": "0.50kg",
    "weight_raw": "",
    "tokki_raw": "外道",
    "point_raw": "神奈川県 鎌倉市 腰越漁港",
    "kanso_raw": "ターゲットの良型シロアマダイアマダイマダイクロダイイトヨリとまずまずでした！",
    "suion_raw": "14.1℃",
    "suishoku_raw": "",
    "color_raw": "",
    "source": "chowari/喜久丸",
    "tide_label": "大潮",
    "weather_text": "晴れ後時々曇り",
    "weather_detail": {
      "sunrise": "05:07",
      "sunset": "18:16",
      "moonrise": "04:34",
      "moonset": "18:08",
      "weather": "晴れ後時々曇り",
      "temp_high": "21℃",
      "temp_low": "11℃",
      "pressure": "1024.0hPa",
      "wind_dir": "北東",
      "wind_speed": "4.0m/s",
      "wave_dir": "南南東",
      "wave_height": "0.9m/s",
      "water_temp": "14.1℃",
      "tide": "大潮",
      "moon_age": "29.1",
      "bi": "10.1"
    }
  },
  {
    "ship": "喜久丸",
    "area": "腰越港",
    "date": "2026/04/17",
    "trip_no": 1,
    "fish_raw": "イトヨリ",
    "count_raw": "1～2匹",
    "size_raw": "35～43cm",
    "weight_raw": "",
    "tokki_raw": "外道",
    "point_raw": "神奈川県 鎌倉市 腰越漁港",
    "kanso_raw": "ターゲットの良型シロアマダイアマダイマダイクロダイイトヨリとまずまずでした！",
    "suion_raw": "14.1℃",
    "suishoku_raw": "",
    "color_raw": "",
    "source": "chowari/喜久丸",
    "tide_label": "大潮",
    "weather_text": "晴れ後時々曇り",
    "weather_detail": {
      "sunrise": "05:07",
      "sunset": "18:16",
      "moonrise": "04:34",
      "moonset": "18:08",
      "weather": "晴れ後時々曇り",
      "temp_high": "21℃",
      "temp_low": "11℃",
      "pressure": "1024.0hPa",
      "wind_dir": "北東",
      "wind_speed": "4.0m/s",
      "wave_dir": "南南東",
      "wave_height": "0.9m/s",
      "water_temp": "14.1℃",
      "tide": "大潮",
      "moon_age": "29.1",
      "bi": "10.1"
    }
  },
  {
    "ship": "喜久丸",
    "area": "腰越港",
    "date": "2026/04/14",
    "trip_no": 1,
    "fish_raw": "カサゴ",
    "count_raw": "0～2匹",
    "size_raw": "25～35cm",
    "weight_raw": "",
    "tokki_raw": "メイン",
    "point_raw": "神奈川県 鎌倉市 腰越漁港",
    "kanso_raw": "カサゴ他にゲストのアジサバのお土産はバッチリでした！",
    "suion_raw": "14.0℃",
    "suishoku_raw": "",
    "color_raw": "",
    "source": "chowari/喜久丸",
    "tide_label": "中潮",
    "weather_text": "晴れ後時々曇り",
    "weather_detail": {
      "sunrise": "05:11",
      "sunset": "18:14",
      "moonrise": "03:11",
      "moonset": "14:43",
      "weather": "晴れ後時々曇り",
      "temp_high": "23℃",
      "temp_low": "13℃",
      "pressure": "1017.5hPa",
      "wind_dir": "北北東",
      "wind_speed": "2.3m/s",
      "wave_dir": "南南東",
      "wave_height": "0.4m/s",
      "water_temp": "14.0℃",
      "tide": "中潮",
      "moon_age": "26.1",
      "bi": "9.7"
    }
  },
  {
    "ship": "喜久丸",
    "area": "腰越港",
    "date": "2026/04/14",
    "trip_no": 1,
    "fish_raw": "アジ",
    "count_raw": "4～10匹",
    "size_raw": "25～40cm",
    "weight_raw": "",
    "tokki_raw": "外道",
    "point_raw": "神奈川県 鎌倉市 腰越漁港",
    "kanso_raw": "カサゴ他にゲストのアジサバのお土産はバッチリでした！",
    "suion_raw": "14.0℃",
    "suishoku_raw": "",
    "color_raw": "",
    "source": "chowari/喜久丸",
    "tide_label": "中潮",
    "weather_text": "晴れ後時々曇り",
    "weather_detail": {
      "sunrise": "05:11",
      "sunset": "18:14",
      "moonrise": "03:11",
      "moonset": "14:43",
      "weather": "晴れ後時々曇り",
      "temp_high": "23℃",
      "temp_low": "13℃",
      "pressure": "1017.5hPa",
      "wind_dir": "北北東",
      "wind_speed": "2.3m/s",
      "wave_dir": "南南東",
      "wave_height": "0.4m/s",
      "water_temp": "14.0℃",
      "tide": "中潮",
      "moon_age": "26.1",
      "bi": "9.7"
    }
  },
  {
    "ship": "喜久丸",
    "area": "腰越港",
    "date": "2026/04/14",
    "trip_no": 1,
    "fish_raw": "サバ",
    "count_raw": "3～5匹",
    "size_raw": "25～35cm",
    "weight_raw": "",
    "tokki_raw": "外道",
    "point_raw": "神奈川県 鎌倉市 腰越漁港",
    "kanso_raw": "カサゴ他にゲストのアジサバのお土産はバッチリでした！",
    "suion_raw": "14.0℃",
    "suishoku_raw": "",
    "color_raw": "",
    "source": "chowari/喜久丸",
    "tide_label": "中潮",
    "weather_text": "晴れ後時々曇り",
    "weather_detail": {
      "sunrise": "05:11",
      "sunset": "18:14",
      "moonrise": "03:11",
      "moonset": "14:43",
      "weather": "晴れ後時々曇り",
      "temp_high": "23℃",
      "temp_low": "13℃",
      "pressure": "1017.5hPa",
      "wind_dir": "北北東",
      "wind_speed": "2.3m/s",
      "wave_dir": "南南東",
      "wave_height": "0.4m/s",
      "water_temp": "14.0℃",
      "tide": "中潮",
      "moon_age": "26.1",
      "bi": "9.7"
    }
  },
  {
    "ship": "喜久丸",
    "area": "腰越港",
    "date": "2026/04/13",
    "trip_no": 1,
    "fish_raw": "シロアマダイ",
    "count_raw": "合計1匹",
    "size_raw": "28cm",
    "weight_raw": "",
    "tokki_raw": "メイン",
    "point_raw": "神奈川県 鎌倉市 腰越漁港",
    "kanso_raw": "釣りガールの皆さんもイトヨリアジの釣果に恵まれ楽しんでもらえて良かったです他にシロアマダイもキープ出来ました！",
    "suion_raw": "13.8℃",
    "suishoku_raw": "",
    "color_raw": "",
    "source": "chowari/喜久丸",
    "tide_label": "若潮",
    "weather_text": "曇り",
    "weather_detail": {
      "sunrise": "05:12",
      "sunset": "18:13",
      "moonrise": "02:43",
      "moonset": "13:39",
      "weather": "曇り",
      "temp_high": "23℃",
      "temp_low": "14℃",
      "pressure": "1017.4hPa",
      "wind_dir": "南南東",
      "wind_speed": "0.4m/s",
      "wave_dir": "南南東",
      "wave_height": "0.6m/s",
      "water_temp": "13.8℃",
      "tide": "若潮",
      "moon_age": "25.1",
      "bi": "9.0"
    }
  },
  {
    "ship": "喜久丸",
    "area": "腰越港",
    "date": "2026/04/13",
    "trip_no": 1,
    "fish_raw": "アジ",
    "count_raw": "1～7匹",
    "size_raw": "30～40cm",
    "weight_raw": "",
    "tokki_raw": "外道",
    "point_raw": "神奈川県 鎌倉市 腰越漁港",
    "kanso_raw": "釣りガールの皆さんもイトヨリアジの釣果に恵まれ楽しんでもらえて良かったです他にシロアマダイもキープ出来ました！",
    "suion_raw": "13.8℃",
    "suishoku_raw": "",
    "color_raw": "",
    "source": "chowari/喜久丸",
    "tide_label": "若潮",
    "weather_text": "曇り",
    "weather_detail": {
      "sunrise": "05:12",
      "sunset": "18:13",
      "moonrise": "02:43",
      "moonset": "13:39",
      "weather": "曇り",
      "temp_high": "23℃",
      "temp_low": "14℃",
      "pressure": "1017.4hPa",
      "wind_dir": "南南東",
      "wind_speed": "0.4m/s",
      "wave_dir": "南南東",
      "wave_height": "0.6m/s",
      "water_temp": "13.8℃",
      "tide": "若潮",
      "moon_age": "25.1",
      "bi": "9.0"
    }
  },
  {
    "ship": "喜久丸",
    "area": "腰越港",
    "date": "2026/04/12",
    "trip_no": 1,
    "fish_raw": "アマダイ",
    "count_raw": "0～1匹",
    "size_raw": "25～28cm",
    "weight_raw": "",
    "tokki_raw": "メイン",
    "point_raw": "神奈川県 鎌倉市 腰越漁港",
    "kanso_raw": "ゲストのアジサバには恵まれ他にアマダイイトヨリハナダイマハタと顔を出してくれました！ PSアジ0匹の方は船酔いでダウンされてました。",
    "suion_raw": "13.7℃",
    "suishoku_raw": "",
    "color_raw": "",
    "source": "chowari/喜久丸",
    "tide_label": "長潮",
    "weather_text": "晴れ",
    "weather_detail": {
      "sunrise": "05:14",
      "sunset": "18:12",
      "moonrise": "02:12",
      "moonset": "12:35",
      "weather": "晴れ",
      "temp_high": "23℃",
      "temp_low": "12℃",
      "pressure": "1014.4hPa",
      "wind_dir": "東南東",
      "wind_speed": "1.5m/s",
      "wave_dir": "南",
      "wave_height": "0.6m/s",
      "water_temp": "13.7℃",
      "tide": "長潮",
      "moon_age": "24.1",
      "bi": "8.0"
    }
  },
  {
    "ship": "喜久丸",
    "area": "腰越港",
    "date": "2026/04/12",
    "trip_no": 1,
    "fish_raw": "イトヨリ",
    "count_raw": "0～2匹",
    "size_raw": "20～27cm",
    "weight_raw": "",
    "tokki_raw": "外道",
    "point_raw": "神奈川県 鎌倉市 腰越漁港",
    "kanso_raw": "ゲストのアジサバには恵まれ他にアマダイイトヨリハナダイマハタと顔を出してくれました！ PSアジ0匹の方は船酔いでダウンされてました。",
    "suion_raw": "13.7℃",
    "suishoku_raw": "",
    "color_raw": "",
    "source": "chowari/喜久丸",
    "tide_label": "長潮",
    "weather_text": "晴れ",
    "weather_detail": {
      "sunrise": "05:14",
      "sunset": "18:12",
      "moonrise": "02:12",
      "moonset": "12:35",
      "weather": "晴れ",
      "temp_high": "23℃",
      "temp_low": "12℃",
      "pressure": "1014.4hPa",
      "wind_dir": "東南東",
      "wind_speed": "1.5m/s",
      "wave_dir": "南",
      "wave_height": "0.6m/s",
      "water_temp": "13.7℃",
      "tide": "長潮",
      "moon_age": "24.1",
      "bi": "8.0"
    }
  },
  {
    "ship": "喜久丸",
    "area": "腰越港",
    "date": "2026/04/12",
    "trip_no": 1,
    "fish_raw": "アジ",
    "count_raw": "0～8匹",
    "size_raw": "23～38cm",
    "weight_raw": "",
    "tokki_raw": "外道",
    "point_raw": "神奈川県 鎌倉市 腰越漁港",
    "kanso_raw": "ゲストのアジサバには恵まれ他にアマダイイトヨリハナダイマハタと顔を出してくれました！ PSアジ0匹の方は船酔いでダウンされてました。",
    "suion_raw": "13.7℃",
    "suishoku_raw": "",
    "color_raw": "",
    "source": "chowari/喜久丸",
    "tide_label": "長潮",
    "weather_text": "晴れ",
    "weather_detail": {
      "sunrise": "05:14",
      "sunset": "18:12",
      "moonrise": "02:12",
      "moonset": "12:35",
      "weather": "晴れ",
      "temp_high": "23℃",
      "temp_low": "12℃",
      "pressure": "1014.4hPa",
      "wind_dir": "東南東",
      "wind_speed": "1.5m/s",
      "wave_dir": "南",
      "wave_height": "0.6m/s",
      "water_temp": "13.7℃",
      "tide": "長潮",
      "moon_age": "24.1",
      "bi": "8.0"
    }
  },
  {
    "ship": "喜久丸",
    "area": "腰越港",
    "date": "2026/04/09",
    "trip_no": 1,
    "fish_raw": "アジ",
    "count_raw": "0～7匹",
    "size_raw": "25～38cm",
    "weight_raw": "",
    "tokki_raw": "メイン",
    "point_raw": "神奈川県 鎌倉市 腰越漁港",
    "kanso_raw": "朝のうちは底荒れの影響か魚影は濃いのですがアタリが遠く苦戦しましたが後半にかけてアタリも出だしアジサバキントキカサゴと何とかお土産はキープ出来て良かったです！ PS明日は天気予報も悪いので休船します",
    "suion_raw": "13.4℃",
    "suishoku_raw": "",
    "color_raw": "",
    "source": "chowari/喜久丸",
    "tide_label": "小潮",
    "weather_text": "晴れ後時々曇り",
    "weather_detail": {
      "sunrise": "05:18",
      "sunset": "18:10",
      "moonrise": "00:11",
      "moonset": "09:32",
      "weather": "晴れ後時々曇り",
      "temp_high": "20℃",
      "temp_low": "12℃",
      "pressure": "1022.2hPa",
      "wind_dir": "南南西",
      "wind_speed": "5.6m/s",
      "wave_dir": "南",
      "wave_height": "0.7m/s",
      "water_temp": "13.4℃",
      "tide": "小潮",
      "moon_age": "21.1",
      "bi": "7.1"
    }
  },
  {
    "ship": "喜久丸",
    "area": "腰越港",
    "date": "2026/04/09",
    "trip_no": 1,
    "fish_raw": "サバ",
    "count_raw": "0～3匹",
    "size_raw": "25～28cm",
    "weight_raw": "",
    "tokki_raw": "外道",
    "point_raw": "神奈川県 鎌倉市 腰越漁港",
    "kanso_raw": "朝のうちは底荒れの影響か魚影は濃いのですがアタリが遠く苦戦しましたが後半にかけてアタリも出だしアジサバキントキカサゴと何とかお土産はキープ出来て良かったです！ PS明日は天気予報も悪いので休船します",
    "suion_raw": "13.4℃",
    "suishoku_raw": "",
    "color_raw": "",
    "source": "chowari/喜久丸",
    "tide_label": "小潮",
    "weather_text": "晴れ後時々曇り",
    "weather_detail": {
      "sunrise": "05:18",
      "sunset": "18:10",
      "moonrise": "00:11",
      "moonset": "09:32",
      "weather": "晴れ後時々曇り",
      "temp_high": "20℃",
      "temp_low": "12℃",
      "pressure": "1022.2hPa",
      "wind_dir": "南南西",
      "wind_speed": "5.6m/s",
      "wave_dir": "南",
      "wave_height": "0.7m/s",
      "water_temp": "13.4℃",
      "tide": "小潮",
      "moon_age": "21.1",
      "bi": "7.1"
    }
  },
  {
    "ship": "喜久丸",
    "area": "腰越港",
    "date": "2026/04/08",
    "trip_no": 1,
    "fish_raw": "アマダイ",
    "count_raw": "0～4匹",
    "size_raw": "25～30cm",
    "weight_raw": "",
    "tokki_raw": "メイン",
    "point_raw": "神奈川県 鎌倉市 腰越漁港",
    "kanso_raw": "アマダイイトヨリキントキと顔を見ることが出来ましたゲストも良型アジムシガレイと釣れたのですが釣り座により釣果に差が出てしまい少し残念でした！ PS魚影は濃いので底潮が安定すれば今後も楽しみです。",
    "suion_raw": "13.6℃",
    "suishoku_raw": "",
    "color_raw": "",
    "source": "chowari/喜久丸",
    "tide_label": "中潮",
    "weather_text": "晴れ",
    "weather_detail": {
      "sunrise": "05:19",
      "sunset": "18:09",
      "moonrise": "",
      "moonset": "08:39",
      "weather": "晴れ",
      "temp_high": "17℃",
      "temp_low": "9℃",
      "pressure": "1018.6hPa",
      "wind_dir": "北東",
      "wind_speed": "4.0m/s",
      "wave_dir": "南",
      "wave_height": "0.7m/s",
      "water_temp": "13.6℃",
      "tide": "中潮",
      "moon_age": "20.1",
      "bi": "7.9"
    }
  },
  {
    "ship": "喜久丸",
    "area": "腰越港",
    "date": "2026/04/08",
    "trip_no": 1,
    "fish_raw": "イトヨリ",
    "count_raw": "0～4匹",
    "size_raw": "25～32cm",
    "weight_raw": "",
    "tokki_raw": "外道",
    "point_raw": "神奈川県 鎌倉市 腰越漁港",
    "kanso_raw": "アマダイイトヨリキントキと顔を見ることが出来ましたゲストも良型アジムシガレイと釣れたのですが釣り座により釣果に差が出てしまい少し残念でした！ PS魚影は濃いので底潮が安定すれば今後も楽しみです。",
    "suion_raw": "13.6℃",
    "suishoku_raw": "",
    "color_raw": "",
    "source": "chowari/喜久丸",
    "tide_label": "中潮",
    "weather_text": "晴れ",
    "weather_detail": {
      "sunrise": "05:19",
      "sunset": "18:09",
      "moonrise": "",
      "moonset": "08:39",
      "weather": "晴れ",
      "temp_high": "17℃",
      "temp_low": "9℃",
      "pressure": "1018.6hPa",
      "wind_dir": "北東",
      "wind_speed": "4.0m/s",
      "wave_dir": "南",
      "wave_height": "0.7m/s",
      "water_temp": "13.6℃",
      "tide": "中潮",
      "moon_age": "20.1",
      "bi": "7.9"
    }
  },
  {
    "ship": "喜久丸",
    "area": "腰越港",
    "date": "2026/04/08",
    "trip_no": 1,
    "fish_raw": "アジ",
    "count_raw": "0～6匹",
    "size_raw": "28～38cm",
    "weight_raw": "",
    "tokki_raw": "外道",
    "point_raw": "神奈川県 鎌倉市 腰越漁港",
    "kanso_raw": "アマダイイトヨリキントキと顔を見ることが出来ましたゲストも良型アジムシガレイと釣れたのですが釣り座により釣果に差が出てしまい少し残念でした！ PS魚影は濃いので底潮が安定すれば今後も楽しみです。",
    "suion_raw": "13.6℃",
    "suishoku_raw": "",
    "color_raw": "",
    "source": "chowari/喜久丸",
    "tide_label": "中潮",
    "weather_text": "晴れ",
    "weather_detail": {
      "sunrise": "05:19",
      "sunset": "18:09",
      "moonrise": "",
      "moonset": "08:39",
      "weather": "晴れ",
      "temp_high": "17℃",
      "temp_low": "9℃",
      "pressure": "1018.6hPa",
      "wind_dir": "北東",
      "wind_speed": "4.0m/s",
      "wave_dir": "南",
      "wave_height": "0.7m/s",
      "water_temp": "13.6℃",
      "tide": "中潮",
      "moon_age": "20.1",
      "bi": "7.9"
    }
  },
  {
    "ship": "喜久丸",
    "area": "腰越港",
    "date": "2026/04/06",
    "trip_no": 1,
    "fish_raw": "アマダイ",
    "count_raw": "0～3匹",
    "size_raw": "25～35cm",
    "weight_raw": "",
    "tokki_raw": "メイン",
    "point_raw": "神奈川県 鎌倉市 腰越漁港",
    "kanso_raw": "ややウネリが有り船酔いでダウンされた方も居ましたがターゲットのアマダイシロアマダイイトヨリ他にアジとお土産はキープ出来て良かったです！ PS明日は休船しますm(__)m",
    "suion_raw": "13.9℃",
    "suishoku_raw": "",
    "color_raw": "",
    "source": "chowari/喜久丸",
    "tide_label": "中潮",
    "weather_text": "晴れ後時々曇り",
    "weather_detail": {
      "sunrise": "05:22",
      "sunset": "18:07",
      "moonrise": "22:22",
      "moonset": "07:11",
      "weather": "晴れ後時々曇り",
      "temp_high": "23℃",
      "temp_low": "15℃",
      "pressure": "1014.1hPa",
      "wind_dir": "東北東",
      "wind_speed": "2.1m/s",
      "wave_dir": "南",
      "wave_height": "1.1m/s",
      "water_temp": "13.9℃",
      "tide": "中潮",
      "moon_age": "18.1",
      "bi": "7.7"
    }
  },
  {
    "ship": "喜久丸",
    "area": "腰越港",
    "date": "2026/04/06",
    "trip_no": 1,
    "fish_raw": "シロアマダイ",
    "count_raw": "合計1匹",
    "size_raw": "28cm",
    "weight_raw": "",
    "tokki_raw": "外道",
    "point_raw": "神奈川県 鎌倉市 腰越漁港",
    "kanso_raw": "ややウネリが有り船酔いでダウンされた方も居ましたがターゲットのアマダイシロアマダイイトヨリ他にアジとお土産はキープ出来て良かったです！ PS明日は休船しますm(__)m",
    "suion_raw": "13.9℃",
    "suishoku_raw": "",
    "color_raw": "",
    "source": "chowari/喜久丸",
    "tide_label": "中潮",
    "weather_text": "晴れ後時々曇り",
    "weather_detail": {
      "sunrise": "05:22",
      "sunset": "18:07",
      "moonrise": "22:22",
      "moonset": "07:11",
      "weather": "晴れ後時々曇り",
      "temp_high": "23℃",
      "temp_low": "15℃",
      "pressure": "1014.1hPa",
      "wind_dir": "東北東",
      "wind_speed": "2.1m/s",
      "wave_dir": "南",
      "wave_height": "1.1m/s",
      "water_temp": "13.9℃",
      "tide": "中潮",
      "moon_age": "18.1",
      "bi": "7.7"
    }
  },
  {
    "ship": "喜久丸",
    "area": "腰越港",
    "date": "2026/04/06",
    "trip_no": 1,
    "fish_raw": "アジ",
    "count_raw": "0～4匹",
    "size_raw": "28～38cm",
    "weight_raw": "",
    "tokki_raw": "外道",
    "point_raw": "神奈川県 鎌倉市 腰越漁港",
    "kanso_raw": "ややウネリが有り船酔いでダウンされた方も居ましたがターゲットのアマダイシロアマダイイトヨリ他にアジとお土産はキープ出来て良かったです！ PS明日は休船しますm(__)m",
    "suion_raw": "13.9℃",
    "suishoku_raw": "",
    "color_raw": "",
    "source": "chowari/喜久丸",
    "tide_label": "中潮",
    "weather_text": "晴れ後時々曇り",
    "weather_detail": {
      "sunrise": "05:22",
      "sunset": "18:07",
      "moonrise": "22:22",
      "moonset": "07:11",
      "weather": "晴れ後時々曇り",
      "temp_high": "23℃",
      "temp_low": "15℃",
      "pressure": "1014.1hPa",
      "wind_dir": "東北東",
      "wind_speed": "2.1m/s",
      "wave_dir": "南",
      "wave_height": "1.1m/s",
      "water_temp": "13.9℃",
      "tide": "中潮",
      "moon_age": "18.1",
      "bi": "7.7"
    }
  },
  {
    "ship": "喜久丸",
    "area": "腰越港",
    "date": "2026/04/04",
    "trip_no": 1,
    "fish_raw": "イトヨリ",
    "count_raw": "0～1匹",
    "size_raw": "23～30cm",
    "weight_raw": "",
    "tokki_raw": "メイン",
    "point_raw": "神奈川県 鎌倉市 腰越漁港",
    "kanso_raw": "天気予報は悪かったのですが時間まで操船出来ました海上は底荒の為かターゲットのアマダイは釣れませんでしたがイトヨリアジワニゴチと顔を出してくれましたが全体的に数も伸びず残念でした！",
    "suion_raw": "13.6℃",
    "suishoku_raw": "",
    "color_raw": "",
    "source": "chowari/喜久丸",
    "tide_label": "大潮",
    "weather_text": "雨",
    "weather_detail": {
      "sunrise": "05:25",
      "sunset": "18:06",
      "moonrise": "20:22",
      "moonset": "06:05",
      "weather": "雨",
      "temp_high": "19℃",
      "temp_low": "13℃",
      "pressure": "1019.0hPa",
      "wind_dir": "南南西",
      "wind_speed": "2.8m/s",
      "wave_dir": "南",
      "wave_height": "0.4m/s",
      "water_temp": "13.6℃",
      "tide": "大潮",
      "moon_age": "16.1",
      "bi": "8.2"
    }
  },
  {
    "ship": "喜久丸",
    "area": "腰越港",
    "date": "2026/04/01",
    "trip_no": 1,
    "fish_raw": "タイ",
    "count_raw": "合計1匹",
    "size_raw": "1.20kg",
    "weight_raw": "",
    "tokki_raw": "メイン",
    "point_raw": "神奈川県 鎌倉市 腰越漁港",
    "kanso_raw": "チャーター船 昨日からの南西風の影響でコンデションが悪いなかお子様も含めて皆さん頑張ってくれてマダイ1.2㎏アマダイイトヨリアジサバと数は伸びませんでしたが出船出来て良かったと喜んでもらえて良かったです！",
    "suion_raw": "13.4℃",
    "suishoku_raw": "",
    "color_raw": "",
    "source": "chowari/喜久丸",
    "tide_label": "大潮",
    "weather_text": "曇りのち一時雨",
    "weather_detail": {
      "sunrise": "05:29",
      "sunset": "18:03",
      "moonrise": "17:19",
      "moonset": "04:48",
      "weather": "曇りのち一時雨",
      "temp_high": "18℃",
      "temp_low": "12℃",
      "pressure": "1011.0hPa",
      "wind_dir": "北北東",
      "wind_speed": "3.7m/s",
      "wave_dir": "南",
      "wave_height": "1.5m/s",
      "water_temp": "13.4℃",
      "tide": "大潮",
      "moon_age": "13.1",
      "bi": "10.0"
    }
  },
  {
    "ship": "喜久丸",
    "area": "腰越港",
    "date": "2026/03/30",
    "trip_no": 1,
    "fish_raw": "シロアマダイ",
    "count_raw": "合計1匹",
    "size_raw": "40cm",
    "weight_raw": "",
    "tokki_raw": "メイン",
    "point_raw": "神奈川県 鎌倉市 腰越漁港",
    "kanso_raw": "ウィリーアマダイ五目イトヨリ28~35㎝0~1枚ホウボウ26~32㎝0~1枚シロアマダイ40㎝1枚アジ35~40㎝サバEtc ターゲットのシロアマダイイトヨリホウボウ他にゲストのアジとお土産はキープ出来ました！ PS明日は天気予報も悪いので休船しますm(__)m",
    "suion_raw": "13.3℃",
    "suishoku_raw": "",
    "color_raw": "",
    "source": "chowari/喜久丸",
    "tide_label": "中潮",
    "weather_text": "晴れ時々曇り",
    "weather_detail": {
      "sunrise": "05:32",
      "sunset": "18:02",
      "moonrise": "15:15",
      "moonset": "03:56",
      "weather": "晴れ時々曇り",
      "temp_high": "20℃",
      "temp_low": "12℃",
      "pressure": "1022.9hPa",
      "wind_dir": "東北東",
      "wind_speed": "1.6m/s",
      "wave_dir": "南南東",
      "wave_height": "0.2m/s",
      "water_temp": "13.3℃",
      "tide": "中潮",
      "moon_age": "11.1",
      "bi": "8.3"
    }
  },
  {
    "ship": "喜久丸",
    "area": "腰越港",
    "date": "2026/03/30",
    "trip_no": 1,
    "fish_raw": "アジ",
    "count_raw": "1～6匹",
    "size_raw": "28～35cm",
    "weight_raw": "",
    "tokki_raw": "外道",
    "point_raw": "神奈川県 鎌倉市 腰越漁港",
    "kanso_raw": "ウィリーアマダイ五目イトヨリ28~35㎝0~1枚ホウボウ26~32㎝0~1枚シロアマダイ40㎝1枚アジ35~40㎝サバEtc ターゲットのシロアマダイイトヨリホウボウ他にゲストのアジとお土産はキープ出来ました！ PS明日は天気予報も悪いので休船しますm(__)m",
    "suion_raw": "13.3℃",
    "suishoku_raw": "",
    "color_raw": "",
    "source": "chowari/喜久丸",
    "tide_label": "中潮",
    "weather_text": "晴れ時々曇り",
    "weather_detail": {
      "sunrise": "05:32",
      "sunset": "18:02",
      "moonrise": "15:15",
      "moonset": "03:56",
      "weather": "晴れ時々曇り",
      "temp_high": "20℃",
      "temp_low": "12℃",
      "pressure": "1022.9hPa",
      "wind_dir": "東北東",
      "wind_speed": "1.6m/s",
      "wave_dir": "南南東",
      "wave_height": "0.2m/s",
      "water_temp": "13.3℃",
      "tide": "中潮",
      "moon_age": "11.1",
      "bi": "8.3"
    }
  },
  {
    "ship": "喜久丸",
    "area": "腰越港",
    "date": "2026/03/29",
    "trip_no": 1,
    "fish_raw": "シロアマダイ",
    "count_raw": "0～1匹",
    "size_raw": "40～42cm",
    "weight_raw": "",
    "tokki_raw": "メイン",
    "point_raw": "神奈川県 鎌倉市 腰越漁港",
    "kanso_raw": "ウィリーアマダイ五目アマダイ(シロアマダイ混じり)25~42㎝0~2枚アジ25~38㎝4~8匹Etc 良型シロアマダイ(40~42㎝)アマダイゲストのアジと皆さんに楽しんでもらえてお土産もキープで帰港です！",
    "suion_raw": "13.1℃",
    "suishoku_raw": "",
    "color_raw": "",
    "source": "chowari/喜久丸",
    "tide_label": "若潮",
    "weather_text": "晴れ後時々曇り",
    "weather_detail": {
      "sunrise": "05:33",
      "sunset": "18:01",
      "moonrise": "14:10",
      "moonset": "03:26",
      "weather": "晴れ後時々曇り",
      "temp_high": "21℃",
      "temp_low": "11℃",
      "pressure": "1018.4hPa",
      "wind_dir": "東",
      "wind_speed": "0.6m/s",
      "wave_dir": "南南東",
      "wave_height": "0.2m/s",
      "water_temp": "13.1℃",
      "tide": "若潮",
      "moon_age": "10.1",
      "bi": "7.8"
    }
  },
  {
    "ship": "喜久丸",
    "area": "腰越港",
    "date": "2026/03/29",
    "trip_no": 1,
    "fish_raw": "アマダイ",
    "count_raw": "0～1匹",
    "size_raw": "25～28cm",
    "weight_raw": "",
    "tokki_raw": "外道",
    "point_raw": "神奈川県 鎌倉市 腰越漁港",
    "kanso_raw": "ウィリーアマダイ五目アマダイ(シロアマダイ混じり)25~42㎝0~2枚アジ25~38㎝4~8匹Etc 良型シロアマダイ(40~42㎝)アマダイゲストのアジと皆さんに楽しんでもらえてお土産もキープで帰港です！",
    "suion_raw": "13.1℃",
    "suishoku_raw": "",
    "color_raw": "",
    "source": "chowari/喜久丸",
    "tide_label": "若潮",
    "weather_text": "晴れ後時々曇り",
    "weather_detail": {
      "sunrise": "05:33",
      "sunset": "18:01",
      "moonrise": "14:10",
      "moonset": "03:26",
      "weather": "晴れ後時々曇り",
      "temp_high": "21℃",
      "temp_low": "11℃",
      "pressure": "1018.4hPa",
      "wind_dir": "東",
      "wind_speed": "0.6m/s",
      "wave_dir": "南南東",
      "wave_height": "0.2m/s",
      "water_temp": "13.1℃",
      "tide": "若潮",
      "moon_age": "10.1",
      "bi": "7.8"
    }
  },
  {
    "ship": "喜久丸",
    "area": "腰越港",
    "date": "2026/03/29",
    "trip_no": 1,
    "fish_raw": "アジ",
    "count_raw": "4～8匹",
    "size_raw": "25～38cm",
    "weight_raw": "",
    "tokki_raw": "外道",
    "point_raw": "神奈川県 鎌倉市 腰越漁港",
    "kanso_raw": "ウィリーアマダイ五目アマダイ(シロアマダイ混じり)25~42㎝0~2枚アジ25~38㎝4~8匹Etc 良型シロアマダイ(40~42㎝)アマダイゲストのアジと皆さんに楽しんでもらえてお土産もキープで帰港です！",
    "suion_raw": "13.1℃",
    "suishoku_raw": "",
    "color_raw": "",
    "source": "chowari/喜久丸",
    "tide_label": "若潮",
    "weather_text": "晴れ後時々曇り",
    "weather_detail": {
      "sunrise": "05:33",
      "sunset": "18:01",
      "moonrise": "14:10",
      "moonset": "03:26",
      "weather": "晴れ後時々曇り",
      "temp_high": "21℃",
      "temp_low": "11℃",
      "pressure": "1018.4hPa",
      "wind_dir": "東",
      "wind_speed": "0.6m/s",
      "wave_dir": "南南東",
      "wave_height": "0.2m/s",
      "water_temp": "13.1℃",
      "tide": "若潮",
      "moon_age": "10.1",
      "bi": "7.8"
    }
  },
  {
    "ship": "喜久丸",
    "area": "腰越港",
    "date": "2026/03/28",
    "trip_no": 1,
    "fish_raw": "ハナダイ",
    "count_raw": "0～1匹",
    "size_raw": "0.40～0.80kg",
    "weight_raw": "",
    "tokki_raw": "メイン",
    "point_raw": "神奈川県 鎌倉市 腰越漁港",
    "kanso_raw": "ウィリーアマダイ五目ハナダイ0.4~0.8㎏0~1枚アマダイ28~30㎝0~1枚アジ25~38㎝5~20匹サバ30~40㎝3~10匹ニジハタEtc ターゲットのハナダイアマダイイトヨリ始めゲストのアジサバニジハタとお土産にも恵まれ楽しんでもらえて嬉しい1日でした！",
    "suion_raw": "12.9℃",
    "suishoku_raw": "",
    "color_raw": "",
    "source": "chowari/喜久丸",
    "tide_label": "長潮",
    "weather_text": "曇り時々晴れ",
    "weather_detail": {
      "sunrise": "05:34",
      "sunset": "18:00",
      "moonrise": "13:02",
      "moonset": "02:50",
      "weather": "曇り時々晴れ",
      "temp_high": "19℃",
      "temp_low": "11℃",
      "pressure": "1016.5hPa",
      "wind_dir": "北北東",
      "wind_speed": "3.0m/s",
      "wave_dir": "南南東",
      "wave_height": "0.2m/s",
      "water_temp": "12.9℃",
      "tide": "長潮",
      "moon_age": "9.1",
      "bi": "7.5"
    }
  },
  {
    "ship": "喜久丸",
    "area": "腰越港",
    "date": "2026/03/28",
    "trip_no": 1,
    "fish_raw": "アマダイ",
    "count_raw": "0～1匹",
    "size_raw": "28～38cm",
    "weight_raw": "",
    "tokki_raw": "外道",
    "point_raw": "神奈川県 鎌倉市 腰越漁港",
    "kanso_raw": "ウィリーアマダイ五目ハナダイ0.4~0.8㎏0~1枚アマダイ28~30㎝0~1枚アジ25~38㎝5~20匹サバ30~40㎝3~10匹ニジハタEtc ターゲットのハナダイアマダイイトヨリ始めゲストのアジサバニジハタとお土産にも恵まれ楽しんでもらえて嬉しい1日でした！",
    "suion_raw": "12.9℃",
    "suishoku_raw": "",
    "color_raw": "",
    "source": "chowari/喜久丸",
    "tide_label": "長潮",
    "weather_text": "曇り時々晴れ",
    "weather_detail": {
      "sunrise": "05:34",
      "sunset": "18:00",
      "moonrise": "13:02",
      "moonset": "02:50",
      "weather": "曇り時々晴れ",
      "temp_high": "19℃",
      "temp_low": "11℃",
      "pressure": "1016.5hPa",
      "wind_dir": "北北東",
      "wind_speed": "3.0m/s",
      "wave_dir": "南南東",
      "wave_height": "0.2m/s",
      "water_temp": "12.9℃",
      "tide": "長潮",
      "moon_age": "9.1",
      "bi": "7.5"
    }
  },
  {
    "ship": "喜久丸",
    "area": "腰越港",
    "date": "2026/03/28",
    "trip_no": 1,
    "fish_raw": "アジ",
    "count_raw": "5～20匹",
    "size_raw": "25～38cm",
    "weight_raw": "",
    "tokki_raw": "外道",
    "point_raw": "神奈川県 鎌倉市 腰越漁港",
    "kanso_raw": "ウィリーアマダイ五目ハナダイ0.4~0.8㎏0~1枚アマダイ28~30㎝0~1枚アジ25~38㎝5~20匹サバ30~40㎝3~10匹ニジハタEtc ターゲットのハナダイアマダイイトヨリ始めゲストのアジサバニジハタとお土産にも恵まれ楽しんでもらえて嬉しい1日でした！",
    "suion_raw": "12.9℃",
    "suishoku_raw": "",
    "color_raw": "",
    "source": "chowari/喜久丸",
    "tide_label": "長潮",
    "weather_text": "曇り時々晴れ",
    "weather_detail": {
      "sunrise": "05:34",
      "sunset": "18:00",
      "moonrise": "13:02",
      "moonset": "02:50",
      "weather": "曇り時々晴れ",
      "temp_high": "19℃",
      "temp_low": "11℃",
      "pressure": "1016.5hPa",
      "wind_dir": "北北東",
      "wind_speed": "3.0m/s",
      "wave_dir": "南南東",
      "wave_height": "0.2m/s",
      "water_temp": "12.9℃",
      "tide": "長潮",
      "moon_age": "9.1",
      "bi": "7.5"
    }
  },
  {
    "ship": "喜久丸",
    "area": "腰越港",
    "date": "2026/03/28",
    "trip_no": 1,
    "fish_raw": "サバ",
    "count_raw": "3～10匹",
    "size_raw": "30～40cm",
    "weight_raw": "",
    "tokki_raw": "外道",
    "point_raw": "神奈川県 鎌倉市 腰越漁港",
    "kanso_raw": "ウィリーアマダイ五目ハナダイ0.4~0.8㎏0~1枚アマダイ28~30㎝0~1枚アジ25~38㎝5~20匹サバ30~40㎝3~10匹ニジハタEtc ターゲットのハナダイアマダイイトヨリ始めゲストのアジサバニジハタとお土産にも恵まれ楽しんでもらえて嬉しい1日でした！",
    "suion_raw": "12.9℃",
    "suishoku_raw": "",
    "color_raw": "",
    "source": "chowari/喜久丸",
    "tide_label": "長潮",
    "weather_text": "曇り時々晴れ",
    "weather_detail": {
      "sunrise": "05:34",
      "sunset": "18:00",
      "moonrise": "13:02",
      "moonset": "02:50",
      "weather": "曇り時々晴れ",
      "temp_high": "19℃",
      "temp_low": "11℃",
      "pressure": "1016.5hPa",
      "wind_dir": "北北東",
      "wind_speed": "3.0m/s",
      "wave_dir": "南南東",
      "wave_height": "0.2m/s",
      "water_temp": "12.9℃",
      "tide": "長潮",
      "moon_age": "9.1",
      "bi": "7.5"
    }
  },
  {
    "ship": "喜久丸",
    "area": "腰越港",
    "date": "2026/03/25",
    "trip_no": 1,
    "fish_raw": "シロアマダイ",
    "count_raw": "0～2匹",
    "size_raw": "30～38cm",
    "weight_raw": "",
    "tokki_raw": "メイン",
    "point_raw": "神奈川県 鎌倉市 腰越漁港",
    "kanso_raw": "ウィリーアマダイ五目アマダイ(シロアマダイ混じり)28~48㎝0~2枚ホウボウ28~35㎝0~1枚Etc ターゲットのアマダイシロアマダイホウボウと顔を見ることが出来ましたがアタリを獲るのが難しい1日でした！ PS明日は休船します明後日のご予約お待ちしていますm(__)m",
    "suion_raw": "13.1℃",
    "suishoku_raw": "",
    "color_raw": "",
    "source": "chowari/喜久丸",
    "tide_label": "小潮",
    "weather_text": "雨",
    "weather_detail": {
      "sunrise": "05:39",
      "sunset": "17:57",
      "moonrise": "09:36",
      "moonset": "00:09",
      "weather": "雨",
      "temp_high": "14℃",
      "temp_low": "10℃",
      "pressure": "1019.6hPa",
      "wind_dir": "北東",
      "wind_speed": "1.4m/s",
      "wave_dir": "南南東",
      "wave_height": "0.4m/s",
      "water_temp": "13.1℃",
      "tide": "小潮",
      "moon_age": "6.1",
      "bi": "6.8"
    }
  },
  {
    "ship": "喜久丸",
    "area": "腰越港",
    "date": "2026/03/25",
    "trip_no": 1,
    "fish_raw": "アマダイ",
    "count_raw": "0～1匹",
    "size_raw": "28～48cm",
    "weight_raw": "",
    "tokki_raw": "外道",
    "point_raw": "神奈川県 鎌倉市 腰越漁港",
    "kanso_raw": "ウィリーアマダイ五目アマダイ(シロアマダイ混じり)28~48㎝0~2枚ホウボウ28~35㎝0~1枚Etc ターゲットのアマダイシロアマダイホウボウと顔を見ることが出来ましたがアタリを獲るのが難しい1日でした！ PS明日は休船します明後日のご予約お待ちしていますm(__)m",
    "suion_raw": "13.1℃",
    "suishoku_raw": "",
    "color_raw": "",
    "source": "chowari/喜久丸",
    "tide_label": "小潮",
    "weather_text": "雨",
    "weather_detail": {
      "sunrise": "05:39",
      "sunset": "17:57",
      "moonrise": "09:36",
      "moonset": "00:09",
      "weather": "雨",
      "temp_high": "14℃",
      "temp_low": "10℃",
      "pressure": "1019.6hPa",
      "wind_dir": "北東",
      "wind_speed": "1.4m/s",
      "wave_dir": "南南東",
      "wave_height": "0.4m/s",
      "water_temp": "13.1℃",
      "tide": "小潮",
      "moon_age": "6.1",
      "bi": "6.8"
    }
  },
  {
    "ship": "喜久丸",
    "area": "腰越港",
    "date": "2026/03/25",
    "trip_no": 1,
    "fish_raw": "ホウボウ",
    "count_raw": "0～1匹",
    "size_raw": "28～35cm",
    "weight_raw": "",
    "tokki_raw": "外道",
    "point_raw": "神奈川県 鎌倉市 腰越漁港",
    "kanso_raw": "ウィリーアマダイ五目アマダイ(シロアマダイ混じり)28~48㎝0~2枚ホウボウ28~35㎝0~1枚Etc ターゲットのアマダイシロアマダイホウボウと顔を見ることが出来ましたがアタリを獲るのが難しい1日でした！ PS明日は休船します明後日のご予約お待ちしていますm(__)m",
    "suion_raw": "13.1℃",
    "suishoku_raw": "",
    "color_raw": "",
    "source": "chowari/喜久丸",
    "tide_label": "小潮",
    "weather_text": "雨",
    "weather_detail": {
      "sunrise": "05:39",
      "sunset": "17:57",
      "moonrise": "09:36",
      "moonset": "00:09",
      "weather": "雨",
      "temp_high": "14℃",
      "temp_low": "10℃",
      "pressure": "1019.6hPa",
      "wind_dir": "北東",
      "wind_speed": "1.4m/s",
      "wave_dir": "南南東",
      "wave_height": "0.4m/s",
      "water_temp": "13.1℃",
      "tide": "小潮",
      "moon_age": "6.1",
      "bi": "6.8"
    }
  },
  {
    "ship": "喜久丸",
    "area": "腰越港",
    "date": "2026/03/24",
    "trip_no": 1,
    "fish_raw": "アマダイ",
    "count_raw": "0～2匹",
    "size_raw": "20～40cm",
    "weight_raw": "",
    "tokki_raw": "メイン",
    "point_raw": "神奈川県 鎌倉市 腰越漁港",
    "kanso_raw": "ウィリーアマダイ五目シロアマダイ20~40㎝0~2枚イトヨリ25~38㎝0~2枚サバ30~35㎝0~2匹アジミノカサゴEtc ポイントでは魚影は濃いのですがなかなか釣果に結びつかず苦戦しましたが何とかシロアマダイ良型イトヨリサバアジと顔を見ることが出来ました！",
    "suion_raw": "13.0℃",
    "suishoku_raw": "",
    "color_raw": "",
    "source": "chowari/喜久丸",
    "tide_label": "中潮",
    "weather_text": "晴れ後時々曇り",
    "weather_detail": {
      "sunrise": "05:40",
      "sunset": "17:57",
      "moonrise": "08:39",
      "moonset": "",
      "weather": "晴れ後時々曇り",
      "temp_high": "17℃",
      "temp_low": "9℃",
      "pressure": "1018.8hPa",
      "wind_dir": "北東",
      "wind_speed": "4.0m/s",
      "wave_dir": "南南東",
      "wave_height": "0.6m/s",
      "water_temp": "13.0℃",
      "tide": "中潮",
      "moon_age": "5.1",
      "bi": "7.2"
    }
  },
  {
    "ship": "喜久丸",
    "area": "腰越港",
    "date": "2026/03/24",
    "trip_no": 1,
    "fish_raw": "イトヨリ",
    "count_raw": "0～2匹",
    "size_raw": "25～28cm",
    "weight_raw": "",
    "tokki_raw": "外道",
    "point_raw": "神奈川県 鎌倉市 腰越漁港",
    "kanso_raw": "ウィリーアマダイ五目シロアマダイ20~40㎝0~2枚イトヨリ25~38㎝0~2枚サバ30~35㎝0~2匹アジミノカサゴEtc ポイントでは魚影は濃いのですがなかなか釣果に結びつかず苦戦しましたが何とかシロアマダイ良型イトヨリサバアジと顔を見ることが出来ました！",
    "suion_raw": "13.0℃",
    "suishoku_raw": "",
    "color_raw": "",
    "source": "chowari/喜久丸",
    "tide_label": "中潮",
    "weather_text": "晴れ後時々曇り",
    "weather_detail": {
      "sunrise": "05:40",
      "sunset": "17:57",
      "moonrise": "08:39",
      "moonset": "",
      "weather": "晴れ後時々曇り",
      "temp_high": "17℃",
      "temp_low": "9℃",
      "pressure": "1018.8hPa",
      "wind_dir": "北東",
      "wind_speed": "4.0m/s",
      "wave_dir": "南南東",
      "wave_height": "0.6m/s",
      "water_temp": "13.0℃",
      "tide": "中潮",
      "moon_age": "5.1",
      "bi": "7.2"
    }
  },
  {
    "ship": "喜久丸",
    "area": "腰越港",
    "date": "2026/03/24",
    "trip_no": 1,
    "fish_raw": "サバ",
    "count_raw": "0～2匹",
    "size_raw": "30～35cm",
    "weight_raw": "",
    "tokki_raw": "外道",
    "point_raw": "神奈川県 鎌倉市 腰越漁港",
    "kanso_raw": "ウィリーアマダイ五目シロアマダイ20~40㎝0~2枚イトヨリ25~38㎝0~2枚サバ30~35㎝0~2匹アジミノカサゴEtc ポイントでは魚影は濃いのですがなかなか釣果に結びつかず苦戦しましたが何とかシロアマダイ良型イトヨリサバアジと顔を見ることが出来ました！",
    "suion_raw": "13.0℃",
    "suishoku_raw": "",
    "color_raw": "",
    "source": "chowari/喜久丸",
    "tide_label": "中潮",
    "weather_text": "晴れ後時々曇り",
    "weather_detail": {
      "sunrise": "05:40",
      "sunset": "17:57",
      "moonrise": "08:39",
      "moonset": "",
      "weather": "晴れ後時々曇り",
      "temp_high": "17℃",
      "temp_low": "9℃",
      "pressure": "1018.8hPa",
      "wind_dir": "北東",
      "wind_speed": "4.0m/s",
      "wave_dir": "南南東",
      "wave_height": "0.6m/s",
      "water_temp": "13.0℃",
      "tide": "中潮",
      "moon_age": "5.1",
      "bi": "7.2"
    }
  },
  {
    "ship": "喜久丸",
    "area": "腰越港",
    "date": "2026/03/22",
    "trip_no": 1,
    "fish_raw": "アマダイ",
    "count_raw": "0～3匹",
    "size_raw": "25～40cm",
    "weight_raw": "",
    "tokki_raw": "メイン",
    "point_raw": "神奈川県 鎌倉市 腰越漁港",
    "kanso_raw": "ウィリーアマダイ五目アマダイ(シロアマダイ混じり)25~40㎝0~1枚イトヨリ26~50㎝0~2枚0~1枚アジ28~33㎝0~5匹サバ30~35㎝0~6匹ハナダイホウボウアオハタEtc ハナダイアマダイシロアマダイ良型イトヨリホウボウ始めアジサバアオハタとまずまずでしたが釣り座により釣果に恵まれ無い方が出てしまい少し残念でした！ PS明日は休船します明後日のご予約お待ちしていますm(__)m",
    "suion_raw": "12.6℃",
    "suishoku_raw": "",
    "color_raw": "",
    "source": "chowari/喜久丸",
    "tide_label": "中潮",
    "weather_text": "晴れ後時々曇り",
    "weather_detail": {
      "sunrise": "05:43",
      "sunset": "17:55",
      "moonrise": "07:11",
      "moonset": "21:44",
      "weather": "晴れ後時々曇り",
      "temp_high": "17℃",
      "temp_low": "8℃",
      "pressure": "1025.4hPa",
      "wind_dir": "北北東",
      "wind_speed": "2.5m/s",
      "wave_dir": "南南東",
      "wave_height": "0.2m/s",
      "water_temp": "12.6℃",
      "tide": "中潮",
      "moon_age": "3.1",
      "bi": "8.2"
    }
  },
  {
    "ship": "喜久丸",
    "area": "腰越港",
    "date": "2026/03/22",
    "trip_no": 1,
    "fish_raw": "イトヨリ",
    "count_raw": "0～2匹",
    "size_raw": "26～50cm",
    "weight_raw": "",
    "tokki_raw": "外道",
    "point_raw": "神奈川県 鎌倉市 腰越漁港",
    "kanso_raw": "ウィリーアマダイ五目アマダイ(シロアマダイ混じり)25~40㎝0~1枚イトヨリ26~50㎝0~2枚0~1枚アジ28~33㎝0~5匹サバ30~35㎝0~6匹ハナダイホウボウアオハタEtc ハナダイアマダイシロアマダイ良型イトヨリホウボウ始めアジサバアオハタとまずまずでしたが釣り座により釣果に恵まれ無い方が出てしまい少し残念でした！ PS明日は休船します明後日のご予約お待ちしていますm(__)m",
    "suion_raw": "12.6℃",
    "suishoku_raw": "",
    "color_raw": "",
    "source": "chowari/喜久丸",
    "tide_label": "中潮",
    "weather_text": "晴れ後時々曇り",
    "weather_detail": {
      "sunrise": "05:43",
      "sunset": "17:55",
      "moonrise": "07:11",
      "moonset": "21:44",
      "weather": "晴れ後時々曇り",
      "temp_high": "17℃",
      "temp_low": "8℃",
      "pressure": "1025.4hPa",
      "wind_dir": "北北東",
      "wind_speed": "2.5m/s",
      "wave_dir": "南南東",
      "wave_height": "0.2m/s",
      "water_temp": "12.6℃",
      "tide": "中潮",
      "moon_age": "3.1",
      "bi": "8.2"
    }
  },
  {
    "ship": "喜久丸",
    "area": "腰越港",
    "date": "2026/03/22",
    "trip_no": 1,
    "fish_raw": "アジ",
    "count_raw": "0～5匹",
    "size_raw": "28～33cm",
    "weight_raw": "",
    "tokki_raw": "外道",
    "point_raw": "神奈川県 鎌倉市 腰越漁港",
    "kanso_raw": "ウィリーアマダイ五目アマダイ(シロアマダイ混じり)25~40㎝0~1枚イトヨリ26~50㎝0~2枚0~1枚アジ28~33㎝0~5匹サバ30~35㎝0~6匹ハナダイホウボウアオハタEtc ハナダイアマダイシロアマダイ良型イトヨリホウボウ始めアジサバアオハタとまずまずでしたが釣り座により釣果に恵まれ無い方が出てしまい少し残念でした！ PS明日は休船します明後日のご予約お待ちしていますm(__)m",
    "suion_raw": "12.6℃",
    "suishoku_raw": "",
    "color_raw": "",
    "source": "chowari/喜久丸",
    "tide_label": "中潮",
    "weather_text": "晴れ後時々曇り",
    "weather_detail": {
      "sunrise": "05:43",
      "sunset": "17:55",
      "moonrise": "07:11",
      "moonset": "21:44",
      "weather": "晴れ後時々曇り",
      "temp_high": "17℃",
      "temp_low": "8℃",
      "pressure": "1025.4hPa",
      "wind_dir": "北北東",
      "wind_speed": "2.5m/s",
      "wave_dir": "南南東",
      "wave_height": "0.2m/s",
      "water_temp": "12.6℃",
      "tide": "中潮",
      "moon_age": "3.1",
      "bi": "8.2"
    }
  },
  {
    "ship": "喜久丸",
    "area": "腰越港",
    "date": "2026/03/22",
    "trip_no": 1,
    "fish_raw": "サバ",
    "count_raw": "0～5匹",
    "size_raw": "30～35cm",
    "weight_raw": "",
    "tokki_raw": "外道",
    "point_raw": "神奈川県 鎌倉市 腰越漁港",
    "kanso_raw": "ウィリーアマダイ五目アマダイ(シロアマダイ混じり)25~40㎝0~1枚イトヨリ26~50㎝0~2枚0~1枚アジ28~33㎝0~5匹サバ30~35㎝0~6匹ハナダイホウボウアオハタEtc ハナダイアマダイシロアマダイ良型イトヨリホウボウ始めアジサバアオハタとまずまずでしたが釣り座により釣果に恵まれ無い方が出てしまい少し残念でした！ PS明日は休船します明後日のご予約お待ちしていますm(__)m",
    "suion_raw": "12.6℃",
    "suishoku_raw": "",
    "color_raw": "",
    "source": "chowari/喜久丸",
    "tide_label": "中潮",
    "weather_text": "晴れ後時々曇り",
    "weather_detail": {
      "sunrise": "05:43",
      "sunset": "17:55",
      "moonrise": "07:11",
      "moonset": "21:44",
      "weather": "晴れ後時々曇り",
      "temp_high": "17℃",
      "temp_low": "8℃",
      "pressure": "1025.4hPa",
      "wind_dir": "北北東",
      "wind_speed": "2.5m/s",
      "wave_dir": "南南東",
      "wave_height": "0.2m/s",
      "water_temp": "12.6℃",
      "tide": "中潮",
      "moon_age": "3.1",
      "bi": "8.2"
    }
  },
  {
    "ship": "喜久丸",
    "area": "腰越港",
    "date": "2026/03/21",
    "trip_no": 1,
    "fish_raw": "アマダイ",
    "count_raw": "0～1匹",
    "size_raw": "25～42cm",
    "weight_raw": "",
    "tokki_raw": "メイン",
    "point_raw": "神奈川県 鎌倉市 腰越漁港",
    "kanso_raw": "ウィリーアマダイ五目アマダイ(シロアマダイ混じり)25~42㎝0~1枚イトヨリ26~37㎝0~1枚ホウボウ25~30㎝0~3枚アジ28~30㎝0~6匹ハナダイクロダイワニゴチサバEtc 潮流れが悪くアタリを獲るのが難しいなか皆さん頑張ってくれてハナダイクロダイアマダイシロアマダイイトヨリホウボウ始めゲストのアジサバと釣り座により釣果にバラツキがありましたが状況を考えるとまずまずでした！",
    "suion_raw": "12.6℃",
    "suishoku_raw": "",
    "color_raw": "",
    "source": "chowari/喜久丸",
    "tide_label": "中潮",
    "weather_text": "晴れ",
    "weather_detail": {
      "sunrise": "05:44",
      "sunset": "17:54",
      "moonrise": "06:37",
      "moonset": "20:30",
      "weather": "晴れ",
      "temp_high": "16℃",
      "temp_low": "7℃",
      "pressure": "1022.2hPa",
      "wind_dir": "北東",
      "wind_speed": "2.9m/s",
      "wave_dir": "南",
      "wave_height": "0.3m/s",
      "water_temp": "12.6℃",
      "tide": "中潮",
      "moon_age": "2.1",
      "bi": "8.1"
    }
  },
  {
    "ship": "喜久丸",
    "area": "腰越港",
    "date": "2026/03/21",
    "trip_no": 1,
    "fish_raw": "イトヨリ",
    "count_raw": "0～1匹",
    "size_raw": "26～37cm",
    "weight_raw": "",
    "tokki_raw": "外道",
    "point_raw": "神奈川県 鎌倉市 腰越漁港",
    "kanso_raw": "ウィリーアマダイ五目アマダイ(シロアマダイ混じり)25~42㎝0~1枚イトヨリ26~37㎝0~1枚ホウボウ25~30㎝0~3枚アジ28~30㎝0~6匹ハナダイクロダイワニゴチサバEtc 潮流れが悪くアタリを獲るのが難しいなか皆さん頑張ってくれてハナダイクロダイアマダイシロアマダイイトヨリホウボウ始めゲストのアジサバと釣り座により釣果にバラツキがありましたが状況を考えるとまずまずでした！",
    "suion_raw": "12.6℃",
    "suishoku_raw": "",
    "color_raw": "",
    "source": "chowari/喜久丸",
    "tide_label": "中潮",
    "weather_text": "晴れ",
    "weather_detail": {
      "sunrise": "05:44",
      "sunset": "17:54",
      "moonrise": "06:37",
      "moonset": "20:30",
      "weather": "晴れ",
      "temp_high": "16℃",
      "temp_low": "7℃",
      "pressure": "1022.2hPa",
      "wind_dir": "北東",
      "wind_speed": "2.9m/s",
      "wave_dir": "南",
      "wave_height": "0.3m/s",
      "water_temp": "12.6℃",
      "tide": "中潮",
      "moon_age": "2.1",
      "bi": "8.1"
    }
  },
  {
    "ship": "喜久丸",
    "area": "腰越港",
    "date": "2026/03/21",
    "trip_no": 1,
    "fish_raw": "アジ",
    "count_raw": "0～6匹",
    "size_raw": "28～30cm",
    "weight_raw": "",
    "tokki_raw": "外道",
    "point_raw": "神奈川県 鎌倉市 腰越漁港",
    "kanso_raw": "ウィリーアマダイ五目アマダイ(シロアマダイ混じり)25~42㎝0~1枚イトヨリ26~37㎝0~1枚ホウボウ25~30㎝0~3枚アジ28~30㎝0~6匹ハナダイクロダイワニゴチサバEtc 潮流れが悪くアタリを獲るのが難しいなか皆さん頑張ってくれてハナダイクロダイアマダイシロアマダイイトヨリホウボウ始めゲストのアジサバと釣り座により釣果にバラツキがありましたが状況を考えるとまずまずでした！",
    "suion_raw": "12.6℃",
    "suishoku_raw": "",
    "color_raw": "",
    "source": "chowari/喜久丸",
    "tide_label": "中潮",
    "weather_text": "晴れ",
    "weather_detail": {
      "sunrise": "05:44",
      "sunset": "17:54",
      "moonrise": "06:37",
      "moonset": "20:30",
      "weather": "晴れ",
      "temp_high": "16℃",
      "temp_low": "7℃",
      "pressure": "1022.2hPa",
      "wind_dir": "北東",
      "wind_speed": "2.9m/s",
      "wave_dir": "南",
      "wave_height": "0.3m/s",
      "water_temp": "12.6℃",
      "tide": "中潮",
      "moon_age": "2.1",
      "bi": "8.1"
    }
  }
]