[
  {
    "ship": "ふじ丸",
    "area": "戸田港",
    "date": "2026/06/24",
    "trip_no": 1,
    "fish_raw": "マルイカ",
    "count_raw": "6～20匹",
    "size_raw": "",
    "weight_raw": "",
    "tokki_raw": "メイン",
    "point_raw": "静岡県 沼津市 戸田港",
    "kanso_raw": "マルイカ便、途中フィーバータイムきたけど、一瞬で過ぎ去り。ポツポツ釣り。サバにやられ、仕掛けロストする人もいました。イカメタルに大剣が掛かり良かったです。これからなのでイカメタルファンよろしくお願いします。",
    "suion_raw": "22.7℃",
    "suishoku_raw": "",
    "color_raw": "",
    "source": "chowari/ふじ丸",
    "tide_label": "長潮",
    "weather_text": "曇り",
    "weather_detail": {
      "sunrise": "04:31",
      "sunset": "19:03",
      "moonrise": "14:01",
      "moonset": "00:17",
      "weather": "曇り",
      "temp_high": "27℃",
      "temp_low": "20℃",
      "pressure": "1013.4hPa",
      "wind_dir": "東北東",
      "wind_speed": "0.7m/s",
      "wave_dir": "南南西",
      "wave_height": "0.4m/s",
      "water_temp": "22.7℃",
      "tide": "長潮",
      "moon_age": "9.0",
      "bi": "9.0"
    }
  },
  {
    "ship": "ふじ丸",
    "area": "戸田港",
    "date": "2026/06/23",
    "trip_no": 1,
    "fish_raw": "イサキ",
    "count_raw": "20～23匹",
    "size_raw": "",
    "weight_raw": "",
    "tokki_raw": "メイン",
    "point_raw": "静岡県 沼津市 戸田港",
    "kanso_raw": "午前便、時折、大鯖もヒット。今日も良いサイズが揃いました。大鯖は入れ喰いにならず少しで良いお土産になりました。 朝からしおの流れ良くポツポツの喰い。 最後にマダイがヒットしてきてくれました。 イサキ遅れ気味のスタートでしたが、喰い サイズ共にいい感じです。 宜しくお願いします。",
    "suion_raw": "22.5℃",
    "suishoku_raw": "",
    "color_raw": "",
    "source": "chowari/ふじ丸",
    "tide_label": "小潮",
    "weather_text": "曇り",
    "weather_detail": {
      "sunrise": "04:31",
      "sunset": "19:02",
      "moonrise": "13:02",
      "moonset": "",
      "weather": "曇り",
      "temp_high": "27℃",
      "temp_low": "21℃",
      "pressure": "1009.1hPa",
      "wind_dir": "東",
      "wind_speed": "1.8m/s",
      "wave_dir": "南西",
      "wave_height": "0.4m/s",
      "water_temp": "22.5℃",
      "tide": "小潮",
      "moon_age": "8.0",
      "bi": "7.5"
    }
  },
  {
    "ship": "ふじ丸",
    "area": "戸田港",
    "date": "2026/06/23",
    "trip_no": 1,
    "fish_raw": "マダイ",
    "count_raw": "合計1匹",
    "size_raw": "",
    "weight_raw": "",
    "tokki_raw": "外道",
    "point_raw": "静岡県 沼津市 戸田港",
    "kanso_raw": "午前便、時折、大鯖もヒット。今日も良いサイズが揃いました。大鯖は入れ喰いにならず少しで良いお土産になりました。 朝からしおの流れ良くポツポツの喰い。 最後にマダイがヒットしてきてくれました。 イサキ遅れ気味のスタートでしたが、喰い サイズ共にいい感じです。 宜しくお願いします。",
    "suion_raw": "22.5℃",
    "suishoku_raw": "",
    "color_raw": "",
    "source": "chowari/ふじ丸",
    "tide_label": "小潮",
    "weather_text": "曇り",
    "weather_detail": {
      "sunrise": "04:31",
      "sunset": "19:02",
      "moonrise": "13:02",
      "moonset": "",
      "weather": "曇り",
      "temp_high": "27℃",
      "temp_low": "21℃",
      "pressure": "1009.1hPa",
      "wind_dir": "東",
      "wind_speed": "1.8m/s",
      "wave_dir": "南西",
      "wave_height": "0.4m/s",
      "water_temp": "22.5℃",
      "tide": "小潮",
      "moon_age": "8.0",
      "bi": "7.5"
    }
  },
  {
    "ship": "ふじ丸",
    "area": "戸田港",
    "date": "2026/06/23",
    "trip_no": 1,
    "fish_raw": "サバ",
    "count_raw": "",
    "size_raw": "",
    "weight_raw": "",
    "tokki_raw": "外道",
    "point_raw": "静岡県 沼津市 戸田港",
    "kanso_raw": "午前便、時折、大鯖もヒット。今日も良いサイズが揃いました。大鯖は入れ喰いにならず少しで良いお土産になりました。 朝からしおの流れ良くポツポツの喰い。 最後にマダイがヒットしてきてくれました。 イサキ遅れ気味のスタートでしたが、喰い サイズ共にいい感じです。 宜しくお願いします。",
    "suion_raw": "22.5℃",
    "suishoku_raw": "",
    "color_raw": "",
    "source": "chowari/ふじ丸",
    "tide_label": "小潮",
    "weather_text": "曇り",
    "weather_detail": {
      "sunrise": "04:31",
      "sunset": "19:02",
      "moonrise": "13:02",
      "moonset": "",
      "weather": "曇り",
      "temp_high": "27℃",
      "temp_low": "21℃",
      "pressure": "1009.1hPa",
      "wind_dir": "東",
      "wind_speed": "1.8m/s",
      "wave_dir": "南西",
      "wave_height": "0.4m/s",
      "water_temp": "22.5℃",
      "tide": "小潮",
      "moon_age": "8.0",
      "bi": "7.5"
    }
  },
  {
    "ship": "ふじ丸",
    "area": "戸田港",
    "date": "2026/06/19",
    "trip_no": 1,
    "fish_raw": "マルイカ",
    "count_raw": "8～40匹",
    "size_raw": "",
    "weight_raw": "",
    "tokki_raw": "メイン",
    "point_raw": "静岡県 沼津市 戸田港",
    "kanso_raw": "夕方便、イカメタル好調です。サイズもデカい。イカメタルファン宜しくお願いします。 この時期イカメタル入門にはベストです。 中乗りさんも優しくレクチャーします。 初めてでもどうぞ。",
    "suion_raw": "21.3℃",
    "suishoku_raw": "",
    "color_raw": "",
    "source": "chowari/ふじ丸",
    "tide_label": "中潮",
    "weather_text": "晴れ後時々曇り",
    "weather_detail": {
      "sunrise": "04:30",
      "sunset": "19:02",
      "moonrise": "08:48",
      "moonset": "22:33",
      "weather": "晴れ後時々曇り",
      "temp_high": "31℃",
      "temp_low": "21℃",
      "pressure": "1011.0hPa",
      "wind_dir": "南南西",
      "wind_speed": "0.9m/s",
      "wave_dir": "南南西",
      "wave_height": "0.6m/s",
      "water_temp": "21.3℃",
      "tide": "中潮",
      "moon_age": "4.0",
      "bi": "8.4"
    }
  },
  {
    "ship": "ふじ丸",
    "area": "戸田港",
    "date": "2026/06/18",
    "trip_no": 1,
    "fish_raw": "マルイカ",
    "count_raw": "15～29匹",
    "size_raw": "",
    "weight_raw": "",
    "tokki_raw": "メイン",
    "point_raw": "静岡県 沼津市 戸田港",
    "kanso_raw": "夕方便、今夜はイカメタル初挑戦の方々でチャレンジして頂きました。 この時期はイカメタル初挑戦には良い時だと思います。 ドシドシチャレンジしてみて下さい。",
    "suion_raw": "21.0℃",
    "suishoku_raw": "",
    "color_raw": "",
    "source": "chowari/ふじ丸",
    "tide_label": "中潮",
    "weather_text": "晴れ後時々曇り",
    "weather_detail": {
      "sunrise": "04:30",
      "sunset": "19:01",
      "moonrise": "07:36",
      "moonset": "22:00",
      "weather": "晴れ後時々曇り",
      "temp_high": "30℃",
      "temp_low": "20℃",
      "pressure": "1009.3hPa",
      "wind_dir": "東北東",
      "wind_speed": "3.3m/s",
      "wave_dir": "南南西",
      "wave_height": "0.8m/s",
      "water_temp": "21.0℃",
      "tide": "中潮",
      "moon_age": "3.0",
      "bi": "7.8"
    }
  }
]