[
  {
    "ship": "新栄丸",
    "area": "江見",
    "date": "2026/06/14",
    "trip_no": 1,
    "fish_raw": "クロムツ",
    "count_raw": "0～2匹",
    "size_raw": "",
    "weight_raw": "",
    "tokki_raw": "メイン",
    "point_raw": "千葉県 鴨川市 江見漁港",
    "kanso_raw": "黒ムツ・コマセ五目で出船。 本日ガラガラ出船でした(T_T)美味しいお魚から入って潮の速い中ポツポツ・・。最高４点掛け等ありお土産出来ました。その後はハチビキ狙うもサバのみで残念。最後はコマセ五目で、イサキは各ポイントで釣れお土産十分です。今日はマダイ・マハタは残念。",
    "suion_raw": "22.3℃",
    "suishoku_raw": "",
    "color_raw": "",
    "source": "chowari/新栄丸",
    "tide_label": "大潮",
    "weather_text": "曇り時々晴れ",
    "weather_detail": {
      "sunrise": "04:25",
      "sunset": "18:55",
      "moonrise": "02:53",
      "moonset": "18:15",
      "weather": "曇り時々晴れ",
      "temp_high": "28℃",
      "temp_low": "18℃",
      "pressure": "1017.6hPa",
      "wind_dir": "南南西",
      "wind_speed": "3.4m/s",
      "wave_dir": "南東",
      "wave_height": "0.9m/s",
      "water_temp": "22.3℃",
      "tide": "大潮",
      "moon_age": "28.3",
      "bi": "9.9"
    }
  },
  {
    "ship": "新栄丸",
    "area": "江見",
    "date": "2026/06/14",
    "trip_no": 1,
    "fish_raw": "サバ",
    "count_raw": "",
    "size_raw": "",
    "weight_raw": "",
    "tokki_raw": "外道",
    "point_raw": "千葉県 鴨川市 江見漁港",
    "kanso_raw": "黒ムツ・コマセ五目で出船。 本日ガラガラ出船でした(T_T)美味しいお魚から入って潮の速い中ポツポツ・・。最高４点掛け等ありお土産出来ました。その後はハチビキ狙うもサバのみで残念。最後はコマセ五目で、イサキは各ポイントで釣れお土産十分です。今日はマダイ・マハタは残念。",
    "suion_raw": "22.3℃",
    "suishoku_raw": "",
    "color_raw": "",
    "source": "chowari/新栄丸",
    "tide_label": "大潮",
    "weather_text": "曇り時々晴れ",
    "weather_detail": {
      "sunrise": "04:25",
      "sunset": "18:55",
      "moonrise": "02:53",
      "moonset": "18:15",
      "weather": "曇り時々晴れ",
      "temp_high": "28℃",
      "temp_low": "18℃",
      "pressure": "1017.6hPa",
      "wind_dir": "南南西",
      "wind_speed": "3.4m/s",
      "wave_dir": "南東",
      "wave_height": "0.9m/s",
      "water_temp": "22.3℃",
      "tide": "大潮",
      "moon_age": "28.3",
      "bi": "9.9"
    }
  },
  {
    "ship": "新栄丸",
    "area": "江見",
    "date": "2026/06/14",
    "trip_no": 1,
    "fish_raw": "イサキ",
    "count_raw": "",
    "size_raw": "",
    "weight_raw": "",
    "tokki_raw": "外道",
    "point_raw": "千葉県 鴨川市 江見漁港",
    "kanso_raw": "黒ムツ・コマセ五目で出船。 本日ガラガラ出船でした(T_T)美味しいお魚から入って潮の速い中ポツポツ・・。最高４点掛け等ありお土産出来ました。その後はハチビキ狙うもサバのみで残念。最後はコマセ五目で、イサキは各ポイントで釣れお土産十分です。今日はマダイ・マハタは残念。",
    "suion_raw": "22.3℃",
    "suishoku_raw": "",
    "color_raw": "",
    "source": "chowari/新栄丸",
    "tide_label": "大潮",
    "weather_text": "曇り時々晴れ",
    "weather_detail": {
      "sunrise": "04:25",
      "sunset": "18:55",
      "moonrise": "02:53",
      "moonset": "18:15",
      "weather": "曇り時々晴れ",
      "temp_high": "28℃",
      "temp_low": "18℃",
      "pressure": "1017.6hPa",
      "wind_dir": "南南西",
      "wind_speed": "3.4m/s",
      "wave_dir": "南東",
      "wave_height": "0.9m/s",
      "water_temp": "22.3℃",
      "tide": "大潮",
      "moon_age": "28.3",
      "bi": "9.9"
    }
  },
  {
    "ship": "新栄丸",
    "area": "江見",
    "date": "2026/06/14",
    "trip_no": 1,
    "fish_raw": "ハナダイ",
    "count_raw": "",
    "size_raw": "",
    "weight_raw": "",
    "tokki_raw": "外道",
    "point_raw": "千葉県 鴨川市 江見漁港",
    "kanso_raw": "黒ムツ・コマセ五目で出船。 本日ガラガラ出船でした(T_T)美味しいお魚から入って潮の速い中ポツポツ・・。最高４点掛け等ありお土産出来ました。その後はハチビキ狙うもサバのみで残念。最後はコマセ五目で、イサキは各ポイントで釣れお土産十分です。今日はマダイ・マハタは残念。",
    "suion_raw": "22.3℃",
    "suishoku_raw": "",
    "color_raw": "",
    "source": "chowari/新栄丸",
    "tide_label": "大潮",
    "weather_text": "曇り時々晴れ",
    "weather_detail": {
      "sunrise": "04:25",
      "sunset": "18:55",
      "moonrise": "02:53",
      "moonset": "18:15",
      "weather": "曇り時々晴れ",
      "temp_high": "28℃",
      "temp_low": "18℃",
      "pressure": "1017.6hPa",
      "wind_dir": "南南西",
      "wind_speed": "3.4m/s",
      "wave_dir": "南東",
      "wave_height": "0.9m/s",
      "water_temp": "22.3℃",
      "tide": "大潮",
      "moon_age": "28.3",
      "bi": "9.9"
    }
  },
  {
    "ship": "新栄丸",
    "area": "江見",
    "date": "2026/06/14",
    "trip_no": 1,
    "fish_raw": "メジナ",
    "count_raw": "",
    "size_raw": "",
    "weight_raw": "",
    "tokki_raw": "外道",
    "point_raw": "千葉県 鴨川市 江見漁港",
    "kanso_raw": "黒ムツ・コマセ五目で出船。 本日ガラガラ出船でした(T_T)美味しいお魚から入って潮の速い中ポツポツ・・。最高４点掛け等ありお土産出来ました。その後はハチビキ狙うもサバのみで残念。最後はコマセ五目で、イサキは各ポイントで釣れお土産十分です。今日はマダイ・マハタは残念。",
    "suion_raw": "22.3℃",
    "suishoku_raw": "",
    "color_raw": "",
    "source": "chowari/新栄丸",
    "tide_label": "大潮",
    "weather_text": "曇り時々晴れ",
    "weather_detail": {
      "sunrise": "04:25",
      "sunset": "18:55",
      "moonrise": "02:53",
      "moonset": "18:15",
      "weather": "曇り時々晴れ",
      "temp_high": "28℃",
      "temp_low": "18℃",
      "pressure": "1017.6hPa",
      "wind_dir": "南南西",
      "wind_speed": "3.4m/s",
      "wave_dir": "南東",
      "wave_height": "0.9m/s",
      "water_temp": "22.3℃",
      "tide": "大潮",
      "moon_age": "28.3",
      "bi": "9.9"
    }
  },
  {
    "ship": "新栄丸",
    "area": "江見",
    "date": "2026/06/14",
    "trip_no": 1,
    "fish_raw": "ウマヅラハギ",
    "count_raw": "",
    "size_raw": "",
    "weight_raw": "",
    "tokki_raw": "外道",
    "point_raw": "千葉県 鴨川市 江見漁港",
    "kanso_raw": "黒ムツ・コマセ五目で出船。 本日ガラガラ出船でした(T_T)美味しいお魚から入って潮の速い中ポツポツ・・。最高４点掛け等ありお土産出来ました。その後はハチビキ狙うもサバのみで残念。最後はコマセ五目で、イサキは各ポイントで釣れお土産十分です。今日はマダイ・マハタは残念。",
    "suion_raw": "22.3℃",
    "suishoku_raw": "",
    "color_raw": "",
    "source": "chowari/新栄丸",
    "tide_label": "大潮",
    "weather_text": "曇り時々晴れ",
    "weather_detail": {
      "sunrise": "04:25",
      "sunset": "18:55",
      "moonrise": "02:53",
      "moonset": "18:15",
      "weather": "曇り時々晴れ",
      "temp_high": "28℃",
      "temp_low": "18℃",
      "pressure": "1017.6hPa",
      "wind_dir": "南南西",
      "wind_speed": "3.4m/s",
      "wave_dir": "南東",
      "wave_height": "0.9m/s",
      "water_temp": "22.3℃",
      "tide": "大潮",
      "moon_age": "28.3",
      "bi": "9.9"
    }
  },
  {
    "ship": "新栄丸",
    "area": "江見",
    "date": "2026/06/14",
    "trip_no": 1,
    "fish_raw": "サバ",
    "count_raw": "",
    "size_raw": "",
    "weight_raw": "",
    "tokki_raw": "外道",
    "point_raw": "千葉県 鴨川市 江見漁港",
    "kanso_raw": "黒ムツ・コマセ五目で出船。 本日ガラガラ出船でした(T_T)美味しいお魚から入って潮の速い中ポツポツ・・。最高４点掛け等ありお土産出来ました。その後はハチビキ狙うもサバのみで残念。最後はコマセ五目で、イサキは各ポイントで釣れお土産十分です。今日はマダイ・マハタは残念。",
    "suion_raw": "22.3℃",
    "suishoku_raw": "",
    "color_raw": "",
    "source": "chowari/新栄丸",
    "tide_label": "大潮",
    "weather_text": "曇り時々晴れ",
    "weather_detail": {
      "sunrise": "04:25",
      "sunset": "18:55",
      "moonrise": "02:53",
      "moonset": "18:15",
      "weather": "曇り時々晴れ",
      "temp_high": "28℃",
      "temp_low": "18℃",
      "pressure": "1017.6hPa",
      "wind_dir": "南南西",
      "wind_speed": "3.4m/s",
      "wave_dir": "南東",
      "wave_height": "0.9m/s",
      "water_temp": "22.3℃",
      "tide": "大潮",
      "moon_age": "28.3",
      "bi": "9.9"
    }
  },
  {
    "ship": "新栄丸",
    "area": "江見",
    "date": "2026/06/13",
    "trip_no": 1,
    "fish_raw": "クロムツ",
    "count_raw": "",
    "size_raw": "",
    "weight_raw": "",
    "tokki_raw": "メイン",
    "point_raw": "千葉県 鴨川市 江見漁港",
    "kanso_raw": "黒ムツ・マダイ五目で出船、 美味しいお魚から入って、いつもの爆釣ではありませんでしたが、最高６点掛けなどありしっかり釣れた方も・・・。潮型が悪かったので手返しの差が出ました。",
    "suion_raw": "22.2℃",
    "suishoku_raw": "",
    "color_raw": "",
    "source": "chowari/新栄丸",
    "tide_label": "中潮",
    "weather_text": "晴れ時々曇り",
    "weather_detail": {
      "sunrise": "04:25",
      "sunset": "18:55",
      "moonrise": "02:06",
      "moonset": "16:59",
      "weather": "晴れ時々曇り",
      "temp_high": "27℃",
      "temp_low": "17℃",
      "pressure": "1015.0hPa",
      "wind_dir": "南西",
      "wind_speed": "2.1m/s",
      "wave_dir": "南南東",
      "wave_height": "0.8m/s",
      "water_temp": "22.2℃",
      "tide": "中潮",
      "moon_age": "27.3",
      "bi": "9.0"
    }
  },
  {
    "ship": "新栄丸",
    "area": "江見",
    "date": "2026/06/13",
    "trip_no": 1,
    "fish_raw": "メダイ",
    "count_raw": "竿頭3匹",
    "size_raw": "",
    "weight_raw": "",
    "tokki_raw": "外道",
    "point_raw": "千葉県 鴨川市 江見漁港",
    "kanso_raw": "黒ムツ・マダイ五目で出船、 美味しいお魚から入って、いつもの爆釣ではありませんでしたが、最高６点掛けなどありしっかり釣れた方も・・・。潮型が悪かったので手返しの差が出ました。",
    "suion_raw": "22.2℃",
    "suishoku_raw": "",
    "color_raw": "",
    "source": "chowari/新栄丸",
    "tide_label": "中潮",
    "weather_text": "晴れ時々曇り",
    "weather_detail": {
      "sunrise": "04:25",
      "sunset": "18:55",
      "moonrise": "02:06",
      "moonset": "16:59",
      "weather": "晴れ時々曇り",
      "temp_high": "27℃",
      "temp_low": "17℃",
      "pressure": "1015.0hPa",
      "wind_dir": "南西",
      "wind_speed": "2.1m/s",
      "wave_dir": "南南東",
      "wave_height": "0.8m/s",
      "water_temp": "22.2℃",
      "tide": "中潮",
      "moon_age": "27.3",
      "bi": "9.0"
    }
  },
  {
    "ship": "新栄丸",
    "area": "江見",
    "date": "2026/06/13",
    "trip_no": 1,
    "fish_raw": "サバ",
    "count_raw": "",
    "size_raw": "",
    "weight_raw": "",
    "tokki_raw": "外道",
    "point_raw": "千葉県 鴨川市 江見漁港",
    "kanso_raw": "黒ムツ・マダイ五目で出船、 美味しいお魚から入って、いつもの爆釣ではありませんでしたが、最高６点掛けなどありしっかり釣れた方も・・・。潮型が悪かったので手返しの差が出ました。",
    "suion_raw": "22.2℃",
    "suishoku_raw": "",
    "color_raw": "",
    "source": "chowari/新栄丸",
    "tide_label": "中潮",
    "weather_text": "晴れ時々曇り",
    "weather_detail": {
      "sunrise": "04:25",
      "sunset": "18:55",
      "moonrise": "02:06",
      "moonset": "16:59",
      "weather": "晴れ時々曇り",
      "temp_high": "27℃",
      "temp_low": "17℃",
      "pressure": "1015.0hPa",
      "wind_dir": "南西",
      "wind_speed": "2.1m/s",
      "wave_dir": "南南東",
      "wave_height": "0.8m/s",
      "water_temp": "22.2℃",
      "tide": "中潮",
      "moon_age": "27.3",
      "bi": "9.0"
    }
  },
  {
    "ship": "新栄丸",
    "area": "江見",
    "date": "2026/06/13",
    "trip_no": 1,
    "fish_raw": "マダイ",
    "count_raw": "",
    "size_raw": "",
    "weight_raw": "",
    "tokki_raw": "外道",
    "point_raw": "千葉県 鴨川市 江見漁港",
    "kanso_raw": "黒ムツ・マダイ五目で出船、 美味しいお魚から入って、いつもの爆釣ではありませんでしたが、最高６点掛けなどありしっかり釣れた方も・・・。潮型が悪かったので手返しの差が出ました。",
    "suion_raw": "22.2℃",
    "suishoku_raw": "",
    "color_raw": "",
    "source": "chowari/新栄丸",
    "tide_label": "中潮",
    "weather_text": "晴れ時々曇り",
    "weather_detail": {
      "sunrise": "04:25",
      "sunset": "18:55",
      "moonrise": "02:06",
      "moonset": "16:59",
      "weather": "晴れ時々曇り",
      "temp_high": "27℃",
      "temp_low": "17℃",
      "pressure": "1015.0hPa",
      "wind_dir": "南西",
      "wind_speed": "2.1m/s",
      "wave_dir": "南南東",
      "wave_height": "0.8m/s",
      "water_temp": "22.2℃",
      "tide": "中潮",
      "moon_age": "27.3",
      "bi": "9.0"
    }
  },
  {
    "ship": "新栄丸",
    "area": "江見",
    "date": "2026/06/13",
    "trip_no": 1,
    "fish_raw": "マハタ",
    "count_raw": "竿頭2匹",
    "size_raw": "",
    "weight_raw": "",
    "tokki_raw": "外道",
    "point_raw": "千葉県 鴨川市 江見漁港",
    "kanso_raw": "黒ムツ・マダイ五目で出船、 美味しいお魚から入って、いつもの爆釣ではありませんでしたが、最高６点掛けなどありしっかり釣れた方も・・・。潮型が悪かったので手返しの差が出ました。",
    "suion_raw": "22.2℃",
    "suishoku_raw": "",
    "color_raw": "",
    "source": "chowari/新栄丸",
    "tide_label": "中潮",
    "weather_text": "晴れ時々曇り",
    "weather_detail": {
      "sunrise": "04:25",
      "sunset": "18:55",
      "moonrise": "02:06",
      "moonset": "16:59",
      "weather": "晴れ時々曇り",
      "temp_high": "27℃",
      "temp_low": "17℃",
      "pressure": "1015.0hPa",
      "wind_dir": "南西",
      "wind_speed": "2.1m/s",
      "wave_dir": "南南東",
      "wave_height": "0.8m/s",
      "water_temp": "22.2℃",
      "tide": "中潮",
      "moon_age": "27.3",
      "bi": "9.0"
    }
  },
  {
    "ship": "新栄丸",
    "area": "江見",
    "date": "2026/06/13",
    "trip_no": 1,
    "fish_raw": "イサキ",
    "count_raw": "竿頭10匹",
    "size_raw": "",
    "weight_raw": "",
    "tokki_raw": "外道",
    "point_raw": "千葉県 鴨川市 江見漁港",
    "kanso_raw": "黒ムツ・マダイ五目で出船、 美味しいお魚から入って、いつもの爆釣ではありませんでしたが、最高６点掛けなどありしっかり釣れた方も・・・。潮型が悪かったので手返しの差が出ました。",
    "suion_raw": "22.2℃",
    "suishoku_raw": "",
    "color_raw": "",
    "source": "chowari/新栄丸",
    "tide_label": "中潮",
    "weather_text": "晴れ時々曇り",
    "weather_detail": {
      "sunrise": "04:25",
      "sunset": "18:55",
      "moonrise": "02:06",
      "moonset": "16:59",
      "weather": "晴れ時々曇り",
      "temp_high": "27℃",
      "temp_low": "17℃",
      "pressure": "1015.0hPa",
      "wind_dir": "南西",
      "wind_speed": "2.1m/s",
      "wave_dir": "南南東",
      "wave_height": "0.8m/s",
      "water_temp": "22.2℃",
      "tide": "中潮",
      "moon_age": "27.3",
      "bi": "9.0"
    }
  },
  {
    "ship": "新栄丸",
    "area": "江見",
    "date": "2026/06/13",
    "trip_no": 1,
    "fish_raw": "ハナダイ",
    "count_raw": "竿頭7匹",
    "size_raw": "",
    "weight_raw": "",
    "tokki_raw": "外道",
    "point_raw": "千葉県 鴨川市 江見漁港",
    "kanso_raw": "黒ムツ・マダイ五目で出船、 美味しいお魚から入って、いつもの爆釣ではありませんでしたが、最高６点掛けなどありしっかり釣れた方も・・・。潮型が悪かったので手返しの差が出ました。",
    "suion_raw": "22.2℃",
    "suishoku_raw": "",
    "color_raw": "",
    "source": "chowari/新栄丸",
    "tide_label": "中潮",
    "weather_text": "晴れ時々曇り",
    "weather_detail": {
      "sunrise": "04:25",
      "sunset": "18:55",
      "moonrise": "02:06",
      "moonset": "16:59",
      "weather": "晴れ時々曇り",
      "temp_high": "27℃",
      "temp_low": "17℃",
      "pressure": "1015.0hPa",
      "wind_dir": "南西",
      "wind_speed": "2.1m/s",
      "wave_dir": "南南東",
      "wave_height": "0.8m/s",
      "water_temp": "22.2℃",
      "tide": "中潮",
      "moon_age": "27.3",
      "bi": "9.0"
    }
  },
  {
    "ship": "新栄丸",
    "area": "江見",
    "date": "2026/06/13",
    "trip_no": 1,
    "fish_raw": "ウマヅラハギ",
    "count_raw": "竿頭3匹",
    "size_raw": "",
    "weight_raw": "",
    "tokki_raw": "外道",
    "point_raw": "千葉県 鴨川市 江見漁港",
    "kanso_raw": "黒ムツ・マダイ五目で出船、 美味しいお魚から入って、いつもの爆釣ではありませんでしたが、最高６点掛けなどありしっかり釣れた方も・・・。潮型が悪かったので手返しの差が出ました。",
    "suion_raw": "22.2℃",
    "suishoku_raw": "",
    "color_raw": "",
    "source": "chowari/新栄丸",
    "tide_label": "中潮",
    "weather_text": "晴れ時々曇り",
    "weather_detail": {
      "sunrise": "04:25",
      "sunset": "18:55",
      "moonrise": "02:06",
      "moonset": "16:59",
      "weather": "晴れ時々曇り",
      "temp_high": "27℃",
      "temp_low": "17℃",
      "pressure": "1015.0hPa",
      "wind_dir": "南西",
      "wind_speed": "2.1m/s",
      "wave_dir": "南南東",
      "wave_height": "0.8m/s",
      "water_temp": "22.2℃",
      "tide": "中潮",
      "moon_age": "27.3",
      "bi": "9.0"
    }
  },
  {
    "ship": "新栄丸",
    "area": "江見",
    "date": "2026/06/13",
    "trip_no": 1,
    "fish_raw": "メジナ",
    "count_raw": "",
    "size_raw": "",
    "weight_raw": "",
    "tokki_raw": "外道",
    "point_raw": "千葉県 鴨川市 江見漁港",
    "kanso_raw": "黒ムツ・マダイ五目で出船、 美味しいお魚から入って、いつもの爆釣ではありませんでしたが、最高６点掛けなどありしっかり釣れた方も・・・。潮型が悪かったので手返しの差が出ました。",
    "suion_raw": "22.2℃",
    "suishoku_raw": "",
    "color_raw": "",
    "source": "chowari/新栄丸",
    "tide_label": "中潮",
    "weather_text": "晴れ時々曇り",
    "weather_detail": {
      "sunrise": "04:25",
      "sunset": "18:55",
      "moonrise": "02:06",
      "moonset": "16:59",
      "weather": "晴れ時々曇り",
      "temp_high": "27℃",
      "temp_low": "17℃",
      "pressure": "1015.0hPa",
      "wind_dir": "南西",
      "wind_speed": "2.1m/s",
      "wave_dir": "南南東",
      "wave_height": "0.8m/s",
      "water_temp": "22.2℃",
      "tide": "中潮",
      "moon_age": "27.3",
      "bi": "9.0"
    }
  },
  {
    "ship": "新栄丸",
    "area": "江見",
    "date": "2026/06/12",
    "trip_no": 1,
    "fish_raw": "ハチビキ",
    "count_raw": "10～20匹",
    "size_raw": "36～48cm",
    "weight_raw": "",
    "tokki_raw": "メイン",
    "point_raw": "千葉県 鴨川市 江見漁港",
    "kanso_raw": "連日爆釣 詳しくは電話📞でお願いします 書けませんが 高級魚全員規定数30達成",
    "suion_raw": "22.1℃",
    "suishoku_raw": "",
    "color_raw": "",
    "source": "chowari/新栄丸",
    "tide_label": "中潮",
    "weather_text": "曇り",
    "weather_detail": {
      "sunrise": "04:25",
      "sunset": "18:55",
      "moonrise": "01:27",
      "moonset": "15:43",
      "weather": "曇り",
      "temp_high": "27℃",
      "temp_low": "17℃",
      "pressure": "1012.7hPa",
      "wind_dir": "南",
      "wind_speed": "2.5m/s",
      "wave_dir": "南南東",
      "wave_height": "1.0m/s",
      "water_temp": "22.1℃",
      "tide": "中潮",
      "moon_age": "26.3",
      "bi": "9.8"
    }
  },
  {
    "ship": "新栄丸",
    "area": "江見",
    "date": "2026/06/12",
    "trip_no": 1,
    "fish_raw": "マダイ",
    "count_raw": "0～3匹",
    "size_raw": "0.40～0.80kg",
    "weight_raw": "",
    "tokki_raw": "外道",
    "point_raw": "千葉県 鴨川市 江見漁港",
    "kanso_raw": "連日爆釣 詳しくは電話📞でお願いします 書けませんが 高級魚全員規定数30達成",
    "suion_raw": "22.1℃",
    "suishoku_raw": "",
    "color_raw": "",
    "source": "chowari/新栄丸",
    "tide_label": "中潮",
    "weather_text": "曇り",
    "weather_detail": {
      "sunrise": "04:25",
      "sunset": "18:55",
      "moonrise": "01:27",
      "moonset": "15:43",
      "weather": "曇り",
      "temp_high": "27℃",
      "temp_low": "17℃",
      "pressure": "1012.7hPa",
      "wind_dir": "南",
      "wind_speed": "2.5m/s",
      "wave_dir": "南南東",
      "wave_height": "1.0m/s",
      "water_temp": "22.1℃",
      "tide": "中潮",
      "moon_age": "26.3",
      "bi": "9.8"
    }
  },
  {
    "ship": "新栄丸",
    "area": "江見",
    "date": "2026/06/12",
    "trip_no": 1,
    "fish_raw": "イサキ",
    "count_raw": "4～15匹",
    "size_raw": "23～34cm",
    "weight_raw": "",
    "tokki_raw": "外道",
    "point_raw": "千葉県 鴨川市 江見漁港",
    "kanso_raw": "連日爆釣 詳しくは電話📞でお願いします 書けませんが 高級魚全員規定数30達成",
    "suion_raw": "22.1℃",
    "suishoku_raw": "",
    "color_raw": "",
    "source": "chowari/新栄丸",
    "tide_label": "中潮",
    "weather_text": "曇り",
    "weather_detail": {
      "sunrise": "04:25",
      "sunset": "18:55",
      "moonrise": "01:27",
      "moonset": "15:43",
      "weather": "曇り",
      "temp_high": "27℃",
      "temp_low": "17℃",
      "pressure": "1012.7hPa",
      "wind_dir": "南",
      "wind_speed": "2.5m/s",
      "wave_dir": "南南東",
      "wave_height": "1.0m/s",
      "water_temp": "22.1℃",
      "tide": "中潮",
      "moon_age": "26.3",
      "bi": "9.8"
    }
  },
  {
    "ship": "新栄丸",
    "area": "江見",
    "date": "2026/06/12",
    "trip_no": 1,
    "fish_raw": "メダイ",
    "count_raw": "0～3匹",
    "size_raw": "0.70～1.80kg",
    "weight_raw": "",
    "tokki_raw": "外道",
    "point_raw": "千葉県 鴨川市 江見漁港",
    "kanso_raw": "連日爆釣 詳しくは電話📞でお願いします 書けませんが 高級魚全員規定数30達成",
    "suion_raw": "22.1℃",
    "suishoku_raw": "",
    "color_raw": "",
    "source": "chowari/新栄丸",
    "tide_label": "中潮",
    "weather_text": "曇り",
    "weather_detail": {
      "sunrise": "04:25",
      "sunset": "18:55",
      "moonrise": "01:27",
      "moonset": "15:43",
      "weather": "曇り",
      "temp_high": "27℃",
      "temp_low": "17℃",
      "pressure": "1012.7hPa",
      "wind_dir": "南",
      "wind_speed": "2.5m/s",
      "wave_dir": "南南東",
      "wave_height": "1.0m/s",
      "water_temp": "22.1℃",
      "tide": "中潮",
      "moon_age": "26.3",
      "bi": "9.8"
    }
  },
  {
    "ship": "新栄丸",
    "area": "江見",
    "date": "2026/06/12",
    "trip_no": 1,
    "fish_raw": "ウマヅラハギ",
    "count_raw": "0～2匹",
    "size_raw": "35～43cm",
    "weight_raw": "",
    "tokki_raw": "外道",
    "point_raw": "千葉県 鴨川市 江見漁港",
    "kanso_raw": "連日爆釣 詳しくは電話📞でお願いします 書けませんが 高級魚全員規定数30達成",
    "suion_raw": "22.1℃",
    "suishoku_raw": "",
    "color_raw": "",
    "source": "chowari/新栄丸",
    "tide_label": "中潮",
    "weather_text": "曇り",
    "weather_detail": {
      "sunrise": "04:25",
      "sunset": "18:55",
      "moonrise": "01:27",
      "moonset": "15:43",
      "weather": "曇り",
      "temp_high": "27℃",
      "temp_low": "17℃",
      "pressure": "1012.7hPa",
      "wind_dir": "南",
      "wind_speed": "2.5m/s",
      "wave_dir": "南南東",
      "wave_height": "1.0m/s",
      "water_temp": "22.1℃",
      "tide": "中潮",
      "moon_age": "26.3",
      "bi": "9.8"
    }
  },
  {
    "ship": "新栄丸",
    "area": "江見",
    "date": "2026/06/11",
    "trip_no": 1,
    "fish_raw": "クロムツ",
    "count_raw": "竿頭20匹",
    "size_raw": "",
    "weight_raw": "",
    "tokki_raw": "メイン",
    "point_raw": "千葉県 鴨川市 江見漁港",
    "kanso_raw": "黒ムツ・マダイ五目で出船今日も(^^)v(^^)v 美味しいお魚さんから入って、昨日のように爆釣ではなかったけど全員お刺身サイズ交じりでしっかりお土産釣れました。同じ場所でハチビキも釣れ、後半のマダイ五目は、マダイっ子とハナダイでトップは１０匹程度。今日もクーラーいっぱいです。美味しく食べてあげてくださいね(#^.^#)明日も黒ムツ・マダイ五目で出船しますのでご予約お待ちしております。ガラガラです(T_T)(T_T)",
    "suion_raw": "22.0℃",
    "suishoku_raw": "",
    "color_raw": "",
    "source": "chowari/新栄丸",
    "tide_label": "若潮",
    "weather_text": "曇り時々晴れ",
    "weather_detail": {
      "sunrise": "04:25",
      "sunset": "18:54",
      "moonrise": "00:55",
      "moonset": "14:30",
      "weather": "曇り時々晴れ",
      "temp_high": "27℃",
      "temp_low": "16℃",
      "pressure": "1012.2hPa",
      "wind_dir": "東南東",
      "wind_speed": "2.1m/s",
      "wave_dir": "南南東",
      "wave_height": "1.0m/s",
      "water_temp": "22.0℃",
      "tide": "若潮",
      "moon_age": "25.3",
      "bi": "10.0"
    }
  },
  {
    "ship": "新栄丸",
    "area": "江見",
    "date": "2026/06/11",
    "trip_no": 1,
    "fish_raw": "メダイ",
    "count_raw": "1～3匹",
    "size_raw": "",
    "weight_raw": "",
    "tokki_raw": "外道",
    "point_raw": "千葉県 鴨川市 江見漁港",
    "kanso_raw": "黒ムツ・マダイ五目で出船今日も(^^)v(^^)v 美味しいお魚さんから入って、昨日のように爆釣ではなかったけど全員お刺身サイズ交じりでしっかりお土産釣れました。同じ場所でハチビキも釣れ、後半のマダイ五目は、マダイっ子とハナダイでトップは１０匹程度。今日もクーラーいっぱいです。美味しく食べてあげてくださいね(#^.^#)明日も黒ムツ・マダイ五目で出船しますのでご予約お待ちしております。ガラガラです(T_T)(T_T)",
    "suion_raw": "22.0℃",
    "suishoku_raw": "",
    "color_raw": "",
    "source": "chowari/新栄丸",
    "tide_label": "若潮",
    "weather_text": "曇り時々晴れ",
    "weather_detail": {
      "sunrise": "04:25",
      "sunset": "18:54",
      "moonrise": "00:55",
      "moonset": "14:30",
      "weather": "曇り時々晴れ",
      "temp_high": "27℃",
      "temp_low": "16℃",
      "pressure": "1012.2hPa",
      "wind_dir": "東南東",
      "wind_speed": "2.1m/s",
      "wave_dir": "南南東",
      "wave_height": "1.0m/s",
      "water_temp": "22.0℃",
      "tide": "若潮",
      "moon_age": "25.3",
      "bi": "10.0"
    }
  },
  {
    "ship": "新栄丸",
    "area": "江見",
    "date": "2026/06/11",
    "trip_no": 1,
    "fish_raw": "オアカムロ",
    "count_raw": "",
    "size_raw": "",
    "weight_raw": "",
    "tokki_raw": "外道",
    "point_raw": "千葉県 鴨川市 江見漁港",
    "kanso_raw": "黒ムツ・マダイ五目で出船今日も(^^)v(^^)v 美味しいお魚さんから入って、昨日のように爆釣ではなかったけど全員お刺身サイズ交じりでしっかりお土産釣れました。同じ場所でハチビキも釣れ、後半のマダイ五目は、マダイっ子とハナダイでトップは１０匹程度。今日もクーラーいっぱいです。美味しく食べてあげてくださいね(#^.^#)明日も黒ムツ・マダイ五目で出船しますのでご予約お待ちしております。ガラガラです(T_T)(T_T)",
    "suion_raw": "22.0℃",
    "suishoku_raw": "",
    "color_raw": "",
    "source": "chowari/新栄丸",
    "tide_label": "若潮",
    "weather_text": "曇り時々晴れ",
    "weather_detail": {
      "sunrise": "04:25",
      "sunset": "18:54",
      "moonrise": "00:55",
      "moonset": "14:30",
      "weather": "曇り時々晴れ",
      "temp_high": "27℃",
      "temp_low": "16℃",
      "pressure": "1012.2hPa",
      "wind_dir": "東南東",
      "wind_speed": "2.1m/s",
      "wave_dir": "南南東",
      "wave_height": "1.0m/s",
      "water_temp": "22.0℃",
      "tide": "若潮",
      "moon_age": "25.3",
      "bi": "10.0"
    }
  },
  {
    "ship": "新栄丸",
    "area": "江見",
    "date": "2026/06/11",
    "trip_no": 1,
    "fish_raw": "サバ",
    "count_raw": "",
    "size_raw": "",
    "weight_raw": "",
    "tokki_raw": "外道",
    "point_raw": "千葉県 鴨川市 江見漁港",
    "kanso_raw": "黒ムツ・マダイ五目で出船今日も(^^)v(^^)v 美味しいお魚さんから入って、昨日のように爆釣ではなかったけど全員お刺身サイズ交じりでしっかりお土産釣れました。同じ場所でハチビキも釣れ、後半のマダイ五目は、マダイっ子とハナダイでトップは１０匹程度。今日もクーラーいっぱいです。美味しく食べてあげてくださいね(#^.^#)明日も黒ムツ・マダイ五目で出船しますのでご予約お待ちしております。ガラガラです(T_T)(T_T)",
    "suion_raw": "22.0℃",
    "suishoku_raw": "",
    "color_raw": "",
    "source": "chowari/新栄丸",
    "tide_label": "若潮",
    "weather_text": "曇り時々晴れ",
    "weather_detail": {
      "sunrise": "04:25",
      "sunset": "18:54",
      "moonrise": "00:55",
      "moonset": "14:30",
      "weather": "曇り時々晴れ",
      "temp_high": "27℃",
      "temp_low": "16℃",
      "pressure": "1012.2hPa",
      "wind_dir": "東南東",
      "wind_speed": "2.1m/s",
      "wave_dir": "南南東",
      "wave_height": "1.0m/s",
      "water_temp": "22.0℃",
      "tide": "若潮",
      "moon_age": "25.3",
      "bi": "10.0"
    }
  },
  {
    "ship": "新栄丸",
    "area": "江見",
    "date": "2026/06/11",
    "trip_no": 1,
    "fish_raw": "マダイ",
    "count_raw": "",
    "size_raw": "",
    "weight_raw": "",
    "tokki_raw": "外道",
    "point_raw": "千葉県 鴨川市 江見漁港",
    "kanso_raw": "黒ムツ・マダイ五目で出船今日も(^^)v(^^)v 美味しいお魚さんから入って、昨日のように爆釣ではなかったけど全員お刺身サイズ交じりでしっかりお土産釣れました。同じ場所でハチビキも釣れ、後半のマダイ五目は、マダイっ子とハナダイでトップは１０匹程度。今日もクーラーいっぱいです。美味しく食べてあげてくださいね(#^.^#)明日も黒ムツ・マダイ五目で出船しますのでご予約お待ちしております。ガラガラです(T_T)(T_T)",
    "suion_raw": "22.0℃",
    "suishoku_raw": "",
    "color_raw": "",
    "source": "chowari/新栄丸",
    "tide_label": "若潮",
    "weather_text": "曇り時々晴れ",
    "weather_detail": {
      "sunrise": "04:25",
      "sunset": "18:54",
      "moonrise": "00:55",
      "moonset": "14:30",
      "weather": "曇り時々晴れ",
      "temp_high": "27℃",
      "temp_low": "16℃",
      "pressure": "1012.2hPa",
      "wind_dir": "東南東",
      "wind_speed": "2.1m/s",
      "wave_dir": "南南東",
      "wave_height": "1.0m/s",
      "water_temp": "22.0℃",
      "tide": "若潮",
      "moon_age": "25.3",
      "bi": "10.0"
    }
  },
  {
    "ship": "新栄丸",
    "area": "江見",
    "date": "2026/06/11",
    "trip_no": 1,
    "fish_raw": "ハナダイ",
    "count_raw": "",
    "size_raw": "",
    "weight_raw": "",
    "tokki_raw": "外道",
    "point_raw": "千葉県 鴨川市 江見漁港",
    "kanso_raw": "黒ムツ・マダイ五目で出船今日も(^^)v(^^)v 美味しいお魚さんから入って、昨日のように爆釣ではなかったけど全員お刺身サイズ交じりでしっかりお土産釣れました。同じ場所でハチビキも釣れ、後半のマダイ五目は、マダイっ子とハナダイでトップは１０匹程度。今日もクーラーいっぱいです。美味しく食べてあげてくださいね(#^.^#)明日も黒ムツ・マダイ五目で出船しますのでご予約お待ちしております。ガラガラです(T_T)(T_T)",
    "suion_raw": "22.0℃",
    "suishoku_raw": "",
    "color_raw": "",
    "source": "chowari/新栄丸",
    "tide_label": "若潮",
    "weather_text": "曇り時々晴れ",
    "weather_detail": {
      "sunrise": "04:25",
      "sunset": "18:54",
      "moonrise": "00:55",
      "moonset": "14:30",
      "weather": "曇り時々晴れ",
      "temp_high": "27℃",
      "temp_low": "16℃",
      "pressure": "1012.2hPa",
      "wind_dir": "東南東",
      "wind_speed": "2.1m/s",
      "wave_dir": "南南東",
      "wave_height": "1.0m/s",
      "water_temp": "22.0℃",
      "tide": "若潮",
      "moon_age": "25.3",
      "bi": "10.0"
    }
  },
  {
    "ship": "新栄丸",
    "area": "江見",
    "date": "2026/06/11",
    "trip_no": 1,
    "fish_raw": "イサキ",
    "count_raw": "竿頭10匹",
    "size_raw": "",
    "weight_raw": "",
    "tokki_raw": "外道",
    "point_raw": "千葉県 鴨川市 江見漁港",
    "kanso_raw": "黒ムツ・マダイ五目で出船今日も(^^)v(^^)v 美味しいお魚さんから入って、昨日のように爆釣ではなかったけど全員お刺身サイズ交じりでしっかりお土産釣れました。同じ場所でハチビキも釣れ、後半のマダイ五目は、マダイっ子とハナダイでトップは１０匹程度。今日もクーラーいっぱいです。美味しく食べてあげてくださいね(#^.^#)明日も黒ムツ・マダイ五目で出船しますのでご予約お待ちしております。ガラガラです(T_T)(T_T)",
    "suion_raw": "22.0℃",
    "suishoku_raw": "",
    "color_raw": "",
    "source": "chowari/新栄丸",
    "tide_label": "若潮",
    "weather_text": "曇り時々晴れ",
    "weather_detail": {
      "sunrise": "04:25",
      "sunset": "18:54",
      "moonrise": "00:55",
      "moonset": "14:30",
      "weather": "曇り時々晴れ",
      "temp_high": "27℃",
      "temp_low": "16℃",
      "pressure": "1012.2hPa",
      "wind_dir": "東南東",
      "wind_speed": "2.1m/s",
      "wave_dir": "南南東",
      "wave_height": "1.0m/s",
      "water_temp": "22.0℃",
      "tide": "若潮",
      "moon_age": "25.3",
      "bi": "10.0"
    }
  },
  {
    "ship": "新栄丸",
    "area": "江見",
    "date": "2026/06/11",
    "trip_no": 1,
    "fish_raw": "マハタ",
    "count_raw": "",
    "size_raw": "",
    "weight_raw": "",
    "tokki_raw": "外道",
    "point_raw": "千葉県 鴨川市 江見漁港",
    "kanso_raw": "黒ムツ・マダイ五目で出船今日も(^^)v(^^)v 美味しいお魚さんから入って、昨日のように爆釣ではなかったけど全員お刺身サイズ交じりでしっかりお土産釣れました。同じ場所でハチビキも釣れ、後半のマダイ五目は、マダイっ子とハナダイでトップは１０匹程度。今日もクーラーいっぱいです。美味しく食べてあげてくださいね(#^.^#)明日も黒ムツ・マダイ五目で出船しますのでご予約お待ちしております。ガラガラです(T_T)(T_T)",
    "suion_raw": "22.0℃",
    "suishoku_raw": "",
    "color_raw": "",
    "source": "chowari/新栄丸",
    "tide_label": "若潮",
    "weather_text": "曇り時々晴れ",
    "weather_detail": {
      "sunrise": "04:25",
      "sunset": "18:54",
      "moonrise": "00:55",
      "moonset": "14:30",
      "weather": "曇り時々晴れ",
      "temp_high": "27℃",
      "temp_low": "16℃",
      "pressure": "1012.2hPa",
      "wind_dir": "東南東",
      "wind_speed": "2.1m/s",
      "wave_dir": "南南東",
      "wave_height": "1.0m/s",
      "water_temp": "22.0℃",
      "tide": "若潮",
      "moon_age": "25.3",
      "bi": "10.0"
    }
  },
  {
    "ship": "新栄丸",
    "area": "江見",
    "date": "2026/06/11",
    "trip_no": 1,
    "fish_raw": "ウマヅラハギ",
    "count_raw": "",
    "size_raw": "",
    "weight_raw": "",
    "tokki_raw": "外道",
    "point_raw": "千葉県 鴨川市 江見漁港",
    "kanso_raw": "黒ムツ・マダイ五目で出船今日も(^^)v(^^)v 美味しいお魚さんから入って、昨日のように爆釣ではなかったけど全員お刺身サイズ交じりでしっかりお土産釣れました。同じ場所でハチビキも釣れ、後半のマダイ五目は、マダイっ子とハナダイでトップは１０匹程度。今日もクーラーいっぱいです。美味しく食べてあげてくださいね(#^.^#)明日も黒ムツ・マダイ五目で出船しますのでご予約お待ちしております。ガラガラです(T_T)(T_T)",
    "suion_raw": "22.0℃",
    "suishoku_raw": "",
    "color_raw": "",
    "source": "chowari/新栄丸",
    "tide_label": "若潮",
    "weather_text": "曇り時々晴れ",
    "weather_detail": {
      "sunrise": "04:25",
      "sunset": "18:54",
      "moonrise": "00:55",
      "moonset": "14:30",
      "weather": "曇り時々晴れ",
      "temp_high": "27℃",
      "temp_low": "16℃",
      "pressure": "1012.2hPa",
      "wind_dir": "東南東",
      "wind_speed": "2.1m/s",
      "wave_dir": "南南東",
      "wave_height": "1.0m/s",
      "water_temp": "22.0℃",
      "tide": "若潮",
      "moon_age": "25.3",
      "bi": "10.0"
    }
  },
  {
    "ship": "新栄丸",
    "area": "江見",
    "date": "2026/06/11",
    "trip_no": 1,
    "fish_raw": "アカハタ",
    "count_raw": "",
    "size_raw": "",
    "weight_raw": "",
    "tokki_raw": "外道",
    "point_raw": "千葉県 鴨川市 江見漁港",
    "kanso_raw": "黒ムツ・マダイ五目で出船今日も(^^)v(^^)v 美味しいお魚さんから入って、昨日のように爆釣ではなかったけど全員お刺身サイズ交じりでしっかりお土産釣れました。同じ場所でハチビキも釣れ、後半のマダイ五目は、マダイっ子とハナダイでトップは１０匹程度。今日もクーラーいっぱいです。美味しく食べてあげてくださいね(#^.^#)明日も黒ムツ・マダイ五目で出船しますのでご予約お待ちしております。ガラガラです(T_T)(T_T)",
    "suion_raw": "22.0℃",
    "suishoku_raw": "",
    "color_raw": "",
    "source": "chowari/新栄丸",
    "tide_label": "若潮",
    "weather_text": "曇り時々晴れ",
    "weather_detail": {
      "sunrise": "04:25",
      "sunset": "18:54",
      "moonrise": "00:55",
      "moonset": "14:30",
      "weather": "曇り時々晴れ",
      "temp_high": "27℃",
      "temp_low": "16℃",
      "pressure": "1012.2hPa",
      "wind_dir": "東南東",
      "wind_speed": "2.1m/s",
      "wave_dir": "南南東",
      "wave_height": "1.0m/s",
      "water_temp": "22.0℃",
      "tide": "若潮",
      "moon_age": "25.3",
      "bi": "10.0"
    }
  },
  {
    "ship": "新栄丸",
    "area": "江見",
    "date": "2026/06/11",
    "trip_no": 1,
    "fish_raw": "ハチビキ",
    "count_raw": "",
    "size_raw": "",
    "weight_raw": "",
    "tokki_raw": "外道",
    "point_raw": "千葉県 鴨川市 江見漁港",
    "kanso_raw": "黒ムツ・マダイ五目で出船今日も(^^)v(^^)v 美味しいお魚さんから入って、昨日のように爆釣ではなかったけど全員お刺身サイズ交じりでしっかりお土産釣れました。同じ場所でハチビキも釣れ、後半のマダイ五目は、マダイっ子とハナダイでトップは１０匹程度。今日もクーラーいっぱいです。美味しく食べてあげてくださいね(#^.^#)明日も黒ムツ・マダイ五目で出船しますのでご予約お待ちしております。ガラガラです(T_T)(T_T)",
    "suion_raw": "22.0℃",
    "suishoku_raw": "",
    "color_raw": "",
    "source": "chowari/新栄丸",
    "tide_label": "若潮",
    "weather_text": "曇り時々晴れ",
    "weather_detail": {
      "sunrise": "04:25",
      "sunset": "18:54",
      "moonrise": "00:55",
      "moonset": "14:30",
      "weather": "曇り時々晴れ",
      "temp_high": "27℃",
      "temp_low": "16℃",
      "pressure": "1012.2hPa",
      "wind_dir": "東南東",
      "wind_speed": "2.1m/s",
      "wave_dir": "南南東",
      "wave_height": "1.0m/s",
      "water_temp": "22.0℃",
      "tide": "若潮",
      "moon_age": "25.3",
      "bi": "10.0"
    }
  }
]