[
  {
    "ship": "ふじ丸",
    "area": "戸田港",
    "date": "2026/06/07",
    "trip_no": 1,
    "fish_raw": "オオモンハタ",
    "count_raw": "",
    "size_raw": "",
    "weight_raw": "",
    "tokki_raw": "メイン",
    "point_raw": "静岡県 沼津市 戸田港",
    "kanso_raw": "根魚便。TOP10~3、ジグにめちゃめちゃ大きいオオモンハタ出ました！ アカハタもデカい！！ 初心者の方も沢山釣ってくれました!!! 仕掛けも餌も船で売ってます。 またよろしくお願いします レンタルタックルあり。",
    "suion_raw": "21.2℃",
    "suishoku_raw": "",
    "color_raw": "",
    "source": "chowari/ふじ丸",
    "tide_label": "小潮",
    "weather_text": "曇りのち一時雨",
    "weather_detail": {
      "sunrise": "04:30",
      "sunset": "18:57",
      "moonrise": "23:41",
      "moonset": "10:19",
      "weather": "曇りのち一時雨",
      "temp_high": "24℃",
      "temp_low": "19℃",
      "pressure": "1017.1hPa",
      "wind_dir": "東北東",
      "wind_speed": "1.7m/s",
      "wave_dir": "南南西",
      "wave_height": "0.3m/s",
      "water_temp": "21.2℃",
      "tide": "小潮",
      "moon_age": "21.3",
      "bi": "7.7"
    }
  },
  {
    "ship": "ふじ丸",
    "area": "戸田港",
    "date": "2026/06/07",
    "trip_no": 1,
    "fish_raw": "アカハタ",
    "count_raw": "",
    "size_raw": "",
    "weight_raw": "",
    "tokki_raw": "外道",
    "point_raw": "静岡県 沼津市 戸田港",
    "kanso_raw": "根魚便。TOP10~3、ジグにめちゃめちゃ大きいオオモンハタ出ました！ アカハタもデカい！！ 初心者の方も沢山釣ってくれました!!! 仕掛けも餌も船で売ってます。 またよろしくお願いします レンタルタックルあり。",
    "suion_raw": "21.2℃",
    "suishoku_raw": "",
    "color_raw": "",
    "source": "chowari/ふじ丸",
    "tide_label": "小潮",
    "weather_text": "曇りのち一時雨",
    "weather_detail": {
      "sunrise": "04:30",
      "sunset": "18:57",
      "moonrise": "23:41",
      "moonset": "10:19",
      "weather": "曇りのち一時雨",
      "temp_high": "24℃",
      "temp_low": "19℃",
      "pressure": "1017.1hPa",
      "wind_dir": "東北東",
      "wind_speed": "1.7m/s",
      "wave_dir": "南南西",
      "wave_height": "0.3m/s",
      "water_temp": "21.2℃",
      "tide": "小潮",
      "moon_age": "21.3",
      "bi": "7.7"
    }
  },
  {
    "ship": "ふじ丸",
    "area": "戸田港",
    "date": "2026/06/06",
    "trip_no": 1,
    "fish_raw": "マダイ",
    "count_raw": "",
    "size_raw": "",
    "weight_raw": "",
    "tokki_raw": "メイン",
    "point_raw": "静岡県 沼津市 戸田港",
    "kanso_raw": "午前便、本日はリクエストでタイラバ。底な定着したら、巻き巻き…マダイヒット。上がらなかったけど、もしかしたらマダイの当たりも有りました。 根魚便、TOP11~2。今日も40pu出ました！ そして、スペシャルゲストに真鯛!!! タイラバ、ルアー、ワーム、エサなんでも釣れます。今がチャンス、またよろしくお願いします。",
    "suion_raw": "21.5℃",
    "suishoku_raw": "",
    "color_raw": "",
    "source": "chowari/ふじ丸",
    "tide_label": "中潮",
    "weather_text": "曇り時々晴れ",
    "weather_detail": {
      "sunrise": "04:30",
      "sunset": "18:56",
      "moonrise": "23:14",
      "moonset": "09:18",
      "weather": "曇り時々晴れ",
      "temp_high": "26℃",
      "temp_low": "19℃",
      "pressure": "1015.7hPa",
      "wind_dir": "東北東",
      "wind_speed": "1.2m/s",
      "wave_dir": "南南西",
      "wave_height": "0.7m/s",
      "water_temp": "21.5℃",
      "tide": "中潮",
      "moon_age": "20.3",
      "bi": "9.0"
    }
  },
  {
    "ship": "ふじ丸",
    "area": "戸田港",
    "date": "2026/06/06",
    "trip_no": 1,
    "fish_raw": "ホウボウ",
    "count_raw": "",
    "size_raw": "",
    "weight_raw": "",
    "tokki_raw": "外道",
    "point_raw": "静岡県 沼津市 戸田港",
    "kanso_raw": "午前便、本日はリクエストでタイラバ。底な定着したら、巻き巻き…マダイヒット。上がらなかったけど、もしかしたらマダイの当たりも有りました。 根魚便、TOP11~2。今日も40pu出ました！ そして、スペシャルゲストに真鯛!!! タイラバ、ルアー、ワーム、エサなんでも釣れます。今がチャンス、またよろしくお願いします。",
    "suion_raw": "21.5℃",
    "suishoku_raw": "",
    "color_raw": "",
    "source": "chowari/ふじ丸",
    "tide_label": "中潮",
    "weather_text": "曇り時々晴れ",
    "weather_detail": {
      "sunrise": "04:30",
      "sunset": "18:56",
      "moonrise": "23:14",
      "moonset": "09:18",
      "weather": "曇り時々晴れ",
      "temp_high": "26℃",
      "temp_low": "19℃",
      "pressure": "1015.7hPa",
      "wind_dir": "東北東",
      "wind_speed": "1.2m/s",
      "wave_dir": "南南西",
      "wave_height": "0.7m/s",
      "water_temp": "21.5℃",
      "tide": "中潮",
      "moon_age": "20.3",
      "bi": "9.0"
    }
  },
  {
    "ship": "ふじ丸",
    "area": "戸田港",
    "date": "2026/06/06",
    "trip_no": 1,
    "fish_raw": "アカハタ",
    "count_raw": "",
    "size_raw": "",
    "weight_raw": "",
    "tokki_raw": "外道",
    "point_raw": "静岡県 沼津市 戸田港",
    "kanso_raw": "午前便、本日はリクエストでタイラバ。底な定着したら、巻き巻き…マダイヒット。上がらなかったけど、もしかしたらマダイの当たりも有りました。 根魚便、TOP11~2。今日も40pu出ました！ そして、スペシャルゲストに真鯛!!! タイラバ、ルアー、ワーム、エサなんでも釣れます。今がチャンス、またよろしくお願いします。",
    "suion_raw": "21.5℃",
    "suishoku_raw": "",
    "color_raw": "",
    "source": "chowari/ふじ丸",
    "tide_label": "中潮",
    "weather_text": "曇り時々晴れ",
    "weather_detail": {
      "sunrise": "04:30",
      "sunset": "18:56",
      "moonrise": "23:14",
      "moonset": "09:18",
      "weather": "曇り時々晴れ",
      "temp_high": "26℃",
      "temp_low": "19℃",
      "pressure": "1015.7hPa",
      "wind_dir": "東北東",
      "wind_speed": "1.2m/s",
      "wave_dir": "南南西",
      "wave_height": "0.7m/s",
      "water_temp": "21.5℃",
      "tide": "中潮",
      "moon_age": "20.3",
      "bi": "9.0"
    }
  },
  {
    "ship": "ふじ丸",
    "area": "戸田港",
    "date": "2026/06/05",
    "trip_no": 1,
    "fish_raw": "ムギイカ",
    "count_raw": "20～67匹",
    "size_raw": "",
    "weight_raw": "",
    "tokki_raw": "メイン",
    "point_raw": "静岡県 沼津市 戸田港",
    "kanso_raw": "ムギイカ便、ポツポツずーっと当たってました！ 風が強くてちょっとやりにくかったかな。 サイズもそこそこ大きくて釣ってて楽しいです。 またよろしくお願いします。",
    "suion_raw": "21.5℃",
    "suishoku_raw": "",
    "color_raw": "",
    "source": "chowari/ふじ丸",
    "tide_label": "中潮",
    "weather_text": "曇り",
    "weather_detail": {
      "sunrise": "04:30",
      "sunset": "18:56",
      "moonrise": "22:45",
      "moonset": "08:18",
      "weather": "曇り",
      "temp_high": "26℃",
      "temp_low": "19℃",
      "pressure": "1008.8hPa",
      "wind_dir": "東北東",
      "wind_speed": "4.8m/s",
      "wave_dir": "南南西",
      "wave_height": "0.5m/s",
      "water_temp": "21.5℃",
      "tide": "中潮",
      "moon_age": "19.3",
      "bi": "9.7"
    }
  },
  {
    "ship": "ふじ丸",
    "area": "戸田港",
    "date": "2026/06/05",
    "trip_no": 2,
    "fish_raw": "アカハタ",
    "count_raw": "5～16匹",
    "size_raw": "",
    "weight_raw": "",
    "tokki_raw": "メイン",
    "point_raw": "静岡県 沼津市 戸田港",
    "kanso_raw": "根魚便、活性もよくあたりも多くて楽しかったです!! 風があって釣りにくかったけど頑張ってくれました。 またよろしくお願いします。",
    "suion_raw": "21.5℃",
    "suishoku_raw": "",
    "color_raw": "",
    "source": "chowari/ふじ丸",
    "tide_label": "中潮",
    "weather_text": "曇り",
    "weather_detail": {
      "sunrise": "04:30",
      "sunset": "18:56",
      "moonrise": "22:45",
      "moonset": "08:18",
      "weather": "曇り",
      "temp_high": "26℃",
      "temp_low": "19℃",
      "pressure": "1008.8hPa",
      "wind_dir": "東北東",
      "wind_speed": "4.8m/s",
      "wave_dir": "南南西",
      "wave_height": "0.5m/s",
      "water_temp": "21.5℃",
      "tide": "中潮",
      "moon_age": "19.3",
      "bi": "9.7"
    }
  },
  {
    "ship": "ふじ丸",
    "area": "戸田港",
    "date": "2026/06/05",
    "trip_no": 2,
    "fish_raw": "カサゴ",
    "count_raw": "",
    "size_raw": "",
    "weight_raw": "",
    "tokki_raw": "外道",
    "point_raw": "静岡県 沼津市 戸田港",
    "kanso_raw": "根魚便、活性もよくあたりも多くて楽しかったです!! 風があって釣りにくかったけど頑張ってくれました。 またよろしくお願いします。",
    "suion_raw": "21.5℃",
    "suishoku_raw": "",
    "color_raw": "",
    "source": "chowari/ふじ丸",
    "tide_label": "中潮",
    "weather_text": "曇り",
    "weather_detail": {
      "sunrise": "04:30",
      "sunset": "18:56",
      "moonrise": "22:45",
      "moonset": "08:18",
      "weather": "曇り",
      "temp_high": "26℃",
      "temp_low": "19℃",
      "pressure": "1008.8hPa",
      "wind_dir": "東北東",
      "wind_speed": "4.8m/s",
      "wave_dir": "南南西",
      "wave_height": "0.5m/s",
      "water_temp": "21.5℃",
      "tide": "中潮",
      "moon_age": "19.3",
      "bi": "9.7"
    }
  },
  {
    "ship": "ふじ丸",
    "area": "戸田港",
    "date": "2026/06/05",
    "trip_no": 2,
    "fish_raw": "オオモンハタ",
    "count_raw": "",
    "size_raw": "",
    "weight_raw": "",
    "tokki_raw": "外道",
    "point_raw": "静岡県 沼津市 戸田港",
    "kanso_raw": "根魚便、活性もよくあたりも多くて楽しかったです!! 風があって釣りにくかったけど頑張ってくれました。 またよろしくお願いします。",
    "suion_raw": "21.5℃",
    "suishoku_raw": "",
    "color_raw": "",
    "source": "chowari/ふじ丸",
    "tide_label": "中潮",
    "weather_text": "曇り",
    "weather_detail": {
      "sunrise": "04:30",
      "sunset": "18:56",
      "moonrise": "22:45",
      "moonset": "08:18",
      "weather": "曇り",
      "temp_high": "26℃",
      "temp_low": "19℃",
      "pressure": "1008.8hPa",
      "wind_dir": "東北東",
      "wind_speed": "4.8m/s",
      "wave_dir": "南南西",
      "wave_height": "0.5m/s",
      "water_temp": "21.5℃",
      "tide": "中潮",
      "moon_age": "19.3",
      "bi": "9.7"
    }
  },
  {
    "ship": "ふじ丸",
    "area": "戸田港",
    "date": "2026/06/05",
    "trip_no": 2,
    "fish_raw": "エソ",
    "count_raw": "",
    "size_raw": "",
    "weight_raw": "",
    "tokki_raw": "外道",
    "point_raw": "静岡県 沼津市 戸田港",
    "kanso_raw": "根魚便、活性もよくあたりも多くて楽しかったです!! 風があって釣りにくかったけど頑張ってくれました。 またよろしくお願いします。",
    "suion_raw": "21.5℃",
    "suishoku_raw": "",
    "color_raw": "",
    "source": "chowari/ふじ丸",
    "tide_label": "中潮",
    "weather_text": "曇り",
    "weather_detail": {
      "sunrise": "04:30",
      "sunset": "18:56",
      "moonrise": "22:45",
      "moonset": "08:18",
      "weather": "曇り",
      "temp_high": "26℃",
      "temp_low": "19℃",
      "pressure": "1008.8hPa",
      "wind_dir": "東北東",
      "wind_speed": "4.8m/s",
      "wave_dir": "南南西",
      "wave_height": "0.5m/s",
      "water_temp": "21.5℃",
      "tide": "中潮",
      "moon_age": "19.3",
      "bi": "9.7"
    }
  },
  {
    "ship": "ふじ丸",
    "area": "戸田港",
    "date": "2026/06/05",
    "trip_no": 2,
    "fish_raw": "ベラ",
    "count_raw": "",
    "size_raw": "",
    "weight_raw": "",
    "tokki_raw": "外道",
    "point_raw": "静岡県 沼津市 戸田港",
    "kanso_raw": "根魚便、活性もよくあたりも多くて楽しかったです!! 風があって釣りにくかったけど頑張ってくれました。 またよろしくお願いします。",
    "suion_raw": "21.5℃",
    "suishoku_raw": "",
    "color_raw": "",
    "source": "chowari/ふじ丸",
    "tide_label": "中潮",
    "weather_text": "曇り",
    "weather_detail": {
      "sunrise": "04:30",
      "sunset": "18:56",
      "moonrise": "22:45",
      "moonset": "08:18",
      "weather": "曇り",
      "temp_high": "26℃",
      "temp_low": "19℃",
      "pressure": "1008.8hPa",
      "wind_dir": "東北東",
      "wind_speed": "4.8m/s",
      "wave_dir": "南南西",
      "wave_height": "0.5m/s",
      "water_temp": "21.5℃",
      "tide": "中潮",
      "moon_age": "19.3",
      "bi": "9.7"
    }
  }
]